Workbook

Sheet 00_คู่มือ
A1: คู่มือใช้งานไฟล์ THAI-RAP Excel Template สำหรับกรอกและสรุปข้อมูลร้าน 50 ร้าน
A2: ขั้นตอน | B2: วิธีใช้งาน
A3: 1 | B3: กรอกข้อมูลร้านในชีต 01_ข้อมูลร้าน
A4: 2 | B4: กรอกคะแนน 0-4 ในชีต 02_ประเมิน50ร้าน ช่อง Q1-Q50
A5: 3 | B5: ดูสรุปใน 03_สรุปคะแนน และ 04_Dashboard
A6: 4 | B6: ดูคำถามเต็มและหลักฐานใน 05_QuestionMaster
A7: 5 | B7: Red Flag = ข้อที่ได้คะแนน 0-1
A9: คะแนน | B9: ระดับ | C9: ความหมาย
A10: 0 | B10: ไม่มีเลย | C10: ไม่มีการดำเนินการ/ไม่มีหลักฐาน
A11: 1 | B11: มีบ้าง | C11: ทำบางส่วนแต่ไม่เป็นระบบ
A12: 2 | B12: พื้นฐาน | C12: มีวิธีทำพื้นฐาน
A13: 3 | B13: ดี | C13: เป็นระบบ มีหลักฐาน
A14: 4 | B14: ดีมาก | C14: วัดผลและต่อยอดได้
A16: แหล่งอ้างอิง | B16: รายละเอียด
A17: THAI-RAP_แบบฟอร์มประเมินร้าน_50ข้อ_Manual(3).pdf | B17: ใช้เป็นแบบฟอร์มภาคสนามและรายการประเมิน
A18: THAI-RAP_รายละเอียดแบบประเมินร้าน_50ข้อ_และคู่มือเก็บข้อมูล(2).pdf | B18: ใช้เป็นคู่มือมิติ น้ำหนัก เกณฑ์คะแนน หลักฐาน และ Red Flag

Sheet 01_ข้อมูลร้าน
A1: รหัสร้าน | B1: ชื่อร้าน | C1: จังหวัด | D1: อำเภอ/ตำบล | E1: ประเภทร้าน | F1: เจ้าของ/ผู้ให้ข้อมูล | G1: โทรศัพท์ | H1: ช่องทางขายหลัก | I1: ยอดขายเฉลี่ย/วัน | J1: ยอดขายเฉลี่ย/เดือน | K1: เมนูขายดี 1 | L1: เมนูขายดี 2 | M1: เมนูขายดี 3 | N1: ต้นทุนวัตถุดิบ/เดือน | O1: ค่าแรง/เดือน | P1: ค่าเช่า/ค่าใช้จ่ายประจำ | Q1: กำไรประมาณการ/เดือน | R1: ปัญหาหลัก 3 ข้อ | S1: ด้านสังคม | T1: ด้านสิ่งแวดล้อม | U1: เป้าหมาย 3-6 เดือน | V1: รอบประเมิน | W1: วันที่ประเมิน | X1: ชื่อผู้ประเมิน | Y1: หมายเหตุ
A2: RAP69-001 | B2: Seed restaurant | R2: 1.ร้านมีระบบอยู่ได้ด้วยตัวเอง ( staff training, system, etc.) 2.มี 2 ready-to-products ออกมา ( คง concept วัตถุดิบจากชุมชน ) 3.เพิ่มเมนู สร้างเมนู signature 4.เพิ่มความพร้อมในการให้บริการจนสามารถเปิดดำเนินการได้ทุกวั | S2: ทำอยู่แล้ว supplier (อาหาร) ปัจจุบันเป็นคนในชุมชน 100% + มี consignment นำ product ชุมชนมาวาง แต่ ณ ตอนนี้ยังไม่ได้มีแพลนจะเพิ่มอะไรในด้านนี้ อยากโฟกัสไปกับการวางระบบร้านก่อน | T2: โดยปัจจุบันร้าน concern เรื่องนี้อยู่แล้ว ด้วย concept บรรจุภัณฑ์ถ้า take-away ใช้เป็นกล่องกระดาษ - แก้วกระดาษ ตอนทิ้งขยะมีแยก พลาสติก,ขวดแก้ว, ขยะเปียก (ในชุมชนตรงนั้นมีที่ทิ้งขยะแยกประเภทอย่างละเอียด) | U2: สร้างระบบเทรนนิ่งให้ร้านรันได้ด้วยตัวเองเพื่อความสุขและเวลาชีวิตที่สมดุล ควบคู่การเพิ่มเมนู Signature และคลอด 2 ผลิตภัณฑ์พร้อมทาน โดยมุ่งเน้นการใช้วัตถุดิบและสนับสนุน Supplier ในชุมชน 100% พร้อมคงเจตนารมณ์รักษ์โลกผ่านการแยกขยะและใช้บรรจุภัณฑ์ที่เป็นมิตรต่อสิ่งแวดล้อมอย่างยั่งยืนในปี 2026 | V2: T0
A3: RAP69-002 | B3: ก๋วยเตี๋ยวเรือคุณปุ๊ก | V3: T0
A4: RAP69-003 | B4: บ้าน-บ้าน สุขพอดี | R4: 1.สร้างมาตรฐานการบริการและการประกอบอาหารในแบบฉบับบ้าน-บ้าน สุขพอดี 2.พัฒนาเมนูเด่นจากสวนและเมนูประจำถิ่น เชื่อมโยงการปลูก การปรุง และการเรียนรู้ให้เกื้อหนุนกัน 3.สร้างการรับรู้ให้ผู้คนนึกถึงบ้าน-บ้าน สุขพอดี เมื่อต้องการประสบการณ์ "ดม เด็ด ปรุง จริง" 4.พัฒนาระบบสมาชิกและกิจกรรมต่อเนื่อง เพื่อสร้างการกลับมาเรียนรู้และเติบโตร่วมกัน 5.ยกระดับไซรัปมะพร้าวสู่สินค้าซิกเนเจอร์ ที่สะท้อนคุณค่าจากทรัพยากรและภูมิปัญญาในพื้นที่ | S4: มุ่งเป็นต้นแบบของพื้นที่แห่งอาหาร การเรียนรู้ และการใช้ชีวิตที่เกื้อกูลกัน เชื่อมโยง "สวนสู่ครัว ครัวสู่ชีวิต" ผ่านวัตถุดิบจากธรรมชาติ ภูมิปัญญาท้องถิ่น และประสบการณ์ "ดม เด็ด ปรุง จริง" เพื่อสร้างคุณค่าร่วมทางเศรษฐกิจ สังคม และสิ่งแวดล้อม พร้อมส่งต่อความสุข ความหมาย และความยั่งยืนให้แก่ผู้คน ชุมชน และโลกใบนี้ | U4: ขับเคลื่อนอัตลักษณ์ 'สวนสู่ครัว ครัวสู่ชีวิต' ผ่านมาตรฐานบริการ เมนูถิ่น และประสบการณ์ 'ดม เด็ด ปรุง จริง' ควบคู่การรุกตลาดเพื่อสร้างรายได้รวมในปี 2569 กว่า 900,000 บาท บนฐานคิดการพึ่งพาธรรมชาติและภูมิปัญญาท้องถิ่น มุ่งเป็นต้นแบบพื้นที่อาหารและการเรียนรู้ที่เกื้อกูลสิ่งแวดล้อม พร้อมส่งต่อความสุขและความยั่งยืนให้กับผู้คน ชุมชน และโลกใบนี้ | V4: T0
A5: RAP69-004 | B5: แฟรนไชส์ก๋วยเตี๋ยวปากหม้อแม่ว่าดี | V5: T0
A6: RAP69-005 | B6: 16Brix Melon Farm&Café | R6: 1.เพิ่มยอดขายในส่วนคาเฟ่ ให้มีรายรับเฉลี่ย 250,000 บาทต่อเดือน ที่กำไรสุทธิ 25% โดยมีผลิตภัณฑ์หลักดังนี้ -เมล่อนผล (online&offline) -อาหาร น้ำ -ของฝาก *รวมถึงโอกาสสเกลสาขาเพิ่มยอดขายในสถานที่ที่น่าสนใจ (มองพื้นที่ประเภทกลุ่ม Healthcare) 2.ทำผลิตภัณฑ์ที่มีโอกาสเข้าสู่ตลาดใหญ่ได้ และเสกลได้ เพื่อเพิ่มรายรับแบบก้าวกระโดด (หลักล้านบาท) - ก้านไม้หอม กลิ่นเมล่อน (มีสินค้าแล้ว ผลิตโดย วว. ขายทาง online&offline อยู่) - แยมเมล่อน (ทดลองขาย offline อยู่ แต่อยากได้เทคโนโลยียืดอายุ) - Melon Apply Cyder เปลือกเมล่อนลอยแก้ว (ต้นทุนต่ำเนื่องจากเป็น Byproduct ทดลองขายอยู่ แต่อยากพัฒนาแพคเกจ และเทคนิคการยืดอายุ 3.เพิ่มการรับรู้แบรนด์ และเปลี่ยน traffic เป็น income ไปสู่เป้าหมายข้อ 1&2 4.เซทระบบให้งานทุกส่วนรันได้แม้ไม่มีตัวเจ้าของอยู่ | S6: ทางสังคมเรามีการใช้วัตถุดิบในพื้นที่ - เมล่อนปลูกเอง - แรงงานท้องถิ่น - เมล็ดกาแฟ แป้งพิซซ๋า จากกลุ่ม YEC นครนายก - ผักสลัดจากฟาร์มใกล้เคียง | T6: ด้านสิ่งแวดล้อม - ทางฟาร์มใช้โซล่าเซลในส่วนการปลูก - ออกแบบเมนูจาก Byproduct เช่นเปลือกทำลอยแก้ว ผิวเปลือกมีส่งให้น้องที่ม.ศีรนครินทำวิจัย | U6: เซ็ตระบบคาเฟ่ให้รันอัตโนมัติเพื่อยอดขาย 250,000 บาทต่อเดือน ควบคู่การปั้นและยืดอายุผลิตภัณฑ์เมล่อนนวัตกรรมสู่ตลาดใหญ่ในปี 2026 บนฐานความยั่งยืนที่ใช้พลังงานโซล่าเซลล์และขับเคลื่อนครัวแบบไร้ขยะด้วยการแปรรูป Byproduct พร้อมเกื้อกูลสังคมผ่านการจ้างงานและกระจายรายได้สู่เครือข่ายเกษตรกรท้องถิ่นอย่างมั่นคง | V6: T0
A7: RAP69-006 | B7: ร้านอีสานเฮาส์ (304 ปราจีนบุรี) | R7: เป้าหมายทางธุรกิจ : เพิ่มยอดขายให้ได้เดือนละ 5 ล้านบาทต่อเดือน โดยทำร้านให้เป็นห้องรับแขกของจังหวัดปราจีนบุรีให้ได้ - เป็นแลนด์มาร์กของปราจีนบุรี - เป็นร้านที่บริษัท โรงงานต่างๆ และหน่วยงานราชการ เลือกใช้การจัดเลี้ยง ประชุม สัมมนา - เป็นร้านที่คนในพื้นที่อยากพาครอบครัวมาทานอาหารหรือเลี้ยงฉลองในวันสำคัญ - เป็นร้านที่ต้องแวะสำหรับคนที่เดินทางผ่านถนน 304 | S7: เป้าหมายทางสังคม : ร้านอีสานเฮาส์จะเป็นร้านที่ทำให้คนปราจีนบุรีภูมิใจ โดยสร้างงานให้คนในท้องถิ่นได้มีอาชีพ - มีรับนักศึกษาฝึกงานมาฝึกทำอาหารและสร้างเส้นทางความก้าวหน้าในอาชีพ - มีการสนับสนุนเกษตรกรในท้องถิ่น และซื้อวัตถุดิบจากชุมชน ให้ชาวบ้านมีรายได้ เช่น หน่อไม้ไผ่ตง, กุ้งฝอยจากชาวบ้านที่หามาจากแม่น้ำปราจีนบุรี, ปูนาจากชาวบ้านที่ไปขุดจากทุ่งนา เพื่อทำให้ร้านอีสานเฮาส์ไม่ใช่แค่ร้านอาหาร แต่เป็นส่วนหนึ่งของคนจังหวัดปราจีนบุรี | T7: ป้าหมายด้านสิ่งแวดล้อม : ต้องการลดขยะอาหาร และสามารถนำขยะที่เหลือไปใช้ประโยชน์ต่อได้ เช่น ชาวบ้านนำไปเลี้ยงสัตว์ หรือแปรรูปให้เป็นปุ๋ยต่อไป - ส่งเสริมให้ลูกค้านำภาชนะมาใส่เครื่องดื่มเอง แล้วลดราคาเครื่องดื่ม (ตอนนี้ทำอยู่) - สร้างพื้นที่สีเขียว โดยปลูกสวนสมุนไพร ใช้พื้นที่ร้านเป็นแหล่งเรียนรู้เล็กๆ | U7: ปั้นอีสานเฮาส์สู่ห้องรับแขกและแลนด์มาร์กของปราจีนบุรีเพื่อสร้างยอดขาย 5 ล้านบาทต่อเดือน บนฐานความสุขที่เจ้าของร้านมีระบบบริหารจนมีเวลาให้ครอบครัวและพนักงานเติบโตอย่างมั่นคง ควบคู่การสร้างงาน อุดหนุนวัตถุดิบชุมชนอย่างหน่อไม้ไผ่ตงและกุ้งฝอย ตลอดจนจัดการขยะอาหารเพื่อเลี้ยงสัตว์ ทำปุ๋ย และเพิ่มพื้นที่สีเขียวอย่างยั่งยืน | V7: T0
A8: RAP69-007 | B8: ร้านคำนิยม | R8: 5 เป้าหมาย ปี 2569 1.เพิ่มยอดขายรวม 30% 2.พัฒนาระบบมาตรฐานร้านอาหาร (SOP) ครบ 100% 3.ลดต้นทุนอาหาร (FOOD COST) ให้ต่ำกว่า 35% 4.สร้างฐานลูกค้าประจำ 1,000 คน 5.ยกระดับแบรนด์ "คำนิยม" ให้เป็นอาหารที่รับจัดเลี้ยงในและนอกสถานที่ อันดับต้นในพื้นที่ | S8: ใช้ผักและวัตถุดิบท้องถิ่นจากชาวบ้านในพื้นที่เพิ่มขึ้น โดยเฉพาะวัตถุดิบตามฤดูกาล | T8: แยกขยะโดยเฉพาะขยะเศษอาหาร ให้สามารถนำไปทำปุ๋ยหรือใช้เป็นอาหารสัตว์ได้ | U8: พุ่งเป้าเพิ่มยอดขายรวม 30% และลด Food Cost ให้ต่ำกว่า 35% ควบคู่การวางระบบ SOP ครบ 100% เพื่อยกระดับแบรนด์ 'คำนิยม' สู่อันดับต้นของธุรกิจจัดเลี้ยงในปี 2569 บนฐานความสุขที่เจ้าของร้านมีเวลาชีวิตที่สมดุลและพนักงานเติบโตอย่างมีพลัง พร้อมสร้างคุณค่าร่วมกับชุมชนผ่านการใช้ผักและวัตถุดิบตามฤดูกาลในพื้นที่ และจัดการแยกขยะเศษอาหารเพื่อหมุนเวียนประโยชน์กลับสู่สิ่งแวดล้อมอย่างยั่งยืน | V8: T0
A9: RAP69-008 | B9: ร้านอรวรรณบ้านเพ | V9: T0
A10: RAP69-009 | B10: ครัวเดอมอง | V10: T0
A11: RAP69-010 | B11: เรือนไทย พัทยา | V11: T0
A12: RAP69-011 | B12: ร้านอาหาร ทะเลลานโพธิ์ ซีฟู้ด | S12: ผลักดันซีฟู้ดท้องถิ่นกลุ่มหมู่บ้านชาวประมง พ่อค้าเเม่ค้า เมืองพัทยา จังหวัดชลบุรี ออกสู่ตลาดระดับประเทศเเละต่างประเทศให้เป็นที่รู้จัก และดึงดูดนักท่องเที่ยวทั้งชาวไทย เเละชาวต่างชาติ เข้ามาในชุมชน สร้างความเจริญและสร้างรายได้สู่ชุมชน เเละเมืองพัทยา | U12: ยกระดับซีฟู้ดพัทยาสู่แบรนด์ของฝากพรีเมียมด้วยนวัตกรรมและระบบ SOP เพื่อโตรายได้ 25% ปี 2569 บนฐานความสุขที่ได้ส่งมอบความปลอดภัยจนลูกค้ากลายเป็นเพื่อน ควบคู่การลดขยะวัตถุดิบ 10% และผลักดันผลผลิตประมงพื้นบ้านสู่สากลเพื่อสร้างรายได้กลับคืนสู่ชุมชนอย่างยั่งยืน | V12: T0
A13: RAP69-012 | B13: นายกุ่ยไก่หุบบอน @เขาชีจรรย์ | R13: 1. การขยายสาขาเพิ่มการเติบโต 2. เพิ่มเทคโนโลยีเข้ามามีส่วนร่วมในการจัดการ 3. การเพิ่มช่องทางรายได้ใหม่ 4. การจัดการต้นทุน | S13: นำไก่หุบบอน ไก่พื้นเมืองชลบุรี ออกสู่ตลาดระดับประเทศ ให้เป็นที่รู้จัก และดึงดูดนักท่องเที่ยว เข้ามาในชุมชน สร้างความเจริญและสร้างรายได้สู่ชุมชน | U13: สปีดการเติบโตด้วยสาขาพัทยา ระบบแฟรนไชส์ และไก่สับแช่แข็งบุกโมเดิร์นเทรดด้วยระบบ SOP คุมต้นทุนปี 2569 บนฐานความสุขที่ได้ทำสิ่งที่รักและส่งมอบความอร่อยสะอาดจนลูกค้ากลายเป็นเพื่อน ควบคู่การผลักดันไก่พื้นเมืองชลบุรีสู่ระดับประเทศเพื่อดึงดูดนักท่องเที่ยวและสร้างรายได้กลับคืนสู่ชุมชน | V13: T0
A14: RAP69-013 | B14: บ้านสวนบางแสน | V14: T0
A15: RAP69-014 | B15: สวนแววอรุณ | R15: หลังจากกลับมาจากงาน THAI-RAP ผมมาวิเคระห์สถานการณ์เศรษฐกิจ เลยสรุปว่าปีนี้เราจะไม่โฟกัสการไล่ยอดขายครับ แต่จะโฟกัสการสร้างระบบ เพราะเมื่อระบบแข็งแรง ยอดขายจะเป็นผลลัพธ์ที่ตามมาเองเป้าหมายสำคัญของสวนแววอรุณในปี 2569 คือ การจัดทำ SOP ให้ครบทุกแผนก เพื่อเปลี่ยนการทำงานที่พึ่งพาประสบการณ์ของแต่ละคน ให้กลายเป็นมาตรฐานขององค์กร โดยครอบคลุม SOP การจัดเตรียมวัตถุดิบ SOP การปรุงอาหารและมาตรฐานสูตรอาหาร SOP ร้านอาหารและการบริการลูกค้า SOP คาเฟ่และเครื่องดื่ม SOP ที่พัก SOP ลานกางเต็นท์ SOP กิจกรรมและความปลอดภัย SOP การตลาดและการสื่อสารกับลูกค้า SOP งานบริหารและการควบคุมต้นทุน เป้าหมายของเราไม่ใช่เพียงทำให้พนักงานทำงานตามขั้นตอน แต่เพื่อสร้างองค์กรที่สามารถรักษาคุณภาพ มาตรฐาน และประสบการณ์ของลูกค้าได้อย่างสม่ำเสมอ | S15: ด้านสังคม เราให้พื้นที่ชุมชน เข้ามาใช้พื้นที่ของเราจัดกิจกรรมมากขึ้น เช่น เราให้.ศกร.ใช้พื้นที่ตั้งห้องสมุดชุมชน มุมหนังสือประชาชน | T15: ด้านสิ่งแวดล้อม - รักษาพื้นที่สีเขียวและระบบนิเวศภายในสวน และมีการขยายการปลูกต้นไม้และพันธุ์ไม้ป่าในพื้นที่อีก 10 ไร่ - เพิ่มการใช้วัสดุที่เป็นมิตรต่อสิ่งแวดล้อม - พัฒนาระบบจัดการขยะและเศษอาหารให้เกิดประโยชน์สูงสุด โดยปัจจุบัน เราร่วมกับทีมงานวิจัยที่นำเศษอาหารไปทำเป็นอาหารเลี้ยงหนอนเพื่อใช้เป็นแหล่งโปรตีนสัตว์ทดแทนการนำเข้าถั่วเหลืองเป็นต้น - ในช่วงต้นปีที่ผ่านมา เราเพิ่งติดตั้งพลังงานแสงอาทิตย์เพื่อใช้เป็นพลังงานสะอาด | U15: สร้างระบบ SOP ครบทุกแผนกเพื่อยกระดับมาตรฐานบริการและประสบการณ์ของลูกค้าอย่างสม่ำเสมอโดยไม่พึ่งพาบุคคลในปี 2569 บนฐานคิดการเติบโตอย่างมีสติที่โฟกัสระบบก่อนยอดขาย ควบคู่การขยายพื้นที่ป่าสีเขียว 10 ไร่ ใช้พลังงานแสงอาทิตย์ และจัดการขยะเศษอาหารสู่นวัตกรรมอาหารหนอนโปรตีนเพื่อสิ่งแวดล้อม พร้อมเปิดพื้นที่สร้างคุณค่าให้สังคมด้วยการเป็นแหล่งเรียนรู้และห้องสมุดสำหรับชุมชนอย่างยั่งยืน | V15: T0
A16: RAP69-015 | B16: คุณอี๊ดกะเพราแซ่บจี้ด | V16: T0
A17: RAP69-016 | B17: หมูสะเต๊ะอพอลโล | V17: T0
A18: RAP69-017 | B18: วันวาน คาเฟ่ | V18: T0
A19: RAP69-018 | B19: อิ่มอุ่น ณ พัทยา | R19: 1.จัดการระบบ ของพัทยา เพื่อเตรียมขยายสาขาไปกทม. 2.ทำระบบสมาชิก เพื่อให้ลูกค้าเก่ามาใช้บริการซ้ำ/ ให้ระบบหลังบ้านรับทราบข้อมูล ไม่ใช่เพียงจำหน้าลูกค้าได้ 3.ปรับทัศนคติ น้องบริการ ให้ยิ้มเเย้วและกล่าวต้อนรับ-ขอบคุณลูกค้า 4. ทำมุมเช็คอิน 5. จัดทำผลิตภัณเเช่เเข็งเสี่ยวหลงเปา(จากเมนูที่ติดลำดับขายดี) ให้ลูกค้าซื้อกลับ 6. ทำระบบให้ลูกคอมเพลน ผ่าน google form เพื่อเปิดฟังความคิดเห็นลูกค้ามากขึ้น | S19: 1.ทางร้านสนับสนุน ของใช้พื้นบ้านจักรสาร ที่ใช้ตกแต่งร้านจากชุมชน ในจังหวัดชลบุรร 2.การสนับสนุนประมงพื้นบ้าน ทางร้านใช้วัสดุดิบอาหารทะเลในท้องถิ่น | T19: 1.ทำระบบ SOP ล็อกมาตรฐานเมนูเด็ดและควบคุม Food Cost ช่วยลดขยะที่เกิดจากอาหารเหลือทิ้ง 2.สำหรับสินค้าแช่แข็ง ในแผนการพัฒนาผเสี่ยวหลงเปาแช่แข็ง เราจะศึกษาและเลือกใช้บรรจุภัณฑ์ | U19: จัดระบบสาขาของพัทยารองรับการขยายสาขาสู่ กทม. ทำระบบสมาชิก และปั้นเสี่ยวหลงเปาแช่แข็งปี 2026 บนฐานความสุขที่เห็นแบรนด์อิ่มอุ่นเติบโตต่อเนื่องและสร้างความอร่อยให้ทุกครอบครัว ควบคู่การลดขยะอาหารด้วย SOP คุมต้นทุน ตลอดจนอุดหนุนงานจักสานและใช้วัตถุดิบซีฟู้ดจากประมงพื้นบ้านชลบุรีเพื่อขับเคลื่อนเศรษฐกิจชุมชน | V19: T0
A20: RAP69-019 | B20: ร้านอาหารบ่อทองบุรี | R20: 1. แผนยกระดับมาตรฐานการบริการ และอัตลักษณ์อาหาร เป้าหมาย : จัดทำเล่มเมนูใหม่ที่รองรับกลุ่มลูกค้าต่างชาติ ควบคู่ไปกับการพัฒนาศิลปะการจัดจาน เพื่อเพิ่มมูลค่าและความน่าสนใจให้แก่อาหาร แนวทางการดำเนินงาน : ออกแบบและจัดทำเล่มเมนูใหม่ 3 ภาษา (ไทย, อังกฤษ, จีน) เพื่อให้ครอบคลุมและตอบโจทย์การบริการอย่างเป็นสากล คัดเลือกและปรับปรุงภาชนะใส่อาหารชุดใหม่ ให้มีความสวยงามและเข้ากับอัตลักษณ์ของแต่ละเมนู กรอบเวลา : ดำเนินการควบคู่กันให้แล้วเสร็จภายใน 3 เดือน กันยายน 2569 2. แผนพัฒนาประสิทธิภาพระบบครัวและการบริหารจัดการ เป้าหมาย: พัฒนาทักษะบุคลากรและจัดวางระบบบริหารจัดการวัตถุดิบภายในครัวเพื่อลดความสูญเสีย (Food Waste) และเตรียมความพร้อมรองรับฤดูกาลท่องเที่ยวแนวทางการดำเนินงาน : จัดอบรมและพัฒนาทักษะการบริหารจัดการครัว การควบคุมมาตรฐานรสชาติ และการจัดการสต็อกวัตถุดิบอย่างเป็นระบบ กรอบเวลา : ดำเนินการในช่วง กรกฏาคมสิงหาคม 2569 เลือกช่วง Low Season ที่ปริมาณงานหน้าร้านลดลง เพื่อให้บุคลากรโฟกัสกับการพัฒนาได้อย่างเต็มที่ 3. แผนพัฒนาผลิตภัณฑ์นวัตกรรมอาหารและมาตรฐาน อย. เป้าหมาย : พัฒนา "พริกแกงปรุงสำเร็จ" สู่การเป็นของฝากระดับพรีเมี่ยมที่ตอบโจทย์เทรนด์คนรักสุขภาพ พร้อมยกระดับโรงเรือนผลิตให้ผ่านการรับรองมาตรฐาน อย. แนวทางการดำเนินงาน ด้านตัวผลิตภัณฑ์ : ปรับสูตรพริกแกงสำเร็จรูปให้เป็นทางเลือกเพื่อสุขภาพ เช่น การลดโซเดียม ลดน้ำตาล หรือใช้สิ่งทดแทนเพื่อสุขภาพ โดยยังคงรักษาอัตลักษณ์ รสชาติ และสีสันดั้งเดิมของอาหารไทยไว้ ด้านบรรจุภัณฑ์ : พัฒนา Packaging ใหม่ให้มีความสวยงาม ดึงดูดสายตา และสะท้อนคุณค่าความเป็นของฝากพรีเมี่ยมด้านมาตรฐานการผลิต : ดำเนินการจัดตั้งโรงเรือนผลิต (ปัจจุบันโครงสร้างอาคารเสร็จสมบูรณ์แล้ว) โดยจะติดตั้งเครื่องผัด เครื่องบรรจุ และระบบที่เกี่ยวข้อง พร้อมยื่นเอกสารตรวจประเมินเพื่อรับรองมาตรฐาน อย. กรอบเวลา : ดำเนินการติดตั้งระบบโรงเรือนและยื่นตรวจประเมิน อย. ให้แล้วเสร็จภายใน ตุลาคม - พฤษจิกายน 2026 ขึ้นอยู่กับการอนุมัตของ อย. | S20: 1.ปล่อยปลาประจำเดือน ที่อ่างเก็บน้ำคลองหลวงรัชโลทร 2.ถวายภัตรตราหารพระประจำเดือน 3.การมอบข้าวสาร และเลี้ยงอาหารกลางวันเด็ก ประจำ 4.กิจกรรมผูกเสี่ยว ดำนา เกี่ยวข้าว ประจำทุกปี 5.กิจกรรมปลูกป่าชุมชนเพื่อการเรียนรู้ ประจำทุกปี 6.กิจกรรมวันสงกรานต์ รดน้ำขอพรผู้ใหญ่ การกวนข้าวเหนียวแดง ประจำทุกปี 7..สนับสนุนกิจกรรมของชุมชน อำเภอ ทุกงาน ไม่ว่าจะเป็น งานบุญกลางบ้าน งานแม่ศรีผีกระดง งานพ่อพญาเร่ งานประกวดสาวงาม 8.มีศูนย์โอทอป สนับสนุนพื้นที่และพนักงานขายให้ฟรี 9.การประชุมสัมมนาและงานแต่ง จะใช้เบรคเป็นขนมจากภายในชุมชน เป็นขนมไทย ขนมพื้นบ้าน | U20: ยกระดับเมนูและศิลปะการจัดจานสู่สากล ควบคู่กับการเป็นครัวไร้ขยะ (Zero Food Waste) และพัฒนาพริกแกงเพื่อสุขภาพมาตรฐาน อย. โดยร้อยเรียงวัตถุดิบและภูมิปัญญาท้องถิ่นเพื่อกระจายรายได้สู่ชุมชนบ่อทอง พร้อมรับไฮซีซั่นปี 2026 บนฐานความสุขและทีมงานที่มีพลังชีวิตที่สมดุล | V20: T0
A21: RAP69-020 | B21: ผัดไทยคาเฟ่แม่วรรณา | R21: เป้าหมาย: ⁃ ทำให้คนรู้จักแบรนด์และร้านผัดไทยคาเฟ่แม่วรรณาเพิ่มมากขึ้น 70 % ⁃ พัฒนาผัดไทยให้มีรสชาติที่เป็นเอกลักษณ์ (Signature) โดยใช้ "น้ำซอสผัดไทยแม่วรรณา" เป็นหัวใจสำคัญ เพื่อให้ลูกค้าไม่ว่าจะทานเมื่อไหร่หรือที่ไหนก็จะได้รสชาติและคุณภาพที่คงที่ ด้วยการรักษามาตรฐานของร้านเป็นสำคัญ ⁃ มียอดขายเพิ่ม 10,000 - 15,000 บาทต่อวัน ⁃ พัฒนาและเรียนรู้สร้างช่องทางออนไลน์ (Facebook, TikTok, Google Maps) ให้มีผู้ติดตามเพิ่มขึ้นอย่างต่อเนื่อง ⁃ ขยายสาขา และพัฒนารูปแบบ Food Truck และ Franchise ให้โดดเด่นทันสมัยเป็นที่น่าสนใจและน่าลงทุน ⁃ เพิ่มช่องทางกิจกรรมเหมาเสิร์ฟ จัดเลี้ยง Catering และออกงานEvent ต่างๆมากขึ้น ⁃ พัฒนาผลิตภัณฑ์เป็นของฝาก เช่น ซอสผัดไทย ผัดไทยพร้อมทาน และผัดไทยกึ่งสำเร็จรูป แบรนด์แม่วรรณา ให้มีคุณภาพมาตรฐานอย.และปลอดภัย รสชาติเหมือนทานที่ร้าน ⁃ พัฒนาซอสผัดไทย ให้มีสูตรต่างๆนอกจากสูตร ดั้งเดิม แม่วรรณา เป็นสูตรซอสผัดไทยรสสละ และสูตรซอสผัดไทยรสสับปะรด โดยใช้วัตถุดิบในท้องถิ่นที่ขึ้นชื่อมีเอกลักษ์ที่โดดเด่นและแตกต่างเป็นหลัก ⁃ ยกระดับจากร้านอาหารสู่ระบบมาตรฐาน (SOP): การจัดทำขั้นตอนการทำ (SOP) ที่ชัดเจน เพื่อให้การขยายสาขาหรือการบริหารจัดการฟู้ดทรัคเป็นไปได้อย่างมีประสิทธิภาพ ลดความผิดพลาด และควบคุมต้นทุน ⁃ ปรับภาพลักษณ์ผัดไทยจากอาหารริมทาง (Street Food) ให้มีความเป็นไลฟ์สไตล์มากขึ้น ทั้งการตกแต่งรถเทลเลอร์ฟู้ดทรีคให้โดดเด่นเป็นที่จดจำ และแตกต่างมีมุมที่น่าถ่ายรูป ⁃ สร้างเพลงประจำร้านทำให้ลูกค้าจดจำ แบรนด์ ฟังแล้วติดหูเพื่อเข้าถึงกลุ่มลูกค้าได้ง่าย ⁃ มีที่ปรึกษาแหล่งเงินทุน เพื่อโอกาสขยายธุรกิจ ⁃ เป้าหมายสูงสุด: เพื่อให้ "ผัดไทยคาเฟ่แม่วรรณา" ไม่ใช่เป็นมากกว่าร้านอาหาร (Street Food)แต่เป็น "แบรนด์ผัดไทยระดับสากล" ที่มีระบบการจัดการหลังบ้านที่แข็งแกร่ง มีภาพลักษณ์ที่ทันสมัย และเป็นที่จดจำทั้งในแง่ของรสชาติและประสบการณ์ เป็นที่รู้จักทั้งชาวไทยและชาวต่างชาติ | S21: ร้านผัดไทยคาเฟ่แม่วรรณามุ่งสร้างคุณค่าทั้งทางเศรษฐกิจ สังคม และสิ่งแวดล้อม โดยสนับสนุนชุมชนท้องถิ่น ใช้ทรัพยากรอย่างรับผิดชอบ และมีคุณค่า สร้างความสุขให้แก่ลูกค้า พนักงาน ตัวเราและผู้มีส่วนเกี่ยวข้องทุกฝ่าย. | U21: ทะยานสู่ยอดขายเพิ่ม 15,000 บาทต่อวันด้วยซอสผัดไทยสูตรผลไม้ท้องถิ่นและของฝากมาตรฐาน อย. พร้อมวางระบบ SOP พลิกโฉมสู่ Food Truck ทันสมัยเพื่อขยายแฟรนไชส์สู่สากลในปี 2026 บนฐานความสุขของตัวเรา ทีมงาน และลูกค้า ผ่านการสนับสนุนวัตถุดิบชุมชนอย่างเกื้อกูล และใช้ทรัพยากรอย่างรับผิดชอบต่อสิ่งแวดล้อมในทุกขั้นตอน | V21: T0
A22: RAP69-021 | B22: Recharge Cafa | V22: T0
A23: RAP69-022 | B23: หมึกสดริมเล | R23: เป้าหมายของร้านหมึกสดริมเลในปีนี้ 1มีระบบหลังบ้านที่แข็งแรง SOP พนักงาน รวมไปถึงระบบสูตรอาหารคำนวณต้นทุน , Stock , ต้องทำให้ครบทุกเมนูในปีนี้ และปีนี้ระบบหลังบ้านจะต้องแข็งแรงที่สุดในรอบ 5 ปี ตั้งแต่เปิดมา 2.รักษายอดขายให้ได้ 1.5 ล้าน / เดือน หรือทำยอดขายให้มากขึ้นกว่านั้น 3.สร้างตัวตนในโลกออนไลน์การตลาดออนไลน์ให้มากกว่านี้ 4.ขยาย หมึกสดริมเล โมเดลเล็กๆไป บางแสนให้ได้ | S23: ช่วยส่งเสริมให้ชาวประมง คนเรือ ให้มีรายได้มากขึ้นและมั่นคงกว่าเดิม | U23: ปฏิวัติระบบหลังบ้านและสูตรอาหารให้แข็งแกร่งที่สุดในรอบ 5 ปี ควบคู่การรุกตลาดออนไลน์และขยายสาขาโมเดลเล็กที่บางแสนเพื่อสร้างยอดขายเสถียรเกิน 1.5 ล้านบาทต่อเดือน โดยยืนหยัดส่งมอบอาหารทะเลที่สดใหม่ แปลกใหม่ และอร่อย บนฐานการจับมือร่วมกับชาวประมงและคนเรือท้องถิ่นเพื่อสร้างรายได้ที่มั่นคงและเกื้อกูลวิถีชุมชนริมเลอย่างยั่งยืนในปี 2026 | V23: T0
A24: RAP69-023 | B24: บ้านแมะคาเฟ่ | R24: เป้าหมายในปี2026 เป็นจุดหมายปลายทางของนักท่องเที่ยวที่มาเที่ยวจันทบุรี * ติด Top คาเฟ่ที่นักท่องเที่ยวค้นหาในจันทบุรี * มีลูกค้าใหม่จากนักท่องเที่ยวไม่น้อยกว่า 50% * สร้างประสบการณ์ “จากเกษตรกรถึงลูกค้าโดยตรง“ พัฒนาสินค้าแบรนด์บ้านแมะ ให้จัดเจนและเข้มแข็งมากขึ้น เพื่อการขยายสาขา สร้างระบบร้านให้ทำงานได้แม้เจ้าของไม่อยู่ * มีหัวหน้าทีมแต่ละแผนก * จัดทำระบบ SOP ให้ชัดเจนยิ่งขึ้น * ลดปัญหางานตกหล่น * เจ้าของสามารถออกไปพัฒนาธุรกิจได้มากขึ้น พัฒนาทีมงาน * จัดอบรมพนักงาน สร้างทีมงานที่มีทักษะ เก่ง เพื่อการเป็นมืออาชีพ | S24: - เราสนับสนุนและรับซื้อผลผลิตจากเกษตรกรในพื้นที่เพื่อสร้างรายได้หมุนเวียนในชุมชน - สนับสนุนทุนการศึกษา ด้านกีฬา นักเรียนเรียนดี ของโรงเรียนในชุมชน (โรงเรียนบ้านเนินดินแดง / โรงเรียนมัธยมวัดเขาสุกิม) - ให้การสนับสนุนการมีงานทำ ของนักเรียนในชุมชน ให้มีอาชีพเสริม หลังจากเลิกเรียนหรือวันหยุด และเรารองรับการมีงานทำ ของนักเรียนที่มีความประสงค์เรียนจบแล้ว อยากมีงานทำเลย - สนับสนุนโรงทาน เลี้ยงโรงทาน ของทางวัดประจำจังหวัดในชุมชน เวลามีงานหรือเทศกาลต่างๆ | T24: ด้านสิ่งแวดล้อม - ทางร้านมีการคัดแยกขยะก่อนนำไปทิ้ง และแยกขยะสิ่งไหนเก็บไว้ขายต่อได้ - เศษอาหาร ทางร้านได้นำไปให้เป็นอาหารสัตว์ เลี้ยงปลา เลี้ยงไก่ - กากกาแฟทางร้านได้นำไปตากแล้วทำเป็นปุ๋ย ใส่ต้นไม้ แปลงผัก และแปลงดอกไม้ของทางร้าน | U24: ปั้นบ้านแมะสู่ Top คาเฟ่จันทบุรีด้วยระบบ SOP ที่พร้อมขยายสาขาปี 2026 ควบคู่การสร้างงานและมอบทุนการศึกษาแก่เยาวชน พร้อมจัดการขยะหมุนเวียนในร้าน เพื่อความสุขของทีมงานและการมีเวลาให้ครอบครัวอย่างยั่งยืน | V24: T0
A25: RAP69-024 | B25: ร้านทองม้วนคุณใบ้ | R25: ป้าหมายปีนี้ 2026 1.จัดทำคู่มือในการทำขนมทองม้วน 2.จัดระบบการทำงานในร้านทั้งหน้าร้าน และหลังร้าน 3.จัดหาระบบ POS ที่ช่วยจัดการการขาย,บัญชี,สต๊อกวัตถุดิบและสินค้า 4.เพิ่มร้านค้าพันธมิตรเพื่อรับขนมทองม้วนไปขายต่อ (B2B) 5.พัฒนาขนมทองม้วนรสชาติใหม่ | S25: ยกระดับระบบปฏิบัติการภายในร้าน พัฒนาทองม้วนรสชาติใหม่ ขยายตลาดออนไลน์ และ B2B สนับสนุนวัตถุดิบท้องถิ่น สืบทอดภูมิปัญญาขนมไทย และลดผลกระทบต่อสิ่งแวดล้อมในการดำเนินธุรกิจ | U25: ยกระดับระบบปฏิบัติการภายในร้านเพื่อเพิ่มประสิทธิภาพการทำงานอย่างเป็นระบบ ควบคู่การขยายตลาดออนไลน์ B2B และพัฒนาทองม้วนรสชาติใหม่เพื่อเพิ่มยอดขายในปี 2026 บนฐานความยั่งยืนร่วมกับท้องถิ่น ด้วยการสนับสนุนวัตถุดิบชุมชนและสืบทอดภูมิปัญญาขนมไทยอันทรงคุณค่า พร้อมใส่ใจสิ่งแวดล้อมด้วยการลดผลกระทบจากการดำเนินธุรกิจในทุกขั้นตอน | V25: T0
A26: RAP69-025 | B26: ร้านไชโย | V26: T0
A27: RAP69-026 | B27: ก๋วยเตี๋ยวปากหม้อ เกวียนนิยม | V27: T0
A28: RAP69-027 | B28: Chatrium Golf Resort Soidao | V28: T0
A29: RAP69-028 | B29: มาเว้า MA WAO | V29: T0
A30: RAP69-029 | B30: ร้านต้นสลัด | V30: T0
A31: RAP69-030 | B31: The Sunset Deck | V31: T0
A32: RAP69-031 | B32: ร้านครัวรวมรส ๒๕๖๔ จังหวัดตราด | R32: ทำการตลาดให้ลูกค้ารู้จักร้านให้มากขึ้น เน้นพัฒนาสูตรอาหารและระบบหลังร้านใหมีประสิทธิภาพมากที่สุด เพื่อที่จะได้มีเวลาไปจัดการเรื่องอื่นโดยไม่ต้องคอยเฝ้าร้าน และลงมือทำเองทุกอย่างในร้าน | V32: T0
A33: RAP69-032 | B33: ร้านคดข้าว | R33: เป้าหมาย ของร้านคดข้าว 5 ข้อ 1.ต้องการพัฒนา แบรนด์และสานต่อระบบ SOP ที่ดีเยี่ยม 2.ต้องการพัฒนาผลิตภัณฑ์ และต่อยอด ธุรกิตเฟรนไซน์ 3.พัฒนาและ สารต่ออัตลักษณ์ของอาหารพื้นถิ่นจันท์ 4.พัฒนาแรงงานและสร้างมาตรฐานการบริการที่ดีเยี่ยม 5. สร้างแบรนด์ ให้ เป็น ที่จดจำและเป็นแบบอย่าง ในระดับประเทศ | S33: ร้านคดข้าวมุ่งมั่นเติบโตไปพร้อมกับท้องถิ่น โดย เกษตรกรจันทบุรีจะได้รับรายได้ที่มั่นคงและเป็นธรรม (Fair Trade) จากการที่ร้านเข้าทำสัญญาซื้อขายวัตถุดิบอัตลักษณ์เมืองจันท์โดยตรง (Contract Farming) ไม่ผ่านคนกลาง ทั้งกลุ่มผลไม้ตามฤดูกาลและพืชสมุนไพรพื้นบ้าน ทำให้ชาวสวนมีตลาดรองรับผลผลิตที่แน่นอนในราคาที่เหมาะสม ส่วน ชุมชนจะได้รับการยกระดับเศรษฐกิจและการท่องเที่ยว ผ่านการชูภูมิปัญญา 'รสมือยาย' และวัตถุดิบท้องถิ่นมาสร้างมูลค่าเพิ่มเป็นผลิตภัณฑ์สร้างชื่อให้จังหวัด พร้อมกันนี้ ชุมชนยังจะได้รับประโยชน์จากแนวคิดความยั่งยืนที่ร้านนำระบบ SOP มาบริหารจัดการขยะอาหาร (Zero Waste) เพื่อลดผลกระทบต่อสิ่งแวดล้อม และสร้างโมเดลธุรกิจต้นแบบที่เป็นมิตรต่อชุมชนอย่างแท้จริง | U33: ยกระดับระบบ SOP และมาตรฐานบริการเพื่อรักษาคุณค่ารสชาติเก่าเล่าด้วยใจสู่อินเตอร์ ควบคู่การวางระบบครัวกลางและพัฒนาผลิตภัณฑ์พร้อมสเกลขยายสาขาทั่วประเทศในปี 2026 บนฐานความยั่งยืนร่วมกับท้องถิ่น ด้วยการทำข้อตกลงกับกลุ่มเกษตรกรเมืองจันท์เพื่อสร้างรายได้ที่เป็นธรรม (Fair Trade) ควบคู่กับการสืบสานภูมิปัญญาอาหารพื้นถิ่น และบริหารจัดการขยะอาหารในร้านเป็นศูนย์ (Zero Waste) เพื่อเป็นโมเดลธุรกิจต้นแบบที่สร้างความสุขให้ทั้งชุมชนและผู้บริโภค | V33: T0
A34: RAP69-033 | B34: GRID GARDEN | R34: เป้าหมายในปีนี้ของร้าน "Grid Garden" มุ่งมั่นพัฒนาพื้นที่แห่งความสุขของครอบครัวให้มีระบบการจัดการที่สมบูรณ์ โดยการ จัดทำ SOP มาตรฐานการบริการที่เป็นมิตรต่อสัตว์เลี้ยง (Pet-Friendly) ควบคู่ไปกับการ ผลักดันแผนก 'หวานตามกาล' เพื่อรังสรรค์เมนูของหวานและไอศกรีมโฮมเมดคราฟต์จากผลไม้ตามฤดูกาล และ พัฒนาแผนกเบเกอรี่ ให้เน้นการผลิตสินค้ากลุ่มของฝากประเภทหิ้วกลับบ้าน (Take-home) ที่มีดีไซน์และบรรจุภัณฑ์ที่พรีเมียม เพื่อสร้างประสบการณ์คาเฟ่ในสวนที่ครบวงจรและพร้อมเติบโตในฐานะเช็คอินสปอตสำคัญของจันทบุรี | S34: สนับสนุนกลุ่มชาวสวนผลไม้เมืองจันท์ผ่านแบรนด์ "หวานตามกาล" และสร้างพื้นที่ส่วนรวม (Community) ที่ปลอดภัยและเป็นมิตรสำหรับครอบครัวและคนรักสัตว์เลี้ยง | T34: ใช้ผลิตภัณฑ์ทำความสะอาดและดูแลสวนที่เป็นออร์แกนิก $100\%$ เพื่อความปลอดภัยของสัตว์เลี้ยง' | U34: ปักหมุดจุดขายคาเฟ่ในสวนด้วยระบบ SOP บริการ Pet-Friendly เต็มรูปแบบ ควบคู่การปั้นของหวาน 'หวานตามกาล' และเบเกอรี่ของฝากพรีเมียมจากผลไม้เมืองจันท์เพื่อขึ้นแท่นเช็คอินสปอตสำคัญในปีนี้ บนฐานความสุขที่ได้เห็นรอยยิ้มของทุกครอบครัวและสัตว์เลี้ยงในพื้นที่ปลอดภัยที่ใช้ออร์แกนิก $100\%$ พร้อมเกื้อกูลชาวสวนท้องถิ่นและทำปุ๋ยหมักหมุนเวียนบำรุงสวนอย่างยั่งยืน | V34: T0
A35: RAP69-034 | B35: เทียบจันท์ | V35: T0
A36: RAP69-035 | B36: The Chanthaboon Coffee กาแฟจันทบูร | R36: 1.เพิ่มยอดขายเฉลี่ยให้ได้ 100,000 บาทต่อเดือน โดยเพิ่มรายได้ต่อหัวของลูกค้าผ่านการจำหน่ายเครื่องดื่ม ขนม และอาหารที่เหมาะกับร้านกาแฟ (ตอนนี้ยังไม่มีเมนู ขนม และ อาหารชัดเจน ซึ่งลูกค้าหลายคนถามหา ว่ามีอาหารทานไหม) รวมถึงการพัฒนาเมนูชุด (Set Menu) เพื่อกระตุ้นการซื้อหลายรายการต่อครั้ง 2.พัฒนาเมนูอาหารและขนมอย่างเป็นทางการ เพื่อสร้างทางเลือกให้ลูกค้า เพิ่มมูลค่าต่อบิล และรองรับการเติบโตของยอดขายในอนาคต 3.วางระบบสต็อกและการจัดซื้อให้มีประสิทธิภาพ เพื่อควบคุมต้นทุน ลดการสูญเสียวัตถุดิบ และป้องกันปัญหาสินค้าขาดสต็อก 4.จัดทำคู่มือการทำงาน (SOP) สำหรับงานหน้าร้านและหลังร้าน เพื่อให้การทำงานมีมาตรฐาน ลดความผิดพลาด และสามารถส่งมอบสินค้าและบริการได้อย่างสม่ำเสมอ 5.พัฒนาระบบบริหารจัดการร้านและกระจายหน้าที่ความรับผิดชอบให้ทีมงาน เพื่อให้ธุรกิจสามารถดำเนินงานได้อย่างเป็นระบบ และลดการพึ่งพาเจ้าของกิจการ 6.ดำเนินการตลาดอย่างต่อเนื่องทั้งออนไลน์และออฟไลน์ เพื่อสร้างการรับรู้แบรนด์ เพิ่มฐานลูกค้าใหม่ รักษาฐานลูกค้าเดิม และสนับสนุนการเติบโตของยอดขาย เป้าหมายสูงสุด ยกระดับกาแฟจันทบูรให้เป็นร้านกาแฟที่มีระบบบริหารจัดการที่เข้มแข็ง มียอดขายเติบโตอย่างยั่งยืน เป็นแหล่งเรียนรู้ด้านกาแฟ และเป็นหนึ่งในจุดหมายปลายทางของนักท่องเที่ยวและคนรักกาแฟในจังหวัดจันทบุรี ::: | S36: -เป็นพื้นที่พบปะ พูดคุย และแลกเปลี่ยนเรียนรู้ของผู้คนทั้งชาวไทยและชาวต่างชาติ -สร้างโอกาสในการเรียนรู้เรื่องกาแฟ ตั้งแต่การปลูก การแปรรูป ไปจนถึงการชงกาแฟ -ถ่ายทอดเรื่องราวประวัติศาสตร์ วัฒนธรรม และวิถีชีวิตของชุมชนจันทบุรีผ่านกาแฟ -สนับสนุนเกษตรกร ผู้ผลิต และผู้ประกอบการในท้องถิ่นให้มีรายได้เพิ่มขึ้นจากกาแฟ -สร้างงานและพัฒนาทักษะให้กับทีมงานและคนในชุมชน -ผลักดันให้ผู้คนทั้งในและต่างประเทศรับรู้ว่าจันทบุรีมีประวัติการปลูกกาแฟมายาวนาน และเป็นแหล่งผลิตกาแฟคุณภาพของไทย | T36: -ส่งเสริมการปลูกกาแฟแบบพืชผสมผสานในสวนดั้งเดิมของเกษตรกร -ช่วยให้เกษตรกรไม่จำเป็นต้องโค่นพืชเศรษฐกิจเดิมทิ้ง แต่สามารถปลูกกาแฟเป็นรายได้เสริมควบคู่กันได้ -สนับสนุนระบบเกษตรที่มีความหลากหลายทางชีวภาพ มากกว่าการปลูกพืชเชิงเดี่ยว -ช่วยรักษาความอุดมสมบูรณ์ของดินและระบบนิเวศภายในสวน -เพิ่มพื้นที่สีเขียวและร่มเงาให้กับแปลงเกษตร -ลดการสูญเสียและของเสียจากการบริหารจัดการวัตถุดิบอย่างมีประสิทธิภาพ -ส่งเสริมการใช้วัตถุดิบจากท้องถิ่น เพื่อลดการขนส่งและสร้างความยั่งยืนให้กับชุมชน | U36: ผลักดันยอดขายสู่ 100,000 บาทต่อเดือนด้วยเมนูและเซ็ตอาหารใหม่ วางระบบสต็อก และ SOP ให้ร้านรันได้เองในปี 2026 บนฐานความสุขที่ได้เล่าขานประวัติศาสตร์และส่งต่อคุณค่ากาแฟจันทบุรีสู่ระดับโลก ควบคู่การสร้างรายได้และพัฒนาทักษะคนในชุมชน พร้อมขับเคลื่อนสิ่งแวดล้อมที่ยั่งยืนผ่านการส่งเสริมเกษตรกรปลูกกาแฟร่วมในสวนดั้งเดิมเพื่อรักษาความหลากหลายทางชีวภาพและระบบนิเวศอย่างมั่นคง | V36: T0
A37: RAP69-036 | B37: Garagecafechan | V37: T0
A38: RAP69-037 | B38: จันทรโภชนา | R38: สร้างและวางตลาดผลิตภัณฑ์ “จันทร” อย่างมีแนวทางที่มั่นคงในระยะยาว ไม่หวือหวา โดยยึดคุณค่าท้องถิ่นสู่มูลค่าทางธุรกิจ | S38: สร้างและวางตลาดผลิตภัณฑ์ “จันทร” กลุ่มเส้นจันท์ และ สมุนไพร นำคุณค่าท้องถิ่นสู่มูลค่าทางธุรกิจ สู่การเป็นเมืองสร้างสรรค์ด้านอาหาร | U38: ยกระดับร้านอาหารจันทรโภชนาควบคู่การวางตลาดผลิตภัณฑ์ 'จันทร' กลุ่มเส้นจันท์และสมุนไพร เพื่อเปลี่ยนคุณค่าท้องถิ่นสู่มูลค่าธุรกิจอย่างมั่นคง บนฐานความสุขที่ได้ขับเคลื่อนจันทบุรีสู่เมืองสร้างสรรค์ด้านอาหาร ตลอดจนยกระดับเศรษฐกิจชุมชนและภูมิปัญญาท้องถิ่นอย่างยั่งยืน | V38: T0
A39: RAP69-038 | B39: Grizzly Gelato | R39: ป้าหมายในปีนี้ 1. ครึ่งปีหลังยอด x2 ของครึ่งปีแรก 2. สร้างช่องติ๊กตอกร้านอาหาร ให้เป็นช่องดัง ผู้ติดตามหลักพันคน 3. ปั้นเพจเฟสบุคร้านไอติมให้ตัวตนชัด 4. สร้างระบบหลังบ้านให้แน่น พร้อมขยายสาขาปีหน้า | S39: เน้นยกระดับวัตถุดิบท้องถิ่น เช่นพวกผลไม้พันธุ์ที่ไม่เป็นที่นิยม หรือขายไม่ได้ราคา เอามาทำเป็นไอติมที่เพิ่มความคิดสร้างสรรค์เข้าไป | U39: ลุยปั๊มยอดขายครึ่งปีหลังให้โตเป็น 2 เท่า ควบคู่การสร้างตัวตนบน TikTok และ Facebook พร้อมเซ็ตระบบหลังบ้านให้แน่นเพื่อเตรียมขยายสาขา บนฐานการทำงานที่มีความสุขผ่านการทำ R&D ไอติมรสชาติใหม่ ๆ ที่ชวนว้าว และมุ่งยกระดับผลไม้ท้องถิ่นสายพันธุ์นอกกระแสให้มีมูลค่าเพิ่ม เพื่อกระจายรายได้และสร้างรอยยิ้มกลับคืนสู่เกษตรกรในชุมชน | V39: T0
A40: RAP69-039 | B40: ครัวตามธาตุ | V40: T0
A41: RAP69-040 | B41: จิน ข้าวมันไก่สไตล์สิงคโปร์ | R41: เป้าหมายที่ชัดเจน ในปีนี้ของ จิน ข้าวมันไก่สไตล์สิงคโปร์ 1. ทำระบบ SOP ในทุกๆกระบวนการ ให้จบสมบูรณ์ 100% พร้อมรูปประกอบในทุกๆกระบวนการ รวมถึงผังองค์กรที่สมบูรณ์ ให้แล้วเสร็จไม่เกินเดือนกันยายนนี้ **ตอนนี้สูตรมาตรฐานในทุกๆสัดส่วนครบค่ะ แต่เรื่องรูปภาพยังไม่สมบูรณ์เรียบร้อยแบบ 100% และยังไม่ออกมาเป็นรูปเล่มที่สมบูรณ์ 2. จัดทำระบบครัวกลางในห้องมาตรฐานเพื่อรักษาคุณภาพตั้งแต่กระบวนการ ขึ้นน้ำจิ้ม น้ำซอสต่างๆ จนถึงการบรรจุให้มีมาตรฐานเพื่อกระจายไปยัง 2 สาขาของทางจิน 3. จัดการเรื่องการเบิกจ่าย สต๊อควัตถุดิบหลังบ้านให้มีความเสถียรมากที่สุด 4. จัดการเรื่องการหาโปรแกรมที่เป็นตัวช่วยเรื่องลำดับการเรียงคิว ลูกค้าจะได้ทราบลำดับและเวลาการรอของคิวตัวเอง 5.เรื่องแฟรนไซส์ทาง จิน ตั้งใจว่าจะไม่ทำค่ะ แต่จะเป็นการขยายสาขาจากทางเราที่เป็นเจ้าของเอง ในพื้นที่ และ ระยะเวลาที่เหมาะสม | S41: 1.กระดูกจากโครงไก่ เรานำมาใส่ในน้ำซุป และสุดท้ายเราจะตักออกมากรองเพื่อรวมกับเศษอาหารนำไปให้กับคนที่มารับไปเลี้ยงสุนัขในศูนย์พักพิง แตงกวา 2.ตอนนี้ทางร้านใช้ของ สวนแถวๆเสม็ดงามในจันทบุรีเป็นหลัก เพื่อส่งเสริมการปลูกผักแบบอินทรีย์ในพื้นที่จันทบุรี 3.พริกไทยเราใช้ พริกไทยของ อ.ท่าใหม่ ที่เป็นกลุ่มวิสาหกิจชุมชน | T41: ตอนนี้จินมีวิธีจัดการขยะ พยายามจัดการ ให้ เกิด Waste ให้น้อยที่สุด เศษผักต่างๆ ทางจินพยายามบริหารให้หมด แต่จะมีบ้างที่เหลือจะเอาไปหมักทำปุ๋ยอินทรีย์ที่สวน | U41: วางรากฐานระบบครัวกลาง คู่มือ SOP และใช้เทคโนโลยีจัดการคิวและสต๊อกอย่างเต็มรูปแบบ เพื่อควบคุมมาตรฐาน 2 สาขาและพร้อมรองรับการขยายตัวในปี 2026 ควบคู่การสร้างระบบครัวหมุนเวียนเพื่อลดขยะอาหารให้เหลือน้อยที่สุด (Zero Food Waste) และมุ่งเน้นการสนับสนุนเกษตรกรอินทรีย์รวมถึงวิสาหกิจชุมชนในจันทบุรีเพื่อกระจายรายได้และเติบโตไปด้วยกันอย่างยั่งยืน | V41: T0
A42: RAP69-041 | B42: สุขทุกวัน คาเฟ่ | R42: สิ่งที่ต้องทำ 1. จัดเรียงอาหารใช้ก่อนหลัง 2. ทำต้นทุนอาหารแค่ละอย่าง 3. วางแผนการตลาดในแต่ละเดือน (ให้ขายได้ทั้งปี) 4. คิดเมนูพิเศษตามเทศกาล 5. ต่อยอดสินค้าให้เป็นสินค้าแบรนด์ตัวเอง สิ่งที่ต้องเลิกทำ 1. เลิกทำงานไม่เป็นระบบ 2. เลิกทำงานที่ไม่มีการวางแผนมาก่อน 3. เลิกทำเมนูที่ขายได้น้อย 4. เลิกก๊อปปี้เมนูที่ร้านอื่นขายดี 5. เลิกเข้าข้างตัวเองแล้วฟังความเห็นลูกค้า | S42: มีการสร้างโอกาส สร้างชุมชนเข้มแข็งอยู่แล้ว และมีการใช้วัตถุดิบจากท้องถิ่น เช่น นมวัว ไข่สนุกสนาน ผัก ผลไม้ ในเครือข่ายของ สุขทุกวันคาเฟ่ พร้อม สร้างเมนูเครื่องดื่ม และ อาหารให้สอดคล้องกับ วัตถุดิบ นั้น ๆ เป็นประจำครับ รวมถึงแรงงานเรา ก็ให้โอกาส น้อง ๆ ในพื้นที่ เข้ามาทำงาน เรียนรู้งานที่คาเฟ่ ของเราจ้า เพื่อลดต้นทุนค่าเดินทางเข้าเมือง ให้ชุมชน | T42: สิ่งแวดล้อม เราทำคาเฟ่ไม้ไผ่ ปลูกผัก ผลไม้ ปลอดสารพิษ ปลูกต้นไม้ ผัก ผลไม้เพิ่ม แบบ อินทรีย์ | U42: ล้างไพ่ระบบเดิมสู่การควบคุมต้นทุนและจัดเก็บวัตถุดิบอย่างเป็นระบบ ปรับปรุงเมนูตามเทศกาล ปั้นแบรนด์สินค้าตัวเอง และรุกการตลาดสร้างตัวตนร้านสุขทุกวันคาเฟ่ให้เป็นที่รู้จักทุกช่องทางในปี 2026 บนฐานความสุขทุกวันในการรักษาธรรมชาติวิถีอินทรีย์และการสร้างอาหารคือยา พร้อมเชื่อมโยงวัตถุดิบท้องถิ่น สร้างงานให้เยาวชน และเปิดพื้นที่คาเฟ่ไม้ไผ่ให้เป็นศูนย์รวมกิจกรรมที่สร้างความอบอุ่น สมาธิ และรอยยิ้มให้กับทุกครอบครัวอย่างยั่งยืน | V42: T0
A43: RAP69-042 | B43: เลย เดอ ลอง | R43: เป้าหมาย ในปีนี้ของ เลย เดอ ลอง "ต้องการเพิ่มยอดขายร้านเติบโต 100% โดยที่ยังสามารถมีกำไรสุทธิไม่น้อยกว่า 25% ภายในปี2569 " | S43: ใช้วัตถุดิบพื้นถิ่น พัฒนาร่วมกับชุมชน และสามารถอยู่ร่วมกับชุมชนได้แบบไม่สร้างปัญหา ที่เกิดจากร้านอาหาร | U43: มุ่งสร้างยอดขายให้เติบโต 100% พร้อมรักษาอัตรากำไรสุทธิไม่น้อยกว่า 25% ภายในปี 2569 ควบคู่การเป็นร้านอาหารต้นแบบที่พัฒนาเมนูร่วมกับชุมชนด้วยการใช้วัตถุดิบพื้นถิ่น และจัดการระบบร้านอย่างใส่ใจไม่สร้างมลพิษให้สิ่งแวดล้อม บนฐานความสุขและความวางใจของครอบครัวที่สามารถรับประทานอาหารในร้านของตัวเองได้อย่างปลอดภัยและภาคภูมิใจในทุก ๆ วัน | V43: T0
A44: RAP69-043 | B44: ร้านที่ 43 | V44: T0
A45: RAP69-044 | B45: ร้านที่ 44 | V45: T0
A46: RAP69-045 | B46: ร้านที่ 45 | V46: T0
A47: RAP69-046 | B47: ร้านที่ 46 | V47: T0
A48: RAP69-047 | B48: ร้านที่ 47 | V48: T0
A49: RAP69-048 | B49: ร้านที่ 48 | V49: T0
A50: RAP69-049 | B50: ร้านที่ 49 | V50: T0
A51: RAP69-050 | B51: ร้านที่ 50 | V51: T0

Sheet 02_ประเมิน50ร้าน
A1: รหัสร้าน | B1: ชื่อร้าน | C1: รอบ | D1: วันที่ประเมิน | E1: Q1 | F1: Q2 | G1: Q3 | H1: Q4 | I1: Q5 | J1: Q6 | K1: Q7 | L1: Q8 | M1: Q9 | N1: Q10 | O1: Q11 | P1: Q12 | Q1: Q13 | R1: Q14 | S1: Q15 | T1: Q16 | U1: Q17 | V1: Q18 | W1: Q19 | X1: Q20 | Y1: Q21 | Z1: Q22 | AA1: Q23 | AB1: Q24 | AC1: Q25 | AD1: Q26 | AE1: Q27 | AF1: Q28 | AG1: Q29 | AH1: Q30 | AI1: Q31 | AJ1: Q32 | AK1: Q33 | AL1: Q34 | AM1: Q35 | AN1: Q36 | AO1: Q37 | AP1: Q38 | AQ1: Q39 | AR1: Q40 | AS1: Q41 | AT1: Q42 | AU1: Q43 | AV1: Q44 | AW1: Q45 | AX1: Q46 | AY1: Q47 | AZ1: Q48 | BA1: Q49 | BB1: Q50 | BC1: ความครบถ้วน | BD1: คะแนนดิบ | BE1: คะแนนรวม % | BF1: คะแนนถ่วงน้ำหนัก | BG1: Red Flag | BH1: ระดับรวม | BI1: มิติเร่งแก้ไข | BJ1: มิติ 1 | BK1: มิติ 2 | BL1: มิติ 3 | BM1: มิติ 4 | BN1: มิติ 5 | BO1: มิติ 6 | BP1: มิติ 7 | BQ1: มิติ 8 | BR1: หมายเหตุ/ข้อเสนอแนะ
A2: RAP69-001 | B2: ='01_ข้อมูลร้าน'!B2 -> Seed restaurant | C2: T0 | E2: 2 | F2: 0 | G2: 3 | H2: 0 | I2: 1 | J2: 2 | K2: 4 | L2: 1 | M2: 2 | N2: 0 | O2: 3 | P2: 4 | Q2: 0 | R2: 2 | S2: 4 | T2: 4 | U2: 3 | V2: 4 | W2: 4 | X2: 1 | Y2: 4 | Z2: 4 | AA2: 4 | AB2: 0 | AC2: 4 | AD2: 4 | AE2: 1 | AF2: 2 | AG2: 1 | AH2: 3 | AI2: 1 | AJ2: 2 | AK2: 2 | AL2: 2 | AM2: 0 | AN2: 4 | AO2: 2 | AP2: 0 | AQ2: 1 | AR2: 3 | AS2: 0 | AT2: 2 | AU2: 1 | AV2: 3 | AW2: 4 | AX2: 1 | AY2: 4 | AZ2: 4 | BA2: 3 | BB2: 3 | BC2: =COUNT(E34:BB34)/50 -> 1 | BD2: =SUM(E34:BB34) -> 150 | BE2: =BD2/200 -> 0.75 | BF2: =SUM(E34:K34)/(7*4)*0.12+SUM(L34:R34)/(7*4)*0.15+SUM(S34:X34)/(6*4)*0.1+SUM(Y34:AE34)/(7*4)*0.13+SUM(AF34:AL34)/(7*4)*0.2+SUM(AM34:AS34)/(7*4)*0.18+SUM(AT34:AX34)/(5*4)*0.05+SUM(AY34:BB34)/(4*4)*0.07 -> 0.74145833 | BG2: =COUNTIFS(E34:BB34,">=0",E34:BB34,"<=1") -> 0 | BH2: =IF(BC2=0,"ยังไม่ประเมิน",IF(BF2>=0.8,"ดีมาก",IF(BF2>=0.65,"ดี",IF(BF2>=0.5,"ต้องพัฒนา","เร่งแก้ไข")))) -> ดี | BI2: =IF(BC2=0,"ยังไม่ประเมิน",INDEX($BJ$1:$BQ$1,1,MATCH(MIN(BJ2:BQ2),BJ2:BQ2,0))) -> มิติ 6 | BJ2: =SUM(E34:K34)/(7*4) -> 0.67857143 | BK2: =SUM(L34:R34)/(7*4) -> 0.85714286 | BL2: =SUM(S34:X34)/(6*4) -> 0.83333333 | BM2: =SUM(Y34:AE34)/(7*4) -> 0.71428571 | BN2: =SUM(AF34:AL34)/(7*4) -> 0.71428571 | BO2: =SUM(AM34:AS34)/(7*4) -> 0.60714286 | BP2: =SUM(AT34:AX34)/(5*4) -> 0.75 | BQ2: =SUM(AY34:BB34)/(4*4) -> 0.9375
A3: RAP69-002 | B3: =IFERROR(VLOOKUP(A3,'01_ข้อมูลร้าน'!$A$2:$B$51,2,FALSE),"") -> ก๋วยเตี๋ยวเรือคุณปุ๊ก | C3: T0 | E3: 4 | F3: 0 | G3: 4 | H3: 3 | I3: 4 | J3: 4 | K3: 4 | L3: 3 | M3: 0 | N3: 0 | O3: 0 | P3: 0 | Q3: 0 | R3: 4 | S3: 4 | T3: 3 | U3: 3 | V3: 1 | W3: 2 | X3: 2 | Y3: 1 | Z3: 3 | AA3: 3 | AB3: 1 | AC3: 2 | AD3: 4 | AE3: 1 | AF3: 2 | AG3: 3 | AH3: 3 | AI3: 2 | AJ3: 2 | AK3: 2 | AL3: 2 | AM3: 2 | AN3: 1 | AO3: 3 | AP3: 1 | AQ3: 0 | AR3: 4 | AS3: 4 | AT3: 3 | AU3: 1 | AV3: 3 | AW3: 1 | AX3: 0 | AY3: 3 | AZ3: 3 | BA3: 3 | BB3: 4 | BC3: =COUNT(E3:BB3)/50 -> 1 | BD3: =SUM(E3:BB3) -> 112 | BE3: =BD3/200 -> 0.56 | BF3: =SUM(E3:K3)/(7*4)*0.12+SUM(L3:R3)/(7*4)*0.15+SUM(S3:X3)/(6*4)*0.1+SUM(Y3:AE3)/(7*4)*0.13+SUM(AF3:AL3)/(7*4)*0.2+SUM(AM3:AS3)/(7*4)*0.18+SUM(AT3:AX3)/(5*4)*0.05+SUM(AY3:BB3)/(4*4)*0.07 -> 0.55580357 | BG3: =COUNTIFS(E3:BB3,">=0",E3:BB3,"<=1") -> 16 | BH3: =IF(BC3=0,"ยังไม่ประเมิน",IF(BF3>=0.8,"ดีมาก",IF(BF3>=0.65,"ดี",IF(BF3>=0.5,"ต้องพัฒนา","เร่งแก้ไข")))) -> ต้องพัฒนา | BI3: =IF(BC3=0,"ยังไม่ประเมิน",INDEX($BJ$1:$BQ$1,1,MATCH(MIN(BJ3:BQ3),BJ3:BQ3,0))) -> มิติ 2 | BJ3: =SUM(E3:K3)/(7*4) -> 0.82142857 | BK3: =SUM(L3:R3)/(7*4) -> 0.25 | BL3: =SUM(S3:X3)/(6*4) -> 0.625 | BM3: =SUM(Y3:AE3)/(7*4) -> 0.53571429 | BN3: =SUM(AF3:AL3)/(7*4) -> 0.57142857 | BO3: =SUM(AM3:AS3)/(7*4) -> 0.53571429 | BP3: =SUM(AT3:AX3)/(5*4) -> 0.4 | BQ3: =SUM(AY3:BB3)/(4*4) -> 0.8125
A4: RAP69-003 | B4: =IFERROR(VLOOKUP(A4,'01_ข้อมูลร้าน'!$A$2:$B$51,2,FALSE),"") -> บ้าน-บ้าน สุขพอดี | C4: T0 | E4: 0 | F4: 0 | G4: 0 | H4: 0 | I4: 0 | J4: 3 | K4: 4 | L4: 0 | M4: 0 | N4: 0 | O4: 0 | P4: 0 | Q4: 0 | R4: 0 | S4: 1 | T4: 1 | U4: 2 | V4: 3 | W4: 3 | X4: 2 | Y4: 4 | Z4: 4 | AA4: 4 | AB4: 4 | AC4: 3 | AD4: 3 | AE4: 3 | AF4: 1 | AG4: 2 | AH4: 3 | AI4: 0 | AJ4: 0 | AK4: 1 | AL4: 2 | AM4: 0 | AN4: 0 | AO4: 0 | AP4: 2 | AQ4: 0 | AR4: 1 | AS4: 0 | AT4: 2 | AU4: 4 | AV4: 3 | AW4: 4 | AX4: 4 | AY4: 4 | AZ4: 4 | BA4: 3 | BB4: 4 | BC4: =COUNT(E4:BB4)/50 -> 1 | BD4: =SUM(E4:BB4) -> 88 | BE4: =BD4/200 -> 0.44 | BF4: =SUM(E4:K4)/(7*4)*0.12+SUM(L4:R4)/(7*4)*0.15+SUM(S4:X4)/(6*4)*0.1+SUM(Y4:AE4)/(7*4)*0.13+SUM(AF4:AL4)/(7*4)*0.2+SUM(AM4:AS4)/(7*4)*0.18+SUM(AT4:AX4)/(5*4)*0.05+SUM(AY4:BB4)/(4*4)*0.07 -> 0.38776786 | BG4: =COUNTIFS(E4:BB4,">=0",E4:BB4,"<=1") -> 24 | BH4: =IF(BC4=0,"ยังไม่ประเมิน",IF(BF4>=0.8,"ดีมาก",IF(BF4>=0.65,"ดี",IF(BF4>=0.5,"ต้องพัฒนา","เร่งแก้ไข")))) -> เร่งแก้ไข | BI4: =IF(BC4=0,"ยังไม่ประเมิน",INDEX($BJ$1:$BQ$1,1,MATCH(MIN(BJ4:BQ4),BJ4:BQ4,0))) -> มิติ 2 | BJ4: =SUM(E4:K4)/(7*4) -> 0.25 | BK4: =SUM(L4:R4)/(7*4) -> 0 | BL4: =SUM(S4:X4)/(6*4) -> 0.5 | BM4: =SUM(Y4:AE4)/(7*4) -> 0.89285714 | BN4: =SUM(AF4:AL4)/(7*4) -> 0.32142857 | BO4: =SUM(AM4:AS4)/(7*4) -> 0.10714286 | BP4: =SUM(AT4:AX4)/(5*4) -> 0.85 | BQ4: =SUM(AY4:BB4)/(4*4) -> 0.9375
A5: RAP69-004 | B5: =IFERROR(VLOOKUP(A5,'01_ข้อมูลร้าน'!$A$2:$B$51,2,FALSE),"") -> แฟรนไชส์ก๋วยเตี๋ยวปากหม้อแม่ว่าดี | C5: T0 | E5: 3 | F5: 4 | G5: 4 | H5: 4 | I5: 4 | J5: 3 | K5: 4 | L5: 2 | M5: 2 | N5: 4 | O5: 3 | P5: 2 | Q5: 2 | R5: 1 | S5: 3 | T5: 2 | U5: 4 | V5: 4 | W5: 3 | X5: 3 | Y5: 4 | Z5: 4 | AA5: 4 | AB5: 3 | AC5: 4 | AD5: 3 | AE5: 3 | AF5: 3 | AG5: 4 | AH5: 4 | AI5: 4 | AJ5: 3 | AK5: 3 | AL5: 3 | AM5: 1 | AN5: 2 | AO5: 4 | AP5: 1 | AQ5: 4 | AR5: 4 | AS5: 2 | AT5: 4 | AU5: 3 | AV5: 4 | AW5: 4 | AX5: 4 | AY5: 4 | AZ5: 4 | BA5: 4 | BB5: 3 | BC5: =COUNT(E5:BB5)/50 -> 1 | BD5: =SUM(E5:BB5) -> 162 | BE5: =BD5/200 -> 0.81 | BF5: =SUM(E5:K5)/(7*4)*0.12+SUM(L5:R5)/(7*4)*0.15+SUM(S5:X5)/(6*4)*0.1+SUM(Y5:AE5)/(7*4)*0.13+SUM(AF5:AL5)/(7*4)*0.2+SUM(AM5:AS5)/(7*4)*0.18+SUM(AT5:AX5)/(5*4)*0.05+SUM(AY5:BB5)/(4*4)*0.07 -> 0.79264881 | BG5: =COUNTIFS(E5:BB5,">=0",E5:BB5,"<=1") -> 3 | BH5: =IF(BC5=0,"ยังไม่ประเมิน",IF(BF5>=0.8,"ดีมาก",IF(BF5>=0.65,"ดี",IF(BF5>=0.5,"ต้องพัฒนา","เร่งแก้ไข")))) -> ดี | BI5: =IF(BC5=0,"ยังไม่ประเมิน",INDEX($BJ$1:$BQ$1,1,MATCH(MIN(BJ5:BQ5),BJ5:BQ5,0))) -> มิติ 2 | BJ5: =SUM(E5:K5)/(7*4) -> 0.92857143 | BK5: =SUM(L5:R5)/(7*4) -> 0.57142857 | BL5: =SUM(S5:X5)/(6*4) -> 0.79166667 | BM5: =SUM(Y5:AE5)/(7*4) -> 0.89285714 | BN5: =SUM(AF5:AL5)/(7*4) -> 0.85714286 | BO5: =SUM(AM5:AS5)/(7*4) -> 0.64285714 | BP5: =SUM(AT5:AX5)/(5*4) -> 0.95 | BQ5: =SUM(AY5:BB5)/(4*4) -> 0.9375
A6: RAP69-005 | B6: =IFERROR(VLOOKUP(A6,'01_ข้อมูลร้าน'!$A$2:$B$51,2,FALSE),"") -> 16Brix Melon Farm&Café | C6: T0 | E6: 4 | F6: 3 | G6: 2 | H6: 4 | I6: 4 | J6: 4 | K6: 4 | L6: 1 | M6: 1 | N6: 0 | O6: 2 | P6: 2 | Q6: 4 | R6: 2 | S6: 4 | T6: 4 | U6: 4 | V6: 1 | W6: 4 | X6: 4 | Y6: 4 | Z6: 4 | AA6: 4 | AB6: 0 | AC6: 4 | AD6: 4 | AE6: 3 | AF6: 4 | AG6: 4 | AH6: 3 | AI6: 3 | AJ6: 3 | AK6: 4 | AL6: 4 | AM6: 2 | AN6: 0 | AO6: 2 | AP6: 2 | AQ6: 2 | AR6: 3 | AS6: 3 | AT6: 3 | AU6: 4 | AV6: 4 | AW6: 4 | AX6: 4 | AY6: 3 | AZ6: 4 | BA6: 4 | BB6: 4 | BC6: =COUNT(E6:BB6)/50 -> 1 | BD6: =SUM(E6:BB6) -> 154 | BE6: =BD6/200 -> 0.77 | BF6: =SUM(E6:K6)/(7*4)*0.12+SUM(L6:R6)/(7*4)*0.15+SUM(S6:X6)/(6*4)*0.1+SUM(Y6:AE6)/(7*4)*0.13+SUM(AF6:AL6)/(7*4)*0.2+SUM(AM6:AS6)/(7*4)*0.18+SUM(AT6:AX6)/(5*4)*0.05+SUM(AY6:BB6)/(4*4)*0.07 -> 0.74741071 | BG6: =COUNTIFS(E6:BB6,">=0",E6:BB6,"<=1") -> 6 | BH6: =IF(BC6=0,"ยังไม่ประเมิน",IF(BF6>=0.8,"ดีมาก",IF(BF6>=0.65,"ดี",IF(BF6>=0.5,"ต้องพัฒนา","เร่งแก้ไข")))) -> ดี | BI6: =IF(BC6=0,"ยังไม่ประเมิน",INDEX($BJ$1:$BQ$1,1,MATCH(MIN(BJ6:BQ6),BJ6:BQ6,0))) -> มิติ 2 | BJ6: =SUM(E6:K6)/(7*4) -> 0.89285714 | BK6: =SUM(L6:R6)/(7*4) -> 0.42857143 | BL6: =SUM(S6:X6)/(6*4) -> 0.875 | BM6: =SUM(Y6:AE6)/(7*4) -> 0.82142857 | BN6: =SUM(AF6:AL6)/(7*4) -> 0.89285714 | BO6: =SUM(AM6:AS6)/(7*4) -> 0.5 | BP6: =SUM(AT6:AX6)/(5*4) -> 0.95 | BQ6: =SUM(AY6:BB6)/(4*4) -> 0.9375
A7: RAP69-006 | B7: =IFERROR(VLOOKUP(A7,'01_ข้อมูลร้าน'!$A$2:$B$51,2,FALSE),"") -> ร้านอีสานเฮาส์ (304 ปราจีนบุรี) | C7: T0 | E7: 4 | F7: 0 | G7: 1 | H7: 4 | I7: 4 | J7: 3 | K7: 4 | L7: 4 | M7: 4 | N7: 3 | O7: 3 | P7: 4 | Q7: 4 | R7: 4 | S7: 4 | T7: 4 | U7: 4 | V7: 4 | W7: 4 | X7: 4 | Y7: 4 | Z7: 4 | AA7: 4 | AB7: 4 | AC7: 4 | AD7: 4 | AE7: 4 | AF7: 3 | AG7: 3 | AH7: 3 | AI7: 3 | AJ7: 3 | AK7: 3 | AL7: 4 | AM7: 4 | AN7: 4 | AO7: 2 | AP7: 4 | AQ7: 2 | AR7: 2 | AS7: 4 | AT7: 4 | AU7: 3 | AV7: 4 | AW7: 4 | AX7: 4 | AY7: 4 | AZ7: 4 | BA7: 4 | BB7: 4 | BC7: =COUNT(E7:BB7)/50 -> 1 | BD7: =SUM(E7:BB7) -> 177 | BE7: =BD7/200 -> 0.885 | BF7: =SUM(E7:K7)/(7*4)*0.12+SUM(L7:R7)/(7*4)*0.15+SUM(S7:X7)/(6*4)*0.1+SUM(Y7:AE7)/(7*4)*0.13+SUM(AF7:AL7)/(7*4)*0.2+SUM(AM7:AS7)/(7*4)*0.18+SUM(AT7:AX7)/(5*4)*0.05+SUM(AY7:BB7)/(4*4)*0.07 -> 0.87107143 | BG7: =COUNTIFS(E7:BB7,">=0",E7:BB7,"<=1") -> 2 | BH7: =IF(BC7=0,"ยังไม่ประเมิน",IF(BF7>=0.8,"ดีมาก",IF(BF7>=0.65,"ดี",IF(BF7>=0.5,"ต้องพัฒนา","เร่งแก้ไข")))) -> ดีมาก | BI7: =IF(BC7=0,"ยังไม่ประเมิน",INDEX($BJ$1:$BQ$1,1,MATCH(MIN(BJ7:BQ7),BJ7:BQ7,0))) -> มิติ 1 | BJ7: =SUM(E7:K7)/(7*4) -> 0.71428571 | BK7: =SUM(L7:R7)/(7*4) -> 0.92857143 | BL7: =SUM(S7:X7)/(6*4) -> 1 | BM7: =SUM(Y7:AE7)/(7*4) -> 1 | BN7: =SUM(AF7:AL7)/(7*4) -> 0.78571429 | BO7: =SUM(AM7:AS7)/(7*4) -> 0.78571429 | BP7: =SUM(AT7:AX7)/(5*4) -> 0.95 | BQ7: =SUM(AY7:BB7)/(4*4) -> 1
A8: RAP69-007 | B8: =IFERROR(VLOOKUP(A8,'01_ข้อมูลร้าน'!$A$2:$B$51,2,FALSE),"") -> ร้านคำนิยม | C8: T0 | E8: 4 | F8: 3 | G8: 1 | H8: 4 | I8: 3 | J8: 3 | K8: 3 | L8: 3 | M8: 4 | N8: 2 | O8: 1 | P8: 4 | Q8: 4 | R8: 4 | S8: 4 | T8: 4 | U8: 4 | V8: 3 | W8: 4 | X8: 3 | Y8: 4 | Z8: 4 | AA8: 4 | AB8: 4 | AC8: 4 | AD8: 4 | AE8: 2 | AF8: 3 | AG8: 2 | AH8: 1 | AI8: 3 | AJ8: 3 | AK8: 3 | AL8: 2 | AM8: 2 | AN8: 2 | AO8: 3 | AP8: 4 | AQ8: 2 | AR8: 3 | AS8: 4 | AT8: 4 | AU8: 2 | AV8: 4 | AW8: 3 | AX8: 4 | AY8: 4 | AZ8: 4 | BA8: 4 | BB8: 4 | BC8: =COUNT(E8:BB8)/50 -> 1 | BD8: =SUM(E8:BB8) -> 161 | BE8: =BD8/200 -> 0.805 | BF8: =SUM(E8:K8)/(7*4)*0.12+SUM(L8:R8)/(7*4)*0.15+SUM(S8:X8)/(6*4)*0.1+SUM(Y8:AE8)/(7*4)*0.13+SUM(AF8:AL8)/(7*4)*0.2+SUM(AM8:AS8)/(7*4)*0.18+SUM(AT8:AX8)/(5*4)*0.05+SUM(AY8:BB8)/(4*4)*0.07 -> 0.7827381 | BG8: =COUNTIFS(E8:BB8,">=0",E8:BB8,"<=1") -> 3 | BH8: =IF(BC8=0,"ยังไม่ประเมิน",IF(BF8>=0.8,"ดีมาก",IF(BF8>=0.65,"ดี",IF(BF8>=0.5,"ต้องพัฒนา","เร่งแก้ไข")))) -> ดี | BI8: =IF(BC8=0,"ยังไม่ประเมิน",INDEX($BJ$1:$BQ$1,1,MATCH(MIN(BJ8:BQ8),BJ8:BQ8,0))) -> มิติ 5 | BJ8: =SUM(E8:K8)/(7*4) -> 0.75 | BK8: =SUM(L8:R8)/(7*4) -> 0.78571429 | BL8: =SUM(S8:X8)/(6*4) -> 0.91666667 | BM8: =SUM(Y8:AE8)/(7*4) -> 0.92857143 | BN8: =SUM(AF8:AL8)/(7*4) -> 0.60714286 | BO8: =SUM(AM8:AS8)/(7*4) -> 0.71428571 | BP8: =SUM(AT8:AX8)/(5*4) -> 0.85 | BQ8: =SUM(AY8:BB8)/(4*4) -> 1
A9: RAP69-008 | B9: =IFERROR(VLOOKUP(A9,'01_ข้อมูลร้าน'!$A$2:$B$51,2,FALSE),"") -> ร้านอรวรรณบ้านเพ | C9: T0 | E9: 4 | F9: 0 | G9: 0 | H9: 1 | I9: 2 | J9: 2 | K9: 3 | L9: 0 | M9: 0 | N9: 0 | O9: 0 | P9: 0 | Q9: 4 | R9: 0 | S9: 1 | T9: 2 | U9: 4 | V9: 1 | W9: 1 | X9: 1 | Y9: 0 | Z9: 4 | AA9: 4 | AB9: 1 | AC9: 1 | AD9: 1 | AE9: 1 | AF9: 1 | AG9: 2 | AH9: 0 | AI9: 1 | AJ9: 2 | AK9: 2 | AL9: 1 | AM9: 1 | AN9: 1 | AO9: 3 | AP9: 0 | AQ9: 0 | AR9: 3 | AS9: 3 | AT9: 3 | AU9: 4 | AV9: 3 | AW9: 2 | AX9: 3 | AY9: 4 | AZ9: 4 | BA9: 3 | BB9: 3 | BC9: =COUNT(E9:BB9)/50 -> 1 | BD9: =SUM(E9:BB9) -> 87 | BE9: =BD9/200 -> 0.435 | BF9: =SUM(E9:K9)/(7*4)*0.12+SUM(L9:R9)/(7*4)*0.15+SUM(S9:X9)/(6*4)*0.1+SUM(Y9:AE9)/(7*4)*0.13+SUM(AF9:AL9)/(7*4)*0.2+SUM(AM9:AS9)/(7*4)*0.18+SUM(AT9:AX9)/(5*4)*0.05+SUM(AY9:BB9)/(4*4)*0.07 -> 0.4039881 | BG9: =COUNTIFS(E9:BB9,">=0",E9:BB9,"<=1") -> 26 | BH9: =IF(BC9=0,"ยังไม่ประเมิน",IF(BF9>=0.8,"ดีมาก",IF(BF9>=0.65,"ดี",IF(BF9>=0.5,"ต้องพัฒนา","เร่งแก้ไข")))) -> เร่งแก้ไข | BI9: =IF(BC9=0,"ยังไม่ประเมิน",INDEX($BJ$1:$BQ$1,1,MATCH(MIN(BJ9:BQ9),BJ9:BQ9,0))) -> มิติ 2 | BJ9: =SUM(E9:K9)/(7*4) -> 0.42857143 | BK9: =SUM(L9:R9)/(7*4) -> 0.14285714 | BL9: =SUM(S9:X9)/(6*4) -> 0.41666667 | BM9: =SUM(Y9:AE9)/(7*4) -> 0.42857143 | BN9: =SUM(AF9:AL9)/(7*4) -> 0.32142857 | BO9: =SUM(AM9:AS9)/(7*4) -> 0.39285714 | BP9: =SUM(AT9:AX9)/(5*4) -> 0.75 | BQ9: =SUM(AY9:BB9)/(4*4) -> 0.875
A10: RAP69-009 | B10: =IFERROR(VLOOKUP(A10,'01_ข้อมูลร้าน'!$A$2:$B$51,2,FALSE),"") -> ครัวเดอมอง | C10: T0 | E10: 4 | F10: 3 | G10: 4 | H10: 2 | I10: 3 | J10: 2 | K10: 3 | L10: 0 | M10: 2 | N10: 0 | O10: 2 | P10: 0 | Q10: 4 | R10: 3 | S10: 4 | T10: 1 | U10: 2 | V10: 0 | W10: 1 | X10: 0 | Y10: 3 | Z10: 0 | AA10: 3 | AB10: 0 | AC10: 0 | AD10: 1 | AE10: 0 | AF10: 1 | AG10: 1 | AH10: 0 | AI10: 1 | AJ10: 2 | AK10: 2 | AL10: 1 | AM10: 1 | AN10: 0 | AO10: 3 | AP10: 0 | AQ10: 1 | AR10: 4 | AS10: 2 | AT10: 2 | AU10: 3 | AV10: 2 | AW10: 3 | AX10: 0 | AY10: 3 | AZ10: 4 | BA10: 3 | BB10: 3 | BC10: =COUNT(E10:BB10)/50 -> 1 | BD10: =SUM(E10:BB10) -> 89 | BE10: =BD10/200 -> 0.445 | BF10: =SUM(E10:K10)/(7*4)*0.12+SUM(L10:R10)/(7*4)*0.15+SUM(S10:X10)/(6*4)*0.1+SUM(Y10:AE10)/(7*4)*0.13+SUM(AF10:AL10)/(7*4)*0.2+SUM(AM10:AS10)/(7*4)*0.18+SUM(AT10:AX10)/(5*4)*0.05+SUM(AY10:BB10)/(4*4)*0.07 -> 0.42449405 | BG10: =COUNTIFS(E10:BB10,">=0",E10:BB10,"<=1") -> 22 | BH10: =IF(BC10=0,"ยังไม่ประเมิน",IF(BF10>=0.8,"ดีมาก",IF(BF10>=0.65,"ดี",IF(BF10>=0.5,"ต้องพัฒนา","เร่งแก้ไข")))) -> เร่งแก้ไข | BI10: =IF(BC10=0,"ยังไม่ประเมิน",INDEX($BJ$1:$BQ$1,1,MATCH(MIN(BJ10:BQ10),BJ10:BQ10,0))) -> มิติ 4 | BJ10: =SUM(E10:K10)/(7*4) -> 0.75 | BK10: =SUM(L10:R10)/(7*4) -> 0.39285714 | BL10: =SUM(S10:X10)/(6*4) -> 0.33333333 | BM10: =SUM(Y10:AE10)/(7*4) -> 0.25 | BN10: =SUM(AF10:AL10)/(7*4) -> 0.28571429 | BO10: =SUM(AM10:AS10)/(7*4) -> 0.39285714 | BP10: =SUM(AT10:AX10)/(5*4) -> 0.5 | BQ10: =SUM(AY10:BB10)/(4*4) -> 0.8125
A11: RAP69-010 | B11: =IFERROR(VLOOKUP(A11,'01_ข้อมูลร้าน'!$A$2:$B$51,2,FALSE),"") -> เรือนไทย พัทยา | C11: T0 | E11: 4 | F11: 1 | G11: 0 | H11: 1 | I11: 1 | J11: 3 | K11: 4 | L11: 2 | M11: 0 | N11: 4 | O11: 0 | P11: 2 | Q11: 4 | R11: 4 | AM11: 4 | AN11: 1 | AO11: 4 | AP11: 1 | AQ11: 0 | AR11: 4 | AS11: 4 | AT11: 4 | AU11: 3 | AV11: 4 | AW11: 2 | AX11: 4 | AY11: 4 | AZ11: 4 | BA11: 4 | BB11: 1 | BC11: =COUNT(E11:BB11)/50 -> 0.6 | BD11: =SUM(E11:BB11) -> 78 | BE11: =BD11/200 -> 0.39 | BF11: =SUM(E11:K11)/(7*4)*0.12+SUM(L11:R11)/(7*4)*0.15+SUM(S11:X11)/(6*4)*0.1+SUM(Y11:AE11)/(7*4)*0.13+SUM(AF11:AL11)/(7*4)*0.2+SUM(AM11:AS11)/(7*4)*0.18+SUM(AT11:AX11)/(5*4)*0.05+SUM(AY11:BB11)/(4*4)*0.07 -> 0.36080357 | BG11: =COUNTIFS(E11:BB11,">=0",E11:BB11,"<=1") -> 10 | BH11: =IF(BC11=0,"ยังไม่ประเมิน",IF(BF11>=0.8,"ดีมาก",IF(BF11>=0.65,"ดี",IF(BF11>=0.5,"ต้องพัฒนา","เร่งแก้ไข")))) -> เร่งแก้ไข | BI11: =IF(BC11=0,"ยังไม่ประเมิน",INDEX($BJ$1:$BQ$1,1,MATCH(MIN(BJ11:BQ11),BJ11:BQ11,0))) -> มิติ 3 | BJ11: =SUM(E11:K11)/(7*4) -> 0.5 | BK11: =SUM(L11:R11)/(7*4) -> 0.57142857 | BL11: =SUM(S11:X11)/(6*4) -> 0 | BM11: =SUM(Y11:AE11)/(7*4) -> 0 | BN11: =SUM(AF11:AL11)/(7*4) -> 0 | BO11: =SUM(AM11:AS11)/(7*4) -> 0.64285714 | BP11: =SUM(AT11:AX11)/(5*4) -> 0.85 | BQ11: =SUM(AY11:BB11)/(4*4) -> 0.8125
A12: RAP69-011 | B12: =IFERROR(VLOOKUP(A12,'01_ข้อมูลร้าน'!$A$2:$B$51,2,FALSE),"") -> ร้านอาหาร ทะเลลานโพธิ์ ซีฟู้ด | C12: T0 | E12: 3 | F12: 3 | G12: 3 | H12: 1 | I12: 2 | J12: 3 | K12: 1 | L12: 4 | M12: 4 | N12: 4 | O12: 3 | P12: 0 | Q12: 4 | R12: 3 | S12: 4 | T12: 3 | U12: 3 | V12: 2 | W12: 4 | X12: 1 | Y12: 3 | Z12: 2 | AA12: 3 | AB12: 2 | AC12: 1 | AD12: 2 | AE12: 3 | AF12: 2 | AG12: 3 | AH12: 2 | AI12: 2 | AJ12: 3 | AK12: 2 | AL12: 2 | AM12: 4 | AN12: 2 | AO12: 3 | AP12: 4 | AQ12: 3 | AR12: 4 | AS12: 2 | AT12: 3 | AU12: 2 | AV12: 3 | AW12: 3 | AX12: 2 | AY12: 3 | AZ12: 3 | BA12: 3 | BB12: 3 | BC12: =COUNT(E12:BB12)/50 -> 1 | BD12: =SUM(E12:BB12) -> 134 | BE12: =BD12/200 -> 0.67 | BF12: =SUM(E12:K12)/(7*4)*0.12+SUM(L12:R12)/(7*4)*0.15+SUM(S12:X12)/(6*4)*0.1+SUM(Y12:AE12)/(7*4)*0.13+SUM(AF12:AL12)/(7*4)*0.2+SUM(AM12:AS12)/(7*4)*0.18+SUM(AT12:AX12)/(5*4)*0.05+SUM(AY12:BB12)/(4*4)*0.07 -> 0.6722619 | BG12: =COUNTIFS(E12:BB12,">=0",E12:BB12,"<=1") -> 5 | BH12: =IF(BC12=0,"ยังไม่ประเมิน",IF(BF12>=0.8,"ดีมาก",IF(BF12>=0.65,"ดี",IF(BF12>=0.5,"ต้องพัฒนา","เร่งแก้ไข")))) -> ดี | BI12: =IF(BC12=0,"ยังไม่ประเมิน",INDEX($BJ$1:$BQ$1,1,MATCH(MIN(BJ12:BQ12),BJ12:BQ12,0))) -> มิติ 1 | BJ12: =SUM(E12:K12)/(7*4) -> 0.57142857 | BK12: =SUM(L12:R12)/(7*4) -> 0.78571429 | BL12: =SUM(S12:X12)/(6*4) -> 0.70833333 | BM12: =SUM(Y12:AE12)/(7*4) -> 0.57142857 | BN12: =SUM(AF12:AL12)/(7*4) -> 0.57142857 | BO12: =SUM(AM12:AS12)/(7*4) -> 0.78571429 | BP12: =SUM(AT12:AX12)/(5*4) -> 0.65 | BQ12: =SUM(AY12:BB12)/(4*4) -> 0.75
A13: RAP69-012 | B13: =IFERROR(VLOOKUP(A13,'01_ข้อมูลร้าน'!$A$2:$B$51,2,FALSE),"") -> นายกุ่ยไก่หุบบอน @เขาชีจรรย์ | C13: T0 | E13: 4 | F13: 2 | G13: 3 | H13: 1 | I13: 4 | J13: 1 | K13: 3 | L13: 3 | M13: 3 | N13: 3 | O13: 2 | P13: 3 | Q13: 3 | R13: 3 | S13: 4 | T13: 3 | U13: 4 | V13: 3 | W13: 2 | X13: 1 | Y13: 2 | Z13: 2 | AA13: 2 | AB13: 1 | AC13: 1 | AD13: 2 | AE13: 2 | AF13: 2 | AG13: 2 | AH13: 1 | AI13: 3 | AJ13: 3 | AK13: 3 | AL13: 3 | AM13: 3 | AN13: 3 | AO13: 3 | AP13: 3 | AQ13: 3 | AR13: 3 | AS13: 3 | AT13: 4 | AU13: 4 | AV13: 3 | AW13: 3 | AX13: 4 | AY13: 3 | AZ13: 3 | BA13: 3 | BB13: 2 | BC13: =COUNT(E13:BB13)/50 -> 1 | BD13: =SUM(E13:BB13) -> 134 | BE13: =BD13/200 -> 0.67 | BF13: =SUM(E13:K13)/(7*4)*0.12+SUM(L13:R13)/(7*4)*0.15+SUM(S13:X13)/(6*4)*0.1+SUM(Y13:AE13)/(7*4)*0.13+SUM(AF13:AL13)/(7*4)*0.2+SUM(AM13:AS13)/(7*4)*0.18+SUM(AT13:AX13)/(5*4)*0.05+SUM(AY13:BB13)/(4*4)*0.07 -> 0.6603869 | BG13: =COUNTIFS(E13:BB13,">=0",E13:BB13,"<=1") -> 6 | BH13: =IF(BC13=0,"ยังไม่ประเมิน",IF(BF13>=0.8,"ดีมาก",IF(BF13>=0.65,"ดี",IF(BF13>=0.5,"ต้องพัฒนา","เร่งแก้ไข")))) -> ดี | BI13: =IF(BC13=0,"ยังไม่ประเมิน",INDEX($BJ$1:$BQ$1,1,MATCH(MIN(BJ13:BQ13),BJ13:BQ13,0))) -> มิติ 4 | BJ13: =SUM(E13:K13)/(7*4) -> 0.64285714 | BK13: =SUM(L13:R13)/(7*4) -> 0.71428571 | BL13: =SUM(S13:X13)/(6*4) -> 0.70833333 | BM13: =SUM(Y13:AE13)/(7*4) -> 0.42857143 | BN13: =SUM(AF13:AL13)/(7*4) -> 0.60714286 | BO13: =SUM(AM13:AS13)/(7*4) -> 0.75 | BP13: =SUM(AT13:AX13)/(5*4) -> 0.9 | BQ13: =SUM(AY13:BB13)/(4*4) -> 0.6875
A14: RAP69-013 | B14: =IFERROR(VLOOKUP(A14,'01_ข้อมูลร้าน'!$A$2:$B$51,2,FALSE),"") -> บ้านสวนบางแสน | C14: T0 | E14: 4 | F14: 2 | G14: 2 | H14: 1 | I14: 2 | J14: 2 | K14: 1 | L14: 3 | M14: 2 | N14: 2 | O14: 1 | P14: 3 | Q14: 0 | R14: 3 | S14: 4 | T14: 3 | U14: 2 | V14: 0 | W14: 2 | X14: 2 | Y14: 3 | Z14: 3 | AA14: 2 | AB14: 1 | AC14: 1 | AD14: 1 | AE14: 1 | AF14: 1 | AG14: 2 | AH14: 3 | AI14: 4 | AJ14: 2 | AK14: 3 | AL14: 1 | AM14: 3 | AN14: 3 | AO14: 4 | AP14: 3 | AQ14: 1 | AR14: 4 | AS14: 3 | AT14: 3 | AU14: 3 | AV14: 1 | AW14: 3 | AX14: 0 | AY14: 3 | AZ14: 3 | BA14: 3 | BB14: 2 | BC14: =COUNT(E14:BB14)/50 -> 1 | BD14: =SUM(E14:BB14) -> 111 | BE14: =BD14/200 -> 0.555 | BF14: =SUM(E14:K14)/(7*4)*0.12+SUM(L14:R14)/(7*4)*0.15+SUM(S14:X14)/(6*4)*0.1+SUM(Y14:AE14)/(7*4)*0.13+SUM(AF14:AL14)/(7*4)*0.2+SUM(AM14:AS14)/(7*4)*0.18+SUM(AT14:AX14)/(5*4)*0.05+SUM(AY14:BB14)/(4*4)*0.07 -> 0.56729167 | BG14: =COUNTIFS(E14:BB14,">=0",E14:BB14,"<=1") -> 14 | BH14: =IF(BC14=0,"ยังไม่ประเมิน",IF(BF14>=0.8,"ดีมาก",IF(BF14>=0.65,"ดี",IF(BF14>=0.5,"ต้องพัฒนา","เร่งแก้ไข")))) -> ต้องพัฒนา | BI14: =IF(BC14=0,"ยังไม่ประเมิน",INDEX($BJ$1:$BQ$1,1,MATCH(MIN(BJ14:BQ14),BJ14:BQ14,0))) -> มิติ 4 | BJ14: =SUM(E14:K14)/(7*4) -> 0.5 | BK14: =SUM(L14:R14)/(7*4) -> 0.5 | BL14: =SUM(S14:X14)/(6*4) -> 0.54166667 | BM14: =SUM(Y14:AE14)/(7*4) -> 0.42857143 | BN14: =SUM(AF14:AL14)/(7*4) -> 0.57142857 | BO14: =SUM(AM14:AS14)/(7*4) -> 0.75 | BP14: =SUM(AT14:AX14)/(5*4) -> 0.5 | BQ14: =SUM(AY14:BB14)/(4*4) -> 0.6875
A15: RAP69-014 | B15: =IFERROR(VLOOKUP(A15,'01_ข้อมูลร้าน'!$A$2:$B$51,2,FALSE),"") -> สวนแววอรุณ | C15: T0 | E15: 4 | F15: 4 | G15: 0 | H15: 4 | I15: 0 | J15: 3 | K15: 3 | L15: 3 | M15: 3 | N15: 2 | O15: 2 | P15: 2 | Q15: 3 | R15: 3 | S15: 4 | T15: 3 | U15: 3 | V15: 3 | W15: 4 | X15: 1 | Y15: 2 | Z15: 2 | AA15: 3 | AB15: 2 | AC15: 3 | AD15: 2 | AE15: 3 | AF15: 3 | AG15: 2 | AH15: 3 | AI15: 3 | AJ15: 3 | AK15: 2 | AL15: 3 | AM15: 3 | AN15: 3 | AO15: 3 | AP15: 2 | AQ15: 3 | AR15: 2 | AS15: 2 | AT15: 4 | AU15: 2 | AV15: 3 | AW15: 2 | AX15: 1 | AY15: 3 | AZ15: 3 | BA15: 3 | BB15: 2 | BC15: =COUNT(E15:BB15)/50 -> 1 | BD15: =SUM(E15:BB15) -> 131 | BE15: =BD15/200 -> 0.655 | BF15: =SUM(E15:K15)/(7*4)*0.12+SUM(L15:R15)/(7*4)*0.15+SUM(S15:X15)/(6*4)*0.1+SUM(Y15:AE15)/(7*4)*0.13+SUM(AF15:AL15)/(7*4)*0.2+SUM(AM15:AS15)/(7*4)*0.18+SUM(AT15:AX15)/(5*4)*0.05+SUM(AY15:BB15)/(4*4)*0.07 -> 0.65705357 | BG15: =COUNTIFS(E15:BB15,">=0",E15:BB15,"<=1") -> 4 | BH15: =IF(BC15=0,"ยังไม่ประเมิน",IF(BF15>=0.8,"ดีมาก",IF(BF15>=0.65,"ดี",IF(BF15>=0.5,"ต้องพัฒนา","เร่งแก้ไข")))) -> ดี | BI15: =IF(BC15=0,"ยังไม่ประเมิน",INDEX($BJ$1:$BQ$1,1,MATCH(MIN(BJ15:BQ15),BJ15:BQ15,0))) -> มิติ 7 | BJ15: =SUM(E15:K15)/(7*4) -> 0.64285714 | BK15: =SUM(L15:R15)/(7*4) -> 0.64285714 | BL15: =SUM(S15:X15)/(6*4) -> 0.75 | BM15: =SUM(Y15:AE15)/(7*4) -> 0.60714286 | BN15: =SUM(AF15:AL15)/(7*4) -> 0.67857143 | BO15: =SUM(AM15:AS15)/(7*4) -> 0.64285714 | BP15: =SUM(AT15:AX15)/(5*4) -> 0.6 | BQ15: =SUM(AY15:BB15)/(4*4) -> 0.6875
A16: RAP69-015 | B16: =IFERROR(VLOOKUP(A16,'01_ข้อมูลร้าน'!$A$2:$B$51,2,FALSE),"") -> คุณอี๊ดกะเพราแซ่บจี้ด | C16: T0 | E16: 2 | F16: 2 | G16: 3 | H16: 1 | I16: 1 | J16: 1 | K16: 2 | L16: 1 | M16: 1 | N16: 2 | O16: 2 | P16: 3 | Q16: 2 | R16: 2 | S16: 1 | T16: 1 | U16: 2 | V16: 2 | W16: 1 | X16: 1 | Y16: 0 | Z16: 0 | AA16: 0 | AB16: 2 | AC16: 1 | AD16: 1 | AE16: 1 | AF16: 2 | AG16: 2 | AH16: 0 | AI16: 0 | AJ16: 2 | AK16: 2 | AL16: 4 | AM16: 1 | AN16: 2 | AO16: 3 | AP16: 2 | AQ16: 1 | AR16: 4 | AS16: 1 | AT16: 2 | AU16: 1 | AV16: 3 | AW16: 1 | AX16: 2 | AY16: 3 | AZ16: 3 | BA16: 3 | BB16: 2 | BC16: =COUNT(E16:BB16)/50 -> 1 | BD16: =SUM(E16:BB16) -> 84 | BE16: =BD16/200 -> 0.42 | BF16: =SUM(E16:K16)/(7*4)*0.12+SUM(L16:R16)/(7*4)*0.15+SUM(S16:X16)/(6*4)*0.1+SUM(Y16:AE16)/(7*4)*0.13+SUM(AF16:AL16)/(7*4)*0.2+SUM(AM16:AS16)/(7*4)*0.18+SUM(AT16:AX16)/(5*4)*0.05+SUM(AY16:BB16)/(4*4)*0.07 -> 0.42395833 | BG16: =COUNTIFS(E16:BB16,">=0",E16:BB16,"<=1") -> 22 | BH16: =IF(BC16=0,"ยังไม่ประเมิน",IF(BF16>=0.8,"ดีมาก",IF(BF16>=0.65,"ดี",IF(BF16>=0.5,"ต้องพัฒนา","เร่งแก้ไข")))) -> เร่งแก้ไข | BI16: =IF(BC16=0,"ยังไม่ประเมิน",INDEX($BJ$1:$BQ$1,1,MATCH(MIN(BJ16:BQ16),BJ16:BQ16,0))) -> มิติ 4 | BJ16: =SUM(E16:K16)/(7*4) -> 0.42857143 | BK16: =SUM(L16:R16)/(7*4) -> 0.46428571 | BL16: =SUM(S16:X16)/(6*4) -> 0.33333333 | BM16: =SUM(Y16:AE16)/(7*4) -> 0.17857143 | BN16: =SUM(AF16:AL16)/(7*4) -> 0.42857143 | BO16: =SUM(AM16:AS16)/(7*4) -> 0.5 | BP16: =SUM(AT16:AX16)/(5*4) -> 0.45 | BQ16: =SUM(AY16:BB16)/(4*4) -> 0.6875
A17: RAP69-016 | B17: =IFERROR(VLOOKUP(A17,'01_ข้อมูลร้าน'!$A$2:$B$51,2,FALSE),"") -> หมูสะเต๊ะอพอลโล | C17: T0 | BC17: =COUNT(E17:BB17)/50 -> 0 | BD17: =SUM(E17:BB17) -> 0 | BE17: =BD17/200 -> 0 | BF17: =SUM(E17:K17)/(7*4)*0.12+SUM(L17:R17)/(7*4)*0.15+SUM(S17:X17)/(6*4)*0.1+SUM(Y17:AE17)/(7*4)*0.13+SUM(AF17:AL17)/(7*4)*0.2+SUM(AM17:AS17)/(7*4)*0.18+SUM(AT17:AX17)/(5*4)*0.05+SUM(AY17:BB17)/(4*4)*0.07 -> 0 | BG17: =COUNTIFS(E17:BB17,">=0",E17:BB17,"<=1") -> 0 | BH17: =IF(BC17=0,"ยังไม่ประเมิน",IF(BF17>=0.8,"ดีมาก",IF(BF17>=0.65,"ดี",IF(BF17>=0.5,"ต้องพัฒนา","เร่งแก้ไข")))) -> ยังไม่ประเมิน | BI17: =IF(BC17=0,"ยังไม่ประเมิน",INDEX($BJ$1:$BQ$1,1,MATCH(MIN(BJ17:BQ17),BJ17:BQ17,0))) -> ยังไม่ประเมิน | BJ17: =SUM(E17:K17)/(7*4) -> 0 | BK17: =SUM(L17:R17)/(7*4) -> 0 | BL17: =SUM(S17:X17)/(6*4) -> 0 | BM17: =SUM(Y17:AE17)/(7*4) -> 0 | BN17: =SUM(AF17:AL17)/(7*4) -> 0 | BO17: =SUM(AM17:AS17)/(7*4) -> 0 | BP17: =SUM(AT17:AX17)/(5*4) -> 0 | BQ17: =SUM(AY17:BB17)/(4*4) -> 0
A18: RAP69-017 | B18: =IFERROR(VLOOKUP(A18,'01_ข้อมูลร้าน'!$A$2:$B$51,2,FALSE),"") -> วันวาน คาเฟ่ | C18: T0 | E18: 2 | F18: 1 | G18: 1 | H18: 2 | I18: 1 | J18: 2 | K18: 1 | L18: 3 | M18: 3 | N18: 2 | O18: 1 | P18: 2 | Q18: 0 | R18: 2 | S18: 3 | T18: 2 | U18: 2 | V18: 0 | W18: 2 | X18: 1 | Y18: 2 | Z18: 2 | AA18: 2 | AB18: 2 | AC18: 0 | AD18: 1 | AE18: 2 | AF18: 1 | AG18: 2 | AH18: 0 | AI18: 3 | AJ18: 3 | AK18: 2 | AL18: 1 | AM18: 2 | AN18: 2 | AO18: 2 | AP18: 2 | AQ18: 3 | AR18: 2 | AS18: 3 | AT18: 2 | AU18: 1 | AV18: 1 | AW18: 0 | AX18: 0 | AY18: 2 | AZ18: 2 | BA18: 2 | BB18: 2 | BC18: =COUNT(E18:BB18)/50 -> 1 | BD18: =SUM(E18:BB18) -> 84 | BE18: =BD18/200 -> 0.42 | BF18: =SUM(E18:K18)/(7*4)*0.12+SUM(L18:R18)/(7*4)*0.15+SUM(S18:X18)/(6*4)*0.1+SUM(Y18:AE18)/(7*4)*0.13+SUM(AF18:AL18)/(7*4)*0.2+SUM(AM18:AS18)/(7*4)*0.18+SUM(AT18:AX18)/(5*4)*0.05+SUM(AY18:BB18)/(4*4)*0.07 -> 0.43880952 | BG18: =COUNTIFS(E18:BB18,">=0",E18:BB18,"<=1") -> 17 | BH18: =IF(BC18=0,"ยังไม่ประเมิน",IF(BF18>=0.8,"ดีมาก",IF(BF18>=0.65,"ดี",IF(BF18>=0.5,"ต้องพัฒนา","เร่งแก้ไข")))) -> เร่งแก้ไข | BI18: =IF(BC18=0,"ยังไม่ประเมิน",INDEX($BJ$1:$BQ$1,1,MATCH(MIN(BJ18:BQ18),BJ18:BQ18,0))) -> มิติ 7 | BJ18: =SUM(E18:K18)/(7*4) -> 0.35714286 | BK18: =SUM(L18:R18)/(7*4) -> 0.46428571 | BL18: =SUM(S18:X18)/(6*4) -> 0.41666667 | BM18: =SUM(Y18:AE18)/(7*4) -> 0.39285714 | BN18: =SUM(AF18:AL18)/(7*4) -> 0.42857143 | BO18: =SUM(AM18:AS18)/(7*4) -> 0.57142857 | BP18: =SUM(AT18:AX18)/(5*4) -> 0.2 | BQ18: =SUM(AY18:BB18)/(4*4) -> 0.5
A19: RAP69-018 | B19: =IFERROR(VLOOKUP(A19,'01_ข้อมูลร้าน'!$A$2:$B$51,2,FALSE),"") -> อิ่มอุ่น ณ พัทยา | C19: T0 | E19: 2 | F19: 2 | G19: 2 | H19: 3 | I19: 2 | J19: 2 | K19: 2 | L19: 4 | M19: 2 | N19: 1 | O19: 2 | P19: 2 | Q19: 3 | R19: 2 | S19: 3 | T19: 3 | U19: 2 | V19: 2 | W19: 3 | X19: 1 | Y19: 3 | Z19: 2 | AA19: 3 | AB19: 2 | AC19: 2 | AD19: 0 | AE19: 3 | AF19: 2 | AG19: 2 | AH19: 3 | AI19: 3 | AJ19: 3 | AK19: 3 | AL19: 3 | AM19: 3 | AN19: 2 | AO19: 3 | AP19: 2 | AQ19: 1 | AR19: 2 | AS19: 3 | AT19: 2 | AU19: 3 | AV19: 2 | AW19: 2 | AX19: 0 | AY19: 3 | AZ19: 0 | BA19: 0 | BB19: 2 | BC19: =COUNT(E19:BB19)/50 -> 1 | BD19: =SUM(E19:BB19) -> 109 | BE19: =BD19/200 -> 0.545 | BF19: =SUM(E19:K19)/(7*4)*0.12+SUM(L19:R19)/(7*4)*0.15+SUM(S19:X19)/(6*4)*0.1+SUM(Y19:AE19)/(7*4)*0.13+SUM(AF19:AL19)/(7*4)*0.2+SUM(AM19:AS19)/(7*4)*0.18+SUM(AT19:AX19)/(5*4)*0.05+SUM(AY19:BB19)/(4*4)*0.07 -> 0.56092262 | BG19: =COUNTIFS(E19:BB19,">=0",E19:BB19,"<=1") -> 7 | BH19: =IF(BC19=0,"ยังไม่ประเมิน",IF(BF19>=0.8,"ดีมาก",IF(BF19>=0.65,"ดี",IF(BF19>=0.5,"ต้องพัฒนา","เร่งแก้ไข")))) -> ต้องพัฒนา | BI19: =IF(BC19=0,"ยังไม่ประเมิน",INDEX($BJ$1:$BQ$1,1,MATCH(MIN(BJ19:BQ19),BJ19:BQ19,0))) -> มิติ 8 | BJ19: =SUM(E19:K19)/(7*4) -> 0.53571429 | BK19: =SUM(L19:R19)/(7*4) -> 0.57142857 | BL19: =SUM(S19:X19)/(6*4) -> 0.58333333 | BM19: =SUM(Y19:AE19)/(7*4) -> 0.53571429 | BN19: =SUM(AF19:AL19)/(7*4) -> 0.67857143 | BO19: =SUM(AM19:AS19)/(7*4) -> 0.57142857 | BP19: =SUM(AT19:AX19)/(5*4) -> 0.45 | BQ19: =SUM(AY19:BB19)/(4*4) -> 0.3125
A20: RAP69-019 | B20: =IFERROR(VLOOKUP(A20,'01_ข้อมูลร้าน'!$A$2:$B$51,2,FALSE),"") -> ร้านอาหารบ่อทองบุรี | C20: T0 | E20: 4 | F20: 2 | G20: 3 | H20: 1 | I20: 3 | J20: 3 | K20: 2 | L20: 4 | M20: 4 | N20: 4 | O20: 4 | P20: 4 | Q20: 4 | R20: 3 | S20: 3 | T20: 3 | U20: 3 | V20: 2 | W20: 3 | X20: 3 | Y20: 3 | Z20: 3 | AA20: 3 | AB20: 2 | AC20: 3 | AD20: 2 | AE20: 3 | AF20: 1 | AG20: 1 | AH20: 2 | AI20: 4 | AJ20: 4 | AK20: 3 | AL20: 4 | AM20: 4 | AN20: 4 | AO20: 4 | AP20: 4 | AQ20: 4 | AR20: 3 | AS20: 3 | AT20: 3 | AU20: 4 | AV20: 3 | AW20: 3 | AX20: 2 | AY20: 3 | AZ20: 3 | BA20: 3 | BB20: 2 | BC20: =COUNT(E20:BB20)/50 -> 1 | BD20: =SUM(E20:BB20) -> 152 | BE20: =BD20/200 -> 0.76 | BF20: =SUM(E20:K20)/(7*4)*0.12+SUM(L20:R20)/(7*4)*0.15+SUM(S20:X20)/(6*4)*0.1+SUM(Y20:AE20)/(7*4)*0.13+SUM(AF20:AL20)/(7*4)*0.2+SUM(AM20:AS20)/(7*4)*0.18+SUM(AT20:AX20)/(5*4)*0.05+SUM(AY20:BB20)/(4*4)*0.07 -> 0.76931548 | BG20: =COUNTIFS(E20:BB20,">=0",E20:BB20,"<=1") -> 3 | BH20: =IF(BC20=0,"ยังไม่ประเมิน",IF(BF20>=0.8,"ดีมาก",IF(BF20>=0.65,"ดี",IF(BF20>=0.5,"ต้องพัฒนา","เร่งแก้ไข")))) -> ดี | BI20: =IF(BC20=0,"ยังไม่ประเมิน",INDEX($BJ$1:$BQ$1,1,MATCH(MIN(BJ20:BQ20),BJ20:BQ20,0))) -> มิติ 1 | BJ20: =SUM(E20:K20)/(7*4) -> 0.64285714 | BK20: =SUM(L20:R20)/(7*4) -> 0.96428571 | BL20: =SUM(S20:X20)/(6*4) -> 0.70833333 | BM20: =SUM(Y20:AE20)/(7*4) -> 0.67857143 | BN20: =SUM(AF20:AL20)/(7*4) -> 0.67857143 | BO20: =SUM(AM20:AS20)/(7*4) -> 0.92857143 | BP20: =SUM(AT20:AX20)/(5*4) -> 0.75 | BQ20: =SUM(AY20:BB20)/(4*4) -> 0.6875
A21: RAP69-020 | B21: =IFERROR(VLOOKUP(A21,'01_ข้อมูลร้าน'!$A$2:$B$51,2,FALSE),"") -> ผัดไทยคาเฟ่แม่วรรณา | C21: T0 | E21: 3 | F21: 4 | G21: 4 | H21: 2 | I21: 2 | J21: 2 | K21: 2 | L21: 3 | M21: 3 | N21: 2 | O21: 2 | P21: 3 | Q21: 3 | R21: 3 | S21: 4 | T21: 0 | U21: 2 | V21: 2 | W21: 2 | X21: 1 | Y21: 3 | Z21: 2 | AA21: 3 | AB21: 2 | AC21: 1 | AD21: 2 | AE21: 2 | AF21: 0 | AG21: 1 | AH21: 0 | AI21: 3 | AJ21: 3 | AK21: 2 | AL21: 2 | AM21: 3 | AN21: 3 | AO21: 3 | AP21: 2 | AQ21: 2 | AR21: 3 | AS21: 3 | AT21: 3 | AU21: 3 | AV21: 2 | AW21: 0 | AX21: 0 | AY21: 2 | AZ21: 3 | BA21: 3 | BB21: 2 | BC21: =COUNT(E21:BB21)/50 -> 1 | BD21: =SUM(E21:BB21) -> 112 | BE21: =BD21/200 -> 0.56 | BF21: =SUM(E21:K21)/(7*4)*0.12+SUM(L21:R21)/(7*4)*0.15+SUM(S21:X21)/(6*4)*0.1+SUM(Y21:AE21)/(7*4)*0.13+SUM(AF21:AL21)/(7*4)*0.2+SUM(AM21:AS21)/(7*4)*0.18+SUM(AT21:AX21)/(5*4)*0.05+SUM(AY21:BB21)/(4*4)*0.07 -> 0.56315476 | BG21: =COUNTIFS(E21:BB21,">=0",E21:BB21,"<=1") -> 8 | BH21: =IF(BC21=0,"ยังไม่ประเมิน",IF(BF21>=0.8,"ดีมาก",IF(BF21>=0.65,"ดี",IF(BF21>=0.5,"ต้องพัฒนา","เร่งแก้ไข")))) -> ต้องพัฒนา | BI21: =IF(BC21=0,"ยังไม่ประเมิน",INDEX($BJ$1:$BQ$1,1,MATCH(MIN(BJ21:BQ21),BJ21:BQ21,0))) -> มิติ 5 | BJ21: =SUM(E21:K21)/(7*4) -> 0.67857143 | BK21: =SUM(L21:R21)/(7*4) -> 0.67857143 | BL21: =SUM(S21:X21)/(6*4) -> 0.45833333 | BM21: =SUM(Y21:AE21)/(7*4) -> 0.53571429 | BN21: =SUM(AF21:AL21)/(7*4) -> 0.39285714 | BO21: =SUM(AM21:AS21)/(7*4) -> 0.67857143 | BP21: =SUM(AT21:AX21)/(5*4) -> 0.4 | BQ21: =SUM(AY21:BB21)/(4*4) -> 0.625
A22: RAP69-021 | B22: =IFERROR(VLOOKUP(A22,'01_ข้อมูลร้าน'!$A$2:$B$51,2,FALSE),"") -> Recharge Cafa | C22: T0 | E22: 2 | F22: 2 | G22: 2 | H22: 0 | I22: 1 | J22: 2 | K22: 1 | L22: 3 | M22: 3 | N22: 1 | O22: 1 | P22: 2 | Q22: 1 | R22: 2 | S22: 0 | T22: 2 | U22: 2 | V22: 2 | W22: 2 | X22: 1 | Y22: 1 | Z22: 2 | AA22: 2 | AB22: 1 | AC22: 2 | AD22: 2 | AE22: 2 | AF22: 2 | AG22: 1 | AH22: 3 | AI22: 2 | AJ22: 2 | AK22: 2 | AL22: 2 | AM22: 2 | AN22: 2 | AO22: 3 | AP22: 2 | AQ22: 2 | AR22: 3 | AS22: 2 | AT22: 1 | AU22: 1 | AV22: 2 | AW22: 0 | AX22: 0 | AY22: 3 | AZ22: 3 | BA22: 2 | BB22: 1 | BC22: =COUNT(E22:BB22)/50 -> 1 | BD22: =SUM(E22:BB22) -> 87 | BE22: =BD22/200 -> 0.435 | BF22: =SUM(E22:K22)/(7*4)*0.12+SUM(L22:R22)/(7*4)*0.15+SUM(S22:X22)/(6*4)*0.1+SUM(Y22:AE22)/(7*4)*0.13+SUM(AF22:AL22)/(7*4)*0.2+SUM(AM22:AS22)/(7*4)*0.18+SUM(AT22:AX22)/(5*4)*0.05+SUM(AY22:BB22)/(4*4)*0.07 -> 0.45794643 | BG22: =COUNTIFS(E22:BB22,">=0",E22:BB22,"<=1") -> 16 | BH22: =IF(BC22=0,"ยังไม่ประเมิน",IF(BF22>=0.8,"ดีมาก",IF(BF22>=0.65,"ดี",IF(BF22>=0.5,"ต้องพัฒนา","เร่งแก้ไข")))) -> เร่งแก้ไข | BI22: =IF(BC22=0,"ยังไม่ประเมิน",INDEX($BJ$1:$BQ$1,1,MATCH(MIN(BJ22:BQ22),BJ22:BQ22,0))) -> มิติ 7 | BJ22: =SUM(E22:K22)/(7*4) -> 0.35714286 | BK22: =SUM(L22:R22)/(7*4) -> 0.46428571 | BL22: =SUM(S22:X22)/(6*4) -> 0.375 | BM22: =SUM(Y22:AE22)/(7*4) -> 0.42857143 | BN22: =SUM(AF22:AL22)/(7*4) -> 0.5 | BO22: =SUM(AM22:AS22)/(7*4) -> 0.57142857 | BP22: =SUM(AT22:AX22)/(5*4) -> 0.2 | BQ22: =SUM(AY22:BB22)/(4*4) -> 0.5625
A23: RAP69-022 | B23: =IFERROR(VLOOKUP(A23,'01_ข้อมูลร้าน'!$A$2:$B$51,2,FALSE),"") -> หมึกสดริมเล | C23: T0 | E23: 4 | F23: 4 | G23: 3 | H23: 3 | I23: 3 | J23: 4 | K23: 4 | L23: 2 | M23: 3 | N23: 4 | O23: 4 | P23: 4 | Q23: 4 | R23: 2 | S23: 4 | T23: 4 | U23: 4 | V23: 4 | W23: 4 | X23: 4 | Y23: 4 | Z23: 4 | AA23: 4 | AB23: 4 | AC23: 4 | AD23: 4 | AE23: 4 | AF23: 4 | AG23: 4 | AH23: 4 | AI23: 4 | AJ23: 4 | AK23: 4 | AL23: 4 | AM23: 4 | AN23: 4 | AO23: 3 | AP23: 4 | AQ23: 3 | AR23: 4 | AS23: 4 | AT23: 4 | AU23: 4 | AV23: 3 | AW23: 1 | AX23: 1 | AY23: 4 | AZ23: 4 | BA23: 4 | BB23: 3 | BC23: =COUNT(E23:BB23)/50 -> 1 | BD23: =SUM(E23:BB23) -> 182 | BE23: =BD23/200 -> 0.91 | BF23: =SUM(E23:K23)/(7*4)*0.12+SUM(L23:R23)/(7*4)*0.15+SUM(S23:X23)/(6*4)*0.1+SUM(Y23:AE23)/(7*4)*0.13+SUM(AF23:AL23)/(7*4)*0.2+SUM(AM23:AS23)/(7*4)*0.18+SUM(AT23:AX23)/(5*4)*0.05+SUM(AY23:BB23)/(4*4)*0.07 -> 0.925625 | BG23: =COUNTIFS(E23:BB23,">=0",E23:BB23,"<=1") -> 2 | BH23: =IF(BC23=0,"ยังไม่ประเมิน",IF(BF23>=0.8,"ดีมาก",IF(BF23>=0.65,"ดี",IF(BF23>=0.5,"ต้องพัฒนา","เร่งแก้ไข")))) -> ดีมาก | BI23: =IF(BC23=0,"ยังไม่ประเมิน",INDEX($BJ$1:$BQ$1,1,MATCH(MIN(BJ23:BQ23),BJ23:BQ23,0))) -> มิติ 7 | BJ23: =SUM(E23:K23)/(7*4) -> 0.89285714 | BK23: =SUM(L23:R23)/(7*4) -> 0.82142857 | BL23: =SUM(S23:X23)/(6*4) -> 1 | BM23: =SUM(Y23:AE23)/(7*4) -> 1 | BN23: =SUM(AF23:AL23)/(7*4) -> 1 | BO23: =SUM(AM23:AS23)/(7*4) -> 0.92857143 | BP23: =SUM(AT23:AX23)/(5*4) -> 0.65 | BQ23: =SUM(AY23:BB23)/(4*4) -> 0.9375
A24: RAP69-023 | B24: =IFERROR(VLOOKUP(A24,'01_ข้อมูลร้าน'!$A$2:$B$51,2,FALSE),"") -> บ้านแมะคาเฟ่ | C24: T0 | E24: 3 | F24: 4 | G24: 4 | H24: 4 | I24: 4 | J24: 3 | K24: 2 | L24: 3 | M24: 3 | N24: 3 | O24: 1 | P24: 2 | Q24: 2 | R24: 1 | S24: 2 | T24: 3 | U24: 2 | V24: 3 | W24: 3 | X24: 3 | Y24: 4 | Z24: 4 | AA24: 4 | AB24: 3 | AC24: 1 | AD24: 4 | AE24: 4 | AF24: 3 | AG24: 4 | AH24: 4 | AI24: 4 | AJ24: 4 | AK24: 3 | AL24: 2 | AM24: 3 | AN24: 4 | AO24: 4 | AP24: 3 | AQ24: 4 | AR24: 3 | AS24: 3 | AT24: 3 | AU24: 4 | AV24: 4 | AW24: 4 | AX24: 4 | AY24: 3 | AZ24: 4 | BA24: 4 | BB24: 3 | BC24: =COUNT(E24:BB24)/50 -> 1 | BD24: =SUM(E24:BB24) -> 160 | BE24: =BD24/200 -> 0.8 | BF24: =SUM(E24:K24)/(7*4)*0.12+SUM(L24:R24)/(7*4)*0.15+SUM(S24:X24)/(6*4)*0.1+SUM(Y24:AE24)/(7*4)*0.13+SUM(AF24:AL24)/(7*4)*0.2+SUM(AM24:AS24)/(7*4)*0.18+SUM(AT24:AX24)/(5*4)*0.05+SUM(AY24:BB24)/(4*4)*0.07 -> 0.79577381 | BG24: =COUNTIFS(E24:BB24,">=0",E24:BB24,"<=1") -> 3 | BH24: =IF(BC24=0,"ยังไม่ประเมิน",IF(BF24>=0.8,"ดีมาก",IF(BF24>=0.65,"ดี",IF(BF24>=0.5,"ต้องพัฒนา","เร่งแก้ไข")))) -> ดี | BI24: =IF(BC24=0,"ยังไม่ประเมิน",INDEX($BJ$1:$BQ$1,1,MATCH(MIN(BJ24:BQ24),BJ24:BQ24,0))) -> มิติ 2 | BJ24: =SUM(E24:K24)/(7*4) -> 0.85714286 | BK24: =SUM(L24:R24)/(7*4) -> 0.53571429 | BL24: =SUM(S24:X24)/(6*4) -> 0.66666667 | BM24: =SUM(Y24:AE24)/(7*4) -> 0.85714286 | BN24: =SUM(AF24:AL24)/(7*4) -> 0.85714286 | BO24: =SUM(AM24:AS24)/(7*4) -> 0.85714286 | BP24: =SUM(AT24:AX24)/(5*4) -> 0.95 | BQ24: =SUM(AY24:BB24)/(4*4) -> 0.875
A25: RAP69-024 | B25: =IFERROR(VLOOKUP(A25,'01_ข้อมูลร้าน'!$A$2:$B$51,2,FALSE),"") -> ร้านทองม้วนคุณใบ้ | C25: T0 | E25: 3 | F25: 3 | G25: 3 | H25: 4 | I25: 3 | J25: 3 | K25: 2 | L25: 2 | M25: 2 | N25: 4 | O25: 4 | P25: 4 | Q25: 3 | R25: 3 | S25: 4 | T25: 3 | U25: 3 | V25: 3 | W25: 3 | X25: 2 | Y25: 3 | Z25: 3 | AA25: 3 | AB25: 2 | AC25: 2 | AD25: 2 | AE25: 1 | AF25: 3 | AG25: 2 | AH25: 3 | AI25: 3 | AJ25: 3 | AK25: 3 | AL25: 3 | AM25: 1 | AN25: 2 | AO25: 4 | AP25: 3 | AQ25: 2 | AR25: 3 | AS25: 3 | AT25: 4 | AU25: 3 | AV25: 2 | AW25: 4 | AX25: 3 | AY25: 2 | AZ25: 3 | BA25: 3 | BB25: 3 | BC25: =COUNT(E25:BB25)/50 -> 1 | BD25: =SUM(E25:BB25) -> 142 | BE25: =BD25/200 -> 0.71 | BF25: =SUM(E25:K25)/(7*4)*0.12+SUM(L25:R25)/(7*4)*0.15+SUM(S25:X25)/(6*4)*0.1+SUM(Y25:AE25)/(7*4)*0.13+SUM(AF25:AL25)/(7*4)*0.2+SUM(AM25:AS25)/(7*4)*0.18+SUM(AT25:AX25)/(5*4)*0.05+SUM(AY25:BB25)/(4*4)*0.07 -> 0.70383929 | BG25: =COUNTIFS(E25:BB25,">=0",E25:BB25,"<=1") -> 2 | BH25: =IF(BC25=0,"ยังไม่ประเมิน",IF(BF25>=0.8,"ดีมาก",IF(BF25>=0.65,"ดี",IF(BF25>=0.5,"ต้องพัฒนา","เร่งแก้ไข")))) -> ดี | BI25: =IF(BC25=0,"ยังไม่ประเมิน",INDEX($BJ$1:$BQ$1,1,MATCH(MIN(BJ25:BQ25),BJ25:BQ25,0))) -> มิติ 4 | BJ25: =SUM(E25:K25)/(7*4) -> 0.75 | BK25: =SUM(L25:R25)/(7*4) -> 0.78571429 | BL25: =SUM(S25:X25)/(6*4) -> 0.75 | BM25: =SUM(Y25:AE25)/(7*4) -> 0.57142857 | BN25: =SUM(AF25:AL25)/(7*4) -> 0.71428571 | BO25: =SUM(AM25:AS25)/(7*4) -> 0.64285714 | BP25: =SUM(AT25:AX25)/(5*4) -> 0.8 | BQ25: =SUM(AY25:BB25)/(4*4) -> 0.6875
A26: RAP69-025 | B26: =IFERROR(VLOOKUP(A26,'01_ข้อมูลร้าน'!$A$2:$B$51,2,FALSE),"") -> ร้านไชโย | C26: T0 | BC26: =COUNT(E26:BB26)/50 -> 0 | BD26: =SUM(E26:BB26) -> 0 | BE26: =BD26/200 -> 0 | BF26: =SUM(E26:K26)/(7*4)*0.12+SUM(L26:R26)/(7*4)*0.15+SUM(S26:X26)/(6*4)*0.1+SUM(Y26:AE26)/(7*4)*0.13+SUM(AF26:AL26)/(7*4)*0.2+SUM(AM26:AS26)/(7*4)*0.18+SUM(AT26:AX26)/(5*4)*0.05+SUM(AY26:BB26)/(4*4)*0.07 -> 0 | BG26: =COUNTIFS(E26:BB26,">=0",E26:BB26,"<=1") -> 0 | BH26: =IF(BC26=0,"ยังไม่ประเมิน",IF(BF26>=0.8,"ดีมาก",IF(BF26>=0.65,"ดี",IF(BF26>=0.5,"ต้องพัฒนา","เร่งแก้ไข")))) -> ยังไม่ประเมิน | BI26: =IF(BC26=0,"ยังไม่ประเมิน",INDEX($BJ$1:$BQ$1,1,MATCH(MIN(BJ26:BQ26),BJ26:BQ26,0))) -> ยังไม่ประเมิน | BJ26: =SUM(E26:K26)/(7*4) -> 0 | BK26: =SUM(L26:R26)/(7*4) -> 0 | BL26: =SUM(S26:X26)/(6*4) -> 0 | BM26: =SUM(Y26:AE26)/(7*4) -> 0 | BN26: =SUM(AF26:AL26)/(7*4) -> 0 | BO26: =SUM(AM26:AS26)/(7*4) -> 0 | BP26: =SUM(AT26:AX26)/(5*4) -> 0 | BQ26: =SUM(AY26:BB26)/(4*4) -> 0
A27: RAP69-026 | B27: =IFERROR(VLOOKUP(A27,'01_ข้อมูลร้าน'!$A$2:$B$51,2,FALSE),"") -> ก๋วยเตี๋ยวปากหม้อ เกวียนนิยม | C27: T0 | E27: 4 | F27: 4 | G27: 1 | H27: 3 | I27: 4 | J27: 3 | K27: 3 | L27: 4 | M27: 3 | N27: 4 | O27: 3 | P27: 4 | Q27: 4 | R27: 4 | S27: 4 | T27: 4 | U27: 4 | V27: 4 | W27: 3 | X27: 2 | Y27: 4 | Z27: 4 | AA27: 4 | AB27: 4 | AC27: 3 | AD27: 3 | AE27: 3 | AF27: 3 | AG27: 3 | AH27: 4 | AI27: 4 | AJ27: 4 | AK27: 2 | AL27: 3 | AM27: 1 | AN27: 1 | AO27: 3 | AP27: 1 | AQ27: 0 | AR27: 1 | AS27: 3 | AT27: 4 | AU27: 3 | AV27: 4 | AW27: 0 | AX27: 4 | AY27: 4 | AZ27: 4 | BA27: 4 | BB27: 4 | BC27: =COUNT(E27:BB27)/50 -> 1 | BD27: =SUM(E27:BB27) -> 158 | BE27: =BD27/200 -> 0.79 | BF27: =SUM(E27:K27)/(7*4)*0.12+SUM(L27:R27)/(7*4)*0.15+SUM(S27:X27)/(6*4)*0.1+SUM(Y27:AE27)/(7*4)*0.13+SUM(AF27:AL27)/(7*4)*0.2+SUM(AM27:AS27)/(7*4)*0.18+SUM(AT27:AX27)/(5*4)*0.05+SUM(AY27:BB27)/(4*4)*0.07 -> 0.77321429 | BG27: =COUNTIFS(E27:BB27,">=0",E27:BB27,"<=1") -> 7 | BH27: =IF(BC27=0,"ยังไม่ประเมิน",IF(BF27>=0.8,"ดีมาก",IF(BF27>=0.65,"ดี",IF(BF27>=0.5,"ต้องพัฒนา","เร่งแก้ไข")))) -> ดี | BI27: =IF(BC27=0,"ยังไม่ประเมิน",INDEX($BJ$1:$BQ$1,1,MATCH(MIN(BJ27:BQ27),BJ27:BQ27,0))) -> มิติ 6 | BJ27: =SUM(E27:K27)/(7*4) -> 0.78571429 | BK27: =SUM(L27:R27)/(7*4) -> 0.92857143 | BL27: =SUM(S27:X27)/(6*4) -> 0.875 | BM27: =SUM(Y27:AE27)/(7*4) -> 0.89285714 | BN27: =SUM(AF27:AL27)/(7*4) -> 0.82142857 | BO27: =SUM(AM27:AS27)/(7*4) -> 0.35714286 | BP27: =SUM(AT27:AX27)/(5*4) -> 0.75 | BQ27: =SUM(AY27:BB27)/(4*4) -> 1
A28: RAP69-027 | B28: =IFERROR(VLOOKUP(A28,'01_ข้อมูลร้าน'!$A$2:$B$51,2,FALSE),"") -> Chatrium Golf Resort Soidao | C28: T0 | E28: 4 | F28: 4 | G28: 2 | H28: 3 | I28: 4 | J28: 4 | K28: 3 | L28: 4 | M28: 4 | N28: 4 | O28: 4 | P28: 4 | Q28: 3 | R28: 2 | S28: 4 | T28: 3 | U28: 2 | V28: 2 | W28: 2 | X28: 2 | Y28: 3 | Z28: 4 | AA28: 2 | AB28: 0 | AC28: 2 | AD28: 4 | AE28: 3 | AF28: 2 | AG28: 3 | AH28: 4 | AI28: 4 | AJ28: 3 | AK28: 3 | AL28: 3 | AM28: 4 | AN28: 4 | AO28: 3 | AP28: 4 | AQ28: 4 | AR28: 2 | AS28: 2 | AT28: 4 | AU28: 4 | AV28: 4 | AW28: 4 | AX28: 4 | AY28: 4 | AZ28: 4 | BA28: 3 | BB28: 2 | BC28: =COUNT(E28:BB28)/50 -> 1 | BD28: =SUM(E28:BB28) -> 160 | BE28: =BD28/200 -> 0.8 | BF28: =SUM(E28:K28)/(7*4)*0.12+SUM(L28:R28)/(7*4)*0.15+SUM(S28:X28)/(6*4)*0.1+SUM(Y28:AE28)/(7*4)*0.13+SUM(AF28:AL28)/(7*4)*0.2+SUM(AM28:AS28)/(7*4)*0.18+SUM(AT28:AX28)/(5*4)*0.05+SUM(AY28:BB28)/(4*4)*0.07 -> 0.79473214 | BG28: =COUNTIFS(E28:BB28,">=0",E28:BB28,"<=1") -> 1 | BH28: =IF(BC28=0,"ยังไม่ประเมิน",IF(BF28>=0.8,"ดีมาก",IF(BF28>=0.65,"ดี",IF(BF28>=0.5,"ต้องพัฒนา","เร่งแก้ไข")))) -> ดี | BI28: =IF(BC28=0,"ยังไม่ประเมิน",INDEX($BJ$1:$BQ$1,1,MATCH(MIN(BJ28:BQ28),BJ28:BQ28,0))) -> มิติ 3 | BJ28: =SUM(E28:K28)/(7*4) -> 0.85714286 | BK28: =SUM(L28:R28)/(7*4) -> 0.89285714 | BL28: =SUM(S28:X28)/(6*4) -> 0.625 | BM28: =SUM(Y28:AE28)/(7*4) -> 0.64285714 | BN28: =SUM(AF28:AL28)/(7*4) -> 0.78571429 | BO28: =SUM(AM28:AS28)/(7*4) -> 0.82142857 | BP28: =SUM(AT28:AX28)/(5*4) -> 1 | BQ28: =SUM(AY28:BB28)/(4*4) -> 0.8125
A29: RAP69-028 | B29: =IFERROR(VLOOKUP(A29,'01_ข้อมูลร้าน'!$A$2:$B$51,2,FALSE),"") -> มาเว้า MA WAO | C29: T0 | E29: 0 | F29: 0 | G29: 0 | H29: 0 | I29: 0 | J29: 0 | K29: 0 | L29: 0 | M29: 0 | N29: 0 | O29: 0 | P29: 0 | Q29: 0 | R29: 0 | S29: 0 | T29: 0 | U29: 0 | V29: 0 | W29: 0 | X29: 0 | Y29: 0 | Z29: 0 | AA29: 0 | AB29: 0 | AC29: 0 | AD29: 0 | AE29: 0 | AF29: 0 | AG29: 0 | AH29: 0 | AI29: 0 | AJ29: 0 | AK29: 0 | AL29: 0 | AM29: 0 | AN29: 0 | AO29: 0 | AP29: 0 | AQ29: 0 | AR29: 0 | AS29: 0 | AT29: 0 | AU29: 0 | AV29: 0 | AW29: 0 | AX29: 0 | AY29: 0 | AZ29: 0 | BA29: 0 | BB29: 0 | BC29: =COUNT(E29:BB29)/50 -> 1 | BD29: =SUM(E29:BB29) -> 0 | BE29: =BD29/200 -> 0 | BF29: =SUM(E29:K29)/(7*4)*0.12+SUM(L29:R29)/(7*4)*0.15+SUM(S29:X29)/(6*4)*0.1+SUM(Y29:AE29)/(7*4)*0.13+SUM(AF29:AL29)/(7*4)*0.2+SUM(AM29:AS29)/(7*4)*0.18+SUM(AT29:AX29)/(5*4)*0.05+SUM(AY29:BB29)/(4*4)*0.07 -> 0 | BG29: =COUNTIFS(E29:BB29,">=0",E29:BB29,"<=1") -> 50 | BH29: =IF(BC29=0,"ยังไม่ประเมิน",IF(BF29>=0.8,"ดีมาก",IF(BF29>=0.65,"ดี",IF(BF29>=0.5,"ต้องพัฒนา","เร่งแก้ไข")))) -> เร่งแก้ไข | BI29: =IF(BC29=0,"ยังไม่ประเมิน",INDEX($BJ$1:$BQ$1,1,MATCH(MIN(BJ29:BQ29),BJ29:BQ29,0))) -> มิติ 1 | BJ29: =SUM(E29:K29)/(7*4) -> 0 | BK29: =SUM(L29:R29)/(7*4) -> 0 | BL29: =SUM(S29:X29)/(6*4) -> 0 | BM29: =SUM(Y29:AE29)/(7*4) -> 0 | BN29: =SUM(AF29:AL29)/(7*4) -> 0 | BO29: =SUM(AM29:AS29)/(7*4) -> 0 | BP29: =SUM(AT29:AX29)/(5*4) -> 0 | BQ29: =SUM(AY29:BB29)/(4*4) -> 0
A30: RAP69-029 | B30: =IFERROR(VLOOKUP(A30,'01_ข้อมูลร้าน'!$A$2:$B$51,2,FALSE),"") -> ร้านต้นสลัด | C30: T0 | E30: 3 | F30: 2 | G30: 2 | H30: 2 | I30: 1 | J30: 3 | K30: 3 | L30: 4 | M30: 2 | N30: 4 | O30: 1 | P30: 3 | Q30: 4 | R30: 2 | S30: 3 | T30: 1 | U30: 2 | V30: 2 | W30: 2 | X30: 2 | Y30: 3 | Z30: 2 | AA30: 2 | AB30: 2 | AC30: 2 | AD30: 3 | AE30: 3 | AF30: 2 | AG30: 3 | AH30: 4 | AI30: 4 | AJ30: 4 | AK30: 3 | AL30: 3 | AM30: 2 | AN30: 3 | AO30: 3 | AP30: 2 | AQ30: 2 | AR30: 1 | AS30: 2 | AT30: 2 | AU30: 2 | AV30: 2 | AW30: 4 | AX30: 2 | AY30: 3 | AZ30: 3 | BA30: 2 | BB30: 3 | BC30: =COUNT(E30:BB30)/50 -> 1 | BD30: =SUM(E30:BB30) -> 126 | BE30: =BD30/200 -> 0.63 | BF30: =SUM(E30:K30)/(7*4)*0.12+SUM(L30:R30)/(7*4)*0.15+SUM(S30:X30)/(6*4)*0.1+SUM(Y30:AE30)/(7*4)*0.13+SUM(AF30:AL30)/(7*4)*0.2+SUM(AM30:AS30)/(7*4)*0.18+SUM(AT30:AX30)/(5*4)*0.05+SUM(AY30:BB30)/(4*4)*0.07 -> 0.64348214 | BG30: =COUNTIFS(E30:BB30,">=0",E30:BB30,"<=1") -> 4 | BH30: =IF(BC30=0,"ยังไม่ประเมิน",IF(BF30>=0.8,"ดีมาก",IF(BF30>=0.65,"ดี",IF(BF30>=0.5,"ต้องพัฒนา","เร่งแก้ไข")))) -> ต้องพัฒนา | BI30: =IF(BC30=0,"ยังไม่ประเมิน",INDEX($BJ$1:$BQ$1,1,MATCH(MIN(BJ30:BQ30),BJ30:BQ30,0))) -> มิติ 3 | BJ30: =SUM(E30:K30)/(7*4) -> 0.57142857 | BK30: =SUM(L30:R30)/(7*4) -> 0.71428571 | BL30: =SUM(S30:X30)/(6*4) -> 0.5 | BM30: =SUM(Y30:AE30)/(7*4) -> 0.60714286 | BN30: =SUM(AF30:AL30)/(7*4) -> 0.82142857 | BO30: =SUM(AM30:AS30)/(7*4) -> 0.53571429 | BP30: =SUM(AT30:AX30)/(5*4) -> 0.6 | BQ30: =SUM(AY30:BB30)/(4*4) -> 0.6875
A31: RAP69-030 | B31: =IFERROR(VLOOKUP(A31,'01_ข้อมูลร้าน'!$A$2:$B$51,2,FALSE),"") -> The Sunset Deck | C31: T0 | E31: 3 | F31: 2 | G31: 1 | H31: 2 | I31: 3 | J31: 0 | K31: 0 | L31: 4 | M31: 3 | N31: 2 | O31: 3 | P31: 4 | Q31: 4 | R31: 0 | S31: 3 | T31: 2 | U31: 4 | V31: 3 | W31: 2 | X31: 1 | Y31: 0 | Z31: 0 | AA31: 0 | AB31: 0 | AC31: 3 | AD31: 2 | AE31: 3 | AF31: 1 | AG31: 2 | AH31: 4 | AI31: 4 | AJ31: 4 | AK31: 2 | AL31: 1 | AM31: 1 | AN31: 1 | AO31: 1 | AP31: 1 | AQ31: 0 | AR31: 1 | AS31: 1 | AT31: 4 | AU31: 3 | AV31: 4 | AW31: 0 | AX31: 0 | AY31: 4 | AZ31: 4 | BA31: 4 | BB31: 4 | BC31: =COUNT(E31:BB31)/50 -> 1 | BD31: =SUM(E31:BB31) -> 105 | BE31: =BD31/200 -> 0.525 | BF31: =SUM(E31:K31)/(7*4)*0.12+SUM(L31:R31)/(7*4)*0.15+SUM(S31:X31)/(6*4)*0.1+SUM(Y31:AE31)/(7*4)*0.13+SUM(AF31:AL31)/(7*4)*0.2+SUM(AM31:AS31)/(7*4)*0.18+SUM(AT31:AX31)/(5*4)*0.05+SUM(AY31:BB31)/(4*4)*0.07 -> 0.51857143 | BG31: =COUNTIFS(E31:BB31,">=0",E31:BB31,"<=1") -> 20 | BH31: =IF(BC31=0,"ยังไม่ประเมิน",IF(BF31>=0.8,"ดีมาก",IF(BF31>=0.65,"ดี",IF(BF31>=0.5,"ต้องพัฒนา","เร่งแก้ไข")))) -> ต้องพัฒนา | BI31: =IF(BC31=0,"ยังไม่ประเมิน",INDEX($BJ$1:$BQ$1,1,MATCH(MIN(BJ31:BQ31),BJ31:BQ31,0))) -> มิติ 6 | BJ31: =SUM(E31:K31)/(7*4) -> 0.39285714 | BK31: =SUM(L31:R31)/(7*4) -> 0.71428571 | BL31: =SUM(S31:X31)/(6*4) -> 0.625 | BM31: =SUM(Y31:AE31)/(7*4) -> 0.28571429 | BN31: =SUM(AF31:AL31)/(7*4) -> 0.64285714 | BO31: =SUM(AM31:AS31)/(7*4) -> 0.21428571 | BP31: =SUM(AT31:AX31)/(5*4) -> 0.55 | BQ31: =SUM(AY31:BB31)/(4*4) -> 1
A32: RAP69-031 | B32: =IFERROR(VLOOKUP(A32,'01_ข้อมูลร้าน'!$A$2:$B$51,2,FALSE),"") -> ร้านครัวรวมรส ๒๕๖๔ จังหวัดตราด | C32: T0 | E32: 3 | F32: 4 | G32: 2 | H32: 3 | I32: 1 | J32: 4 | K32: 3 | L32: 3 | M32: 2 | N32: 4 | O32: 1 | P32: 4 | Q32: 4 | R32: 3 | S32: 3 | T32: 2 | U32: 3 | V32: 1 | W32: 2 | X32: 1 | Y32: 2 | Z32: 4 | AA32: 2 | AB32: 3 | AC32: 3 | AD32: 3 | AE32: 3 | AF32: 2 | AG32: 3 | AH32: 3 | AI32: 2 | AJ32: 3 | AK32: 3 | AL32: 2 | AM32: 1 | AN32: 2 | AO32: 3 | AP32: 3 | AQ32: 3 | AR32: 2 | AS32: 3 | AT32: 2 | AU32: 3 | AV32: 2 | AW32: 3 | AX32: 3 | AY32: 2 | AZ32: 4 | BA32: 3 | BB32: 1 | BC32: =COUNT(E32:BB32)/50 -> 1 | BD32: =SUM(E32:BB32) -> 131 | BE32: =BD32/200 -> 0.655 | BF32: =SUM(E32:K32)/(7*4)*0.12+SUM(L32:R32)/(7*4)*0.15+SUM(S32:X32)/(6*4)*0.1+SUM(Y32:AE32)/(7*4)*0.13+SUM(AF32:AL32)/(7*4)*0.2+SUM(AM32:AS32)/(7*4)*0.18+SUM(AT32:AX32)/(5*4)*0.05+SUM(AY32:BB32)/(4*4)*0.07 -> 0.65517857 | BG32: =COUNTIFS(E32:BB32,">=0",E32:BB32,"<=1") -> 6 | BH32: =IF(BC32=0,"ยังไม่ประเมิน",IF(BF32>=0.8,"ดีมาก",IF(BF32>=0.65,"ดี",IF(BF32>=0.5,"ต้องพัฒนา","เร่งแก้ไข")))) -> ดี | BI32: =IF(BC32=0,"ยังไม่ประเมิน",INDEX($BJ$1:$BQ$1,1,MATCH(MIN(BJ32:BQ32),BJ32:BQ32,0))) -> มิติ 3 | BJ32: =SUM(E32:K32)/(7*4) -> 0.71428571 | BK32: =SUM(L32:R32)/(7*4) -> 0.75 | BL32: =SUM(S32:X32)/(6*4) -> 0.5 | BM32: =SUM(Y32:AE32)/(7*4) -> 0.71428571 | BN32: =SUM(AF32:AL32)/(7*4) -> 0.64285714 | BO32: =SUM(AM32:AS32)/(7*4) -> 0.60714286 | BP32: =SUM(AT32:AX32)/(5*4) -> 0.65 | BQ32: =SUM(AY32:BB32)/(4*4) -> 0.625
A33: RAP69-032 | B33: =IFERROR(VLOOKUP(A33,'01_ข้อมูลร้าน'!$A$2:$B$51,2,FALSE),"") -> ร้านคดข้าว | C33: T0 | E33: 4 | F33: 4 | G33: 3 | H33: 3 | I33: 3 | J33: 2 | K33: 3 | L33: 4 | M33: 4 | N33: 3 | O33: 3 | P33: 3 | Q33: 4 | R33: 3 | S33: 4 | T33: 3 | U33: 4 | V33: 4 | W33: 4 | X33: 3 | Y33: 4 | Z33: 4 | AA33: 4 | AB33: 3 | AC33: 3 | AD33: 4 | AE33: 3 | AF33: 3 | AG33: 4 | AH33: 4 | AI33: 3 | AJ33: 3 | AK33: 2 | AL33: 3 | AM33: 2 | AN33: 3 | AO33: 2 | AP33: 3 | AQ33: 3 | AR33: 4 | AS33: 3 | AT33: 2 | AU33: 4 | AV33: 3 | AW33: 2 | AX33: 0 | AY33: 3 | AZ33: 4 | BA33: 4 | BB33: 3 | BC33: =COUNT(E33:BB33)/50 -> 1 | BD33: =SUM(E33:BB33) -> 160 | BE33: =BD33/200 -> 0.8 | BF33: =SUM(E33:K33)/(7*4)*0.12+SUM(L33:R33)/(7*4)*0.15+SUM(S33:X33)/(6*4)*0.1+SUM(Y33:AE33)/(7*4)*0.13+SUM(AF33:AL33)/(7*4)*0.2+SUM(AM33:AS33)/(7*4)*0.18+SUM(AT33:AX33)/(5*4)*0.05+SUM(AY33:BB33)/(4*4)*0.07 -> 0.80505952 | BG33: =COUNTIFS(E33:BB33,">=0",E33:BB33,"<=1") -> 1 | BH33: =IF(BC33=0,"ยังไม่ประเมิน",IF(BF33>=0.8,"ดีมาก",IF(BF33>=0.65,"ดี",IF(BF33>=0.5,"ต้องพัฒนา","เร่งแก้ไข")))) -> ดีมาก | BI33: =IF(BC33=0,"ยังไม่ประเมิน",INDEX($BJ$1:$BQ$1,1,MATCH(MIN(BJ33:BQ33),BJ33:BQ33,0))) -> มิติ 7 | BJ33: =SUM(E33:K33)/(7*4) -> 0.78571429 | BK33: =SUM(L33:R33)/(7*4) -> 0.85714286 | BL33: =SUM(S33:X33)/(6*4) -> 0.91666667 | BM33: =SUM(Y33:AE33)/(7*4) -> 0.89285714 | BN33: =SUM(AF33:AL33)/(7*4) -> 0.78571429 | BO33: =SUM(AM33:AS33)/(7*4) -> 0.71428571 | BP33: =SUM(AT33:AX33)/(5*4) -> 0.55 | BQ33: =SUM(AY33:BB33)/(4*4) -> 0.875
A34: RAP69-033 | B34: =IFERROR(VLOOKUP(A34,'01_ข้อมูลร้าน'!$A$2:$B$51,2,FALSE),"") -> GRID GARDEN | C34: T0 | E34: 3 | F34: 3 | G34: 3 | H34: 2 | I34: 3 | J34: 2 | K34: 3 | L34: 4 | M34: 4 | N34: 3 | O34: 3 | P34: 3 | Q34: 4 | R34: 3 | S34: 4 | T34: 3 | U34: 3 | V34: 3 | W34: 3 | X34: 4 | Y34: 4 | Z34: 2 | AA34: 2 | AB34: 3 | AC34: 3 | AD34: 4 | AE34: 2 | AF34: 4 | AG34: 3 | AH34: 3 | AI34: 2 | AJ34: 3 | AK34: 3 | AL34: 2 | AM34: 2 | AN34: 2 | AO34: 3 | AP34: 3 | AQ34: 3 | AR34: 2 | AS34: 2 | AT34: 4 | AU34: 4 | AV34: 3 | AW34: 2 | AX34: 2 | AY34: 4 | AZ34: 4 | BA34: 4 | BB34: 3 | BC34: =COUNT(D34:BB34)/50 -> 1 | BD34: =SUM(E34:BB34) -> 150 | BE34: =BD34/200 -> 0.75 | BF34: =SUM(E34:K34)/(7*4)*0.12+SUM(L34:R34)/(7*4)*0.15+SUM(S34:X34)/(6*4)*0.1+SUM(Y34:AE34)/(7*4)*0.13+SUM(AF34:AL34)/(7*4)*0.2+SUM(AM34:AS34)/(7*4)*0.18+SUM(AT34:AX34)/(5*4)*0.05+SUM(AY34:BB34)/(4*4)*0.07 -> 0.74145833 | BG34: =COUNTIFS(E34:BB34,">=0",E34:BB34,"<=1") -> 0 | BH34: =IF(BC34=0,"ยังไม่ประเมิน",IF(BF34>=0.8,"ดีมาก",IF(BF34>=0.65,"ดี",IF(BF34>=0.5,"ต้องพัฒนา","เร่งแก้ไข")))) -> ดี | BI34: {=IF(BC334=0,"ยังไม่ประเมิน",INDEX($BJ$1:$BQ$1,1,MATCH(MIN(BJ34:BQ34),BJ34:BQ34,0)))} -> ยังไม่ประเมิน | BJ34: =SUM(E34:K34)/(7*4) -> 0.67857143 | BK34: =SUM(L34:R34)/(7*4) -> 0.85714286 | BL34: =SUM(S34:X34)/(6*4) -> 0.83333333 | BM34: =SUM(Y34:AE34)/(7*4) -> 0.71428571 | BN34: =SUM(AF34:AL34)/(7*4) -> 0.71428571 | BO34: =SUM(AM34:AS34)/(7*4) -> 0.60714286 | BP34: =SUM(AT34:AX34)/(5*4) -> 0.75 | BQ34: =SUM(AY34:BB34)/(4*4) -> 0.9375
A35: RAP69-034 | B35: =IFERROR(VLOOKUP(A35,'01_ข้อมูลร้าน'!$A$2:$B$51,2,FALSE),"") -> เทียบจันท์ | C35: T0 | E35: 3 | F35: 2 | G35: 2 | H35: 1 | I35: 1 | J35: 1 | K35: 2 | L35: 2 | M35: 1 | N35: 3 | O35: 0 | P35: 2 | Q35: 4 | R35: 0 | S35: 4 | T35: 2 | U35: 3 | V35: 1 | W35: 2 | X35: 1 | Y35: 3 | Z35: 3 | AA35: 3 | AB35: 2 | AC35: 2 | AD35: 2 | AE35: 2 | AF35: 2 | AG35: 2 | AH35: 1 | AI35: 1 | AJ35: 2 | AK35: 2 | AL35: 2 | AM35: 2 | AN35: 3 | AO35: 3 | AP35: 3 | AQ35: 3 | AR35: 3 | AS35: 3 | AT35: 2 | AU35: 2 | AV35: 1 | AW35: 2 | AX35: 2 | AY35: 3 | AZ35: 3 | BA35: 3 | BB35: 3 | BC35: =COUNT(E35:BB35)/50 -> 1 | BD35: =SUM(E35:BB35) -> 107 | BE35: =BD35/200 -> 0.535 | BF35: =SUM(E35:K35)/(7*4)*0.12+SUM(L35:R35)/(7*4)*0.15+SUM(S35:X35)/(6*4)*0.1+SUM(Y35:AE35)/(7*4)*0.13+SUM(AF35:AL35)/(7*4)*0.2+SUM(AM35:AS35)/(7*4)*0.18+SUM(AT35:AX35)/(5*4)*0.05+SUM(AY35:BB35)/(4*4)*0.07 -> 0.53809524 | BG35: =COUNTIFS(E35:BB35,">=0",E35:BB35,"<=1") -> 11 | BH35: =IF(BC35=0,"ยังไม่ประเมิน",IF(BF35>=0.8,"ดีมาก",IF(BF35>=0.65,"ดี",IF(BF35>=0.5,"ต้องพัฒนา","เร่งแก้ไข")))) -> ต้องพัฒนา | BI35: =IF(BC35=0,"ยังไม่ประเมิน",INDEX($BJ$1:$BQ$1,1,MATCH(MIN(BJ35:BQ35),BJ35:BQ35,0))) -> มิติ 1 | BJ35: =SUM(E35:K35)/(7*4) -> 0.42857143 | BK35: =SUM(L35:R35)/(7*4) -> 0.42857143 | BL35: =SUM(S35:X35)/(6*4) -> 0.54166667 | BM35: =SUM(Y35:AE35)/(7*4) -> 0.60714286 | BN35: =SUM(AF35:AL35)/(7*4) -> 0.42857143 | BO35: =SUM(AM35:AS35)/(7*4) -> 0.71428571 | BP35: =SUM(AT35:AX35)/(5*4) -> 0.45 | BQ35: =SUM(AY35:BB35)/(4*4) -> 0.75
A36: RAP69-035 | B36: =IFERROR(VLOOKUP(A36,'01_ข้อมูลร้าน'!$A$2:$B$51,2,FALSE),"") -> The Chanthaboon Coffee กาแฟจันทบูร | C36: T0 | E36: 4 | F36: 4 | G36: 4 | H36: 4 | I36: 4 | J36: 3 | K36: 3 | L36: 2 | M36: 3 | N36: 3 | O36: 2 | P36: 2 | Q36: 4 | R36: 2 | S36: 4 | T36: 4 | U36: 3 | V36: 4 | W36: 3 | X36: 4 | Y36: 2 | Z36: 2 | AA36: 2 | AB36: 2 | AC36: 2 | AD36: 3 | AE36: 3 | AF36: 2 | AG36: 2 | AH36: 2 | AI36: 2 | AJ36: 2 | AK36: 2 | AL36: 3 | AM36: 2 | AN36: 2 | AO36: 2 | AP36: 2 | AQ36: 1 | AR36: 2 | AS36: 2 | AT36: 3 | AU36: 3 | AV36: 3 | AW36: 4 | AX36: 4 | AY36: 3 | AZ36: 4 | BA36: 3 | BB36: 3 | BC36: =COUNT(E36:BB36)/50 -> 1 | BD36: =SUM(E36:BB36) -> 140 | BE36: =BD36/200 -> 0.7 | BF36: =SUM(E36:K36)/(7*4)*0.12+SUM(L36:R36)/(7*4)*0.15+SUM(S36:X36)/(6*4)*0.1+SUM(Y36:AE36)/(7*4)*0.13+SUM(AF36:AL36)/(7*4)*0.2+SUM(AM36:AS36)/(7*4)*0.18+SUM(AT36:AX36)/(5*4)*0.05+SUM(AY36:BB36)/(4*4)*0.07 -> 0.66389881 | BG36: =COUNTIFS(E36:BB36,">=0",E36:BB36,"<=1") -> 1 | BH36: =IF(BC36=0,"ยังไม่ประเมิน",IF(BF36>=0.8,"ดีมาก",IF(BF36>=0.65,"ดี",IF(BF36>=0.5,"ต้องพัฒนา","เร่งแก้ไข")))) -> ดี | BI36: =IF(BC36=0,"ยังไม่ประเมิน",INDEX($BJ$1:$BQ$1,1,MATCH(MIN(BJ36:BQ36),BJ36:BQ36,0))) -> มิติ 6 | BJ36: =SUM(E36:K36)/(7*4) -> 0.92857143 | BK36: =SUM(L36:R36)/(7*4) -> 0.64285714 | BL36: =SUM(S36:X36)/(6*4) -> 0.91666667 | BM36: =SUM(Y36:AE36)/(7*4) -> 0.57142857 | BN36: =SUM(AF36:AL36)/(7*4) -> 0.53571429 | BO36: =SUM(AM36:AS36)/(7*4) -> 0.46428571 | BP36: =SUM(AT36:AX36)/(5*4) -> 0.85 | BQ36: =SUM(AY36:BB36)/(4*4) -> 0.8125
A37: RAP69-036 | B37: =IFERROR(VLOOKUP(A37,'01_ข้อมูลร้าน'!$A$2:$B$51,2,FALSE),"") -> Garagecafechan | C37: T0 | E37: 3 | F37: 3 | G37: 4 | H37: 2 | I37: 4 | J37: 3 | K37: 3 | L37: 3 | M37: 2 | N37: 2 | O37: 1 | P37: 2 | Q37: 4 | R37: 2 | S37: 4 | T37: 4 | U37: 4 | V37: 4 | W37: 3 | X37: 3 | Y37: 4 | Z37: 4 | AA37: 3 | AB37: 3 | AC37: 4 | AD37: 4 | AE37: 3 | AF37: 3 | AG37: 3 | AH37: 4 | AI37: 3 | AJ37: 2 | AK37: 3 | AL37: 4 | AM37: 4 | AN37: 4 | AO37: 3 | AP37: 4 | AQ37: 4 | AR37: 4 | AS37: 4 | AT37: 3 | AU37: 3 | AV37: 3 | AW37: 1 | AX37: 3 | AY37: 4 | AZ37: 4 | BA37: 4 | BB37: 4 | BC37: =COUNT(E37:BB37)/50 -> 1 | BD37: =SUM(E37:BB37) -> 163 | BE37: =BD37/200 -> 0.815 | BF37: =SUM(E37:K37)/(7*4)*0.12+SUM(L37:R37)/(7*4)*0.15+SUM(S37:X37)/(6*4)*0.1+SUM(Y37:AE37)/(7*4)*0.13+SUM(AF37:AL37)/(7*4)*0.2+SUM(AM37:AS37)/(7*4)*0.18+SUM(AT37:AX37)/(5*4)*0.05+SUM(AY37:BB37)/(4*4)*0.07 -> 0.82095238 | BG37: =COUNTIFS(E37:BB37,">=0",E37:BB37,"<=1") -> 2 | BH37: =IF(BC37=0,"ยังไม่ประเมิน",IF(BF37>=0.8,"ดีมาก",IF(BF37>=0.65,"ดี",IF(BF37>=0.5,"ต้องพัฒนา","เร่งแก้ไข")))) -> ดีมาก | BI37: =IF(BC37=0,"ยังไม่ประเมิน",INDEX($BJ$1:$BQ$1,1,MATCH(MIN(BJ37:BQ37),BJ37:BQ37,0))) -> มิติ 2 | BJ37: =SUM(E37:K37)/(7*4) -> 0.78571429 | BK37: =SUM(L37:R37)/(7*4) -> 0.57142857 | BL37: =SUM(S37:X37)/(6*4) -> 0.91666667 | BM37: =SUM(Y37:AE37)/(7*4) -> 0.89285714 | BN37: =SUM(AF37:AL37)/(7*4) -> 0.78571429 | BO37: =SUM(AM37:AS37)/(7*4) -> 0.96428571 | BP37: =SUM(AT37:AX37)/(5*4) -> 0.65 | BQ37: =SUM(AY37:BB37)/(4*4) -> 1
A38: RAP69-037 | B38: =IFERROR(VLOOKUP(A38,'01_ข้อมูลร้าน'!$A$2:$B$51,2,FALSE),"") -> จันทรโภชนา | C38: T0 | E38: 4 | F38: 3 | G38: 3 | H38: 4 | I38: 4 | J38: 4 | K38: 3 | L38: 3 | M38: 4 | N38: 3 | O38: 4 | P38: 4 | Q38: 4 | R38: 3 | S38: 4 | T38: 4 | U38: 4 | V38: 4 | W38: 4 | X38: 4 | Y38: 3 | Z38: 4 | AA38: 4 | AB38: 3 | AC38: 3 | AD38: 4 | AE38: 3 | AF38: 4 | AG38: 3 | AH38: 3 | AI38: 3 | AJ38: 3 | AK38: 4 | AL38: 4 | AM38: 3 | AN38: 3 | AO38: 3 | AP38: 3 | AQ38: 4 | AR38: 3 | AS38: 4 | AT38: 4 | AU38: 4 | AV38: 4 | AW38: 4 | AX38: 4 | AY38: 4 | AZ38: 3 | BA38: 4 | BB38: 4 | BC38: =COUNT(E38:BB38)/50 -> 1 | BD38: =SUM(E38:BB38) -> 180 | BE38: =BD38/200 -> 0.9 | BF38: =SUM(E38:K38)/(7*4)*0.12+SUM(L38:R38)/(7*4)*0.15+SUM(S38:X38)/(6*4)*0.1+SUM(Y38:AE38)/(7*4)*0.13+SUM(AF38:AL38)/(7*4)*0.2+SUM(AM38:AS38)/(7*4)*0.18+SUM(AT38:AX38)/(5*4)*0.05+SUM(AY38:BB38)/(4*4)*0.07 -> 0.88741071 | BG38: =COUNTIFS(E38:BB38,">=0",E38:BB38,"<=1") -> 0 | BH38: =IF(BC38=0,"ยังไม่ประเมิน",IF(BF38>=0.8,"ดีมาก",IF(BF38>=0.65,"ดี",IF(BF38>=0.5,"ต้องพัฒนา","เร่งแก้ไข")))) -> ดีมาก | BI38: =IF(BC38=0,"ยังไม่ประเมิน",INDEX($BJ$1:$BQ$1,1,MATCH(MIN(BJ38:BQ38),BJ38:BQ38,0))) -> มิติ 6 | BJ38: =SUM(E38:K38)/(7*4) -> 0.89285714 | BK38: =SUM(L38:R38)/(7*4) -> 0.89285714 | BL38: =SUM(S38:X38)/(6*4) -> 1 | BM38: =SUM(Y38:AE38)/(7*4) -> 0.85714286 | BN38: =SUM(AF38:AL38)/(7*4) -> 0.85714286 | BO38: =SUM(AM38:AS38)/(7*4) -> 0.82142857 | BP38: =SUM(AT38:AX38)/(5*4) -> 1 | BQ38: =SUM(AY38:BB38)/(4*4) -> 0.9375
A39: RAP69-038 | B39: =IFERROR(VLOOKUP(A39,'01_ข้อมูลร้าน'!$A$2:$B$51,2,FALSE),"") -> Grizzly Gelato | C39: T0 | E39: 3 | F39: 4 | G39: 4 | H39: 1 | I39: 2 | J39: 3 | K39: 3 | L39: 3 | M39: 2 | N39: 2 | O39: 3 | P39: 3 | Q39: 2 | R39: 4 | S39: 3 | T39: 2 | U39: 2 | V39: 4 | W39: 2 | X39: 4 | Y39: 4 | Z39: 3 | AA39: 2 | AB39: 2 | AC39: 3 | AD39: 2 | AE39: 2 | AF39: 2 | AG39: 2 | AH39: 3 | AI39: 2 | AJ39: 3 | AK39: 3 | AL39: 2 | AM39: 4 | AN39: 4 | AO39: 4 | AP39: 4 | AQ39: 4 | AR39: 2 | AS39: 2 | AT39: 2 | AU39: 3 | AV39: 2 | AW39: 3 | AX39: 3 | AY39: 4 | AZ39: 4 | BA39: 4 | BB39: 4 | BC39: =COUNT(E39:BB39)/50 -> 1 | BD39: =SUM(E39:BB39) -> 144 | BE39: =BD39/200 -> 0.72 | BF39: =SUM(E39:K39)/(7*4)*0.12+SUM(L39:R39)/(7*4)*0.15+SUM(S39:X39)/(6*4)*0.1+SUM(Y39:AE39)/(7*4)*0.13+SUM(AF39:AL39)/(7*4)*0.2+SUM(AM39:AS39)/(7*4)*0.18+SUM(AT39:AX39)/(5*4)*0.05+SUM(AY39:BB39)/(4*4)*0.07 -> 0.72011905 | BG39: =COUNTIFS(E39:BB39,">=0",E39:BB39,"<=1") -> 1 | BH39: =IF(BC39=0,"ยังไม่ประเมิน",IF(BF39>=0.8,"ดีมาก",IF(BF39>=0.65,"ดี",IF(BF39>=0.5,"ต้องพัฒนา","เร่งแก้ไข")))) -> ดี | BI39: =IF(BC39=0,"ยังไม่ประเมิน",INDEX($BJ$1:$BQ$1,1,MATCH(MIN(BJ39:BQ39),BJ39:BQ39,0))) -> มิติ 5 | BJ39: =SUM(E39:K39)/(7*4) -> 0.71428571 | BK39: =SUM(L39:R39)/(7*4) -> 0.67857143 | BL39: =SUM(S39:X39)/(6*4) -> 0.70833333 | BM39: =SUM(Y39:AE39)/(7*4) -> 0.64285714 | BN39: =SUM(AF39:AL39)/(7*4) -> 0.60714286 | BO39: =SUM(AM39:AS39)/(7*4) -> 0.85714286 | BP39: =SUM(AT39:AX39)/(5*4) -> 0.65 | BQ39: =SUM(AY39:BB39)/(4*4) -> 1
A40: RAP69-039 | B40: =IFERROR(VLOOKUP(A40,'01_ข้อมูลร้าน'!$A$2:$B$51,2,FALSE),"") -> ครัวตามธาตุ | C40: T0 | E40: 1 | F40: 0 | G40: 1 | H40: 0 | I40: 1 | J40: 1 | K40: 2 | L40: 2 | M40: 3 | N40: 0 | O40: 1 | P40: 0 | Q40: 0 | R40: 1 | S40: 0 | T40: 1 | U40: 0 | V40: 1 | W40: 2 | X40: 3 | Y40: 2 | Z40: 0 | AA40: 0 | AB40: 0 | AC40: 1 | AD40: 1 | AE40: 1 | AF40: 1 | AG40: 4 | AH40: 3 | AI40: 3 | AJ40: 2 | AK40: 2 | AL40: 2 | AM40: 3 | AN40: 3 | AO40: 2 | AP40: 2 | AQ40: 2 | AR40: 3 | AS40: 3 | AT40: 4 | AU40: 2 | AV40: 4 | AW40: 3 | AX40: 4 | AY40: 1 | AZ40: 0 | BA40: 1 | BB40: 1 | BC40: =COUNT(E40:BB40)/50 -> 1 | BD40: =SUM(E40:BB40) -> 80 | BE40: =BD40/200 -> 0.4 | BF40: =SUM(E40:K40)/(7*4)*0.12+SUM(L40:R40)/(7*4)*0.15+SUM(S40:X40)/(6*4)*0.1+SUM(Y40:AE40)/(7*4)*0.13+SUM(AF40:AL40)/(7*4)*0.2+SUM(AM40:AS40)/(7*4)*0.18+SUM(AT40:AX40)/(5*4)*0.05+SUM(AY40:BB40)/(4*4)*0.07 -> 0.4083631 | BG40: =COUNTIFS(E40:BB40,">=0",E40:BB40,"<=1") -> 26 | BH40: =IF(BC40=0,"ยังไม่ประเมิน",IF(BF40>=0.8,"ดีมาก",IF(BF40>=0.65,"ดี",IF(BF40>=0.5,"ต้องพัฒนา","เร่งแก้ไข")))) -> เร่งแก้ไข | BI40: =IF(BC40=0,"ยังไม่ประเมิน",INDEX($BJ$1:$BQ$1,1,MATCH(MIN(BJ40:BQ40),BJ40:BQ40,0))) -> มิติ 4 | BJ40: =SUM(E40:K40)/(7*4) -> 0.21428571 | BK40: =SUM(L40:R40)/(7*4) -> 0.25 | BL40: =SUM(S40:X40)/(6*4) -> 0.29166667 | BM40: =SUM(Y40:AE40)/(7*4) -> 0.17857143 | BN40: =SUM(AF40:AL40)/(7*4) -> 0.60714286 | BO40: =SUM(AM40:AS40)/(7*4) -> 0.64285714 | BP40: =SUM(AT40:AX40)/(5*4) -> 0.85 | BQ40: =SUM(AY40:BB40)/(4*4) -> 0.1875
A41: RAP69-040 | B41: =IFERROR(VLOOKUP(A41,'01_ข้อมูลร้าน'!$A$2:$B$51,2,FALSE),"") -> จิน ข้าวมันไก่สไตล์สิงคโปร์ | C41: T0 | E41: 4 | F41: 3 | G41: 4 | H41: 2 | I41: 2 | J41: 3 | K41: 3 | L41: 3 | M41: 3 | N41: 3 | O41: 1 | P41: 3 | Q41: 4 | R41: 1 | S41: 4 | T41: 4 | U41: 4 | V41: 3 | W41: 4 | X41: 0 | Y41: 3 | Z41: 3 | AA41: 4 | AB41: 3 | AC41: 2 | AD41: 4 | AE41: 3 | AF41: 3 | AG41: 4 | AH41: 4 | AI41: 4 | AJ41: 4 | AK41: 3 | AL41: 4 | AM41: 3 | AN41: 3 | AO41: 4 | AP41: 3 | AQ41: 4 | AR41: 4 | AS41: 3 | AT41: 3 | AU41: 4 | AV41: 3 | AW41: 1 | AX41: 2 | AY41: 3 | AZ41: 4 | BA41: 4 | BB41: 4 | BC41: =COUNT(E41:BB41)/50 -> 1 | BD41: =SUM(E41:BB41) -> 158 | BE41: =BD41/200 -> 0.79 | BF41: =SUM(E41:K41)/(7*4)*0.12+SUM(L41:R41)/(7*4)*0.15+SUM(S41:X41)/(6*4)*0.1+SUM(Y41:AE41)/(7*4)*0.13+SUM(AF41:AL41)/(7*4)*0.2+SUM(AM41:AS41)/(7*4)*0.18+SUM(AT41:AX41)/(5*4)*0.05+SUM(AY41:BB41)/(4*4)*0.07 -> 0.8058631 | BG41: =COUNTIFS(E41:BB41,">=0",E41:BB41,"<=1") -> 4 | BH41: =IF(BC41=0,"ยังไม่ประเมิน",IF(BF41>=0.8,"ดีมาก",IF(BF41>=0.65,"ดี",IF(BF41>=0.5,"ต้องพัฒนา","เร่งแก้ไข")))) -> ดีมาก | BI41: =IF(BC41=0,"ยังไม่ประเมิน",INDEX($BJ$1:$BQ$1,1,MATCH(MIN(BJ41:BQ41),BJ41:BQ41,0))) -> มิติ 2 | BJ41: =SUM(E41:K41)/(7*4) -> 0.75 | BK41: =SUM(L41:R41)/(7*4) -> 0.64285714 | BL41: =SUM(S41:X41)/(6*4) -> 0.79166667 | BM41: =SUM(Y41:AE41)/(7*4) -> 0.78571429 | BN41: =SUM(AF41:AL41)/(7*4) -> 0.92857143 | BO41: =SUM(AM41:AS41)/(7*4) -> 0.85714286 | BP41: =SUM(AT41:AX41)/(5*4) -> 0.65 | BQ41: =SUM(AY41:BB41)/(4*4) -> 0.9375
A42: RAP69-041 | B42: =IFERROR(VLOOKUP(A42,'01_ข้อมูลร้าน'!$A$2:$B$51,2,FALSE),"") -> สุขทุกวัน คาเฟ่ | C42: T0 | E42: 4 | F42: 2 | G42: 2 | H42: 3 | I42: 2 | J42: 2 | K42: 3 | L42: 3 | M42: 2 | N42: 1 | O42: 2 | P42: 2 | Q42: 4 | R42: 1 | S42: 4 | T42: 3 | U42: 3 | V42: 4 | W42: 3 | X42: 3 | Y42: 3 | Z42: 3 | AA42: 3 | AB42: 2 | AC42: 3 | AD42: 3 | AE42: 3 | AF42: 2 | AG42: 3 | AH42: 3 | AI42: 3 | AJ42: 4 | AK42: 4 | AL42: 4 | AM42: 3 | AN42: 3 | AO42: 3 | AP42: 3 | AQ42: 3 | AR42: 3 | AS42: 4 | AT42: 3 | AU42: 4 | AV42: 3 | AW42: 4 | AX42: 4 | AY42: 4 | AZ42: 4 | BA42: 4 | BB42: 4 | BC42: =COUNT(E42:BB42)/50 -> 1 | BD42: =SUM(E42:BB42) -> 152 | BE42: =BD42/200 -> 0.76 | BF42: =SUM(E42:K42)/(7*4)*0.12+SUM(L42:R42)/(7*4)*0.15+SUM(S42:X42)/(6*4)*0.1+SUM(Y42:AE42)/(7*4)*0.13+SUM(AF42:AL42)/(7*4)*0.2+SUM(AM42:AS42)/(7*4)*0.18+SUM(AT42:AX42)/(5*4)*0.05+SUM(AY42:BB42)/(4*4)*0.07 -> 0.75440476 | BG42: =COUNTIFS(E42:BB42,">=0",E42:BB42,"<=1") -> 2 | BH42: =IF(BC42=0,"ยังไม่ประเมิน",IF(BF42>=0.8,"ดีมาก",IF(BF42>=0.65,"ดี",IF(BF42>=0.5,"ต้องพัฒนา","เร่งแก้ไข")))) -> ดี | BI42: =IF(BC42=0,"ยังไม่ประเมิน",INDEX($BJ$1:$BQ$1,1,MATCH(MIN(BJ42:BQ42),BJ42:BQ42,0))) -> มิติ 2 | BJ42: =SUM(E42:K42)/(7*4) -> 0.64285714 | BK42: =SUM(L42:R42)/(7*4) -> 0.53571429 | BL42: =SUM(S42:X42)/(6*4) -> 0.83333333 | BM42: =SUM(Y42:AE42)/(7*4) -> 0.71428571 | BN42: =SUM(AF42:AL42)/(7*4) -> 0.82142857 | BO42: =SUM(AM42:AS42)/(7*4) -> 0.78571429 | BP42: =SUM(AT42:AX42)/(5*4) -> 0.9 | BQ42: =SUM(AY42:BB42)/(4*4) -> 1
A43: RAP69-042 | B43: =IFERROR(VLOOKUP(A43,'01_ข้อมูลร้าน'!$A$2:$B$51,2,FALSE),"") -> เลย เดอ ลอง | C43: T0 | E43: 3 | F43: 3 | G43: 3 | H43: 3 | I43: 2 | J43: 2 | K43: 3 | L43: 3 | M43: 2 | N43: 3 | O43: 3 | P43: 3 | Q43: 4 | R43: 3 | S43: 3 | T43: 3 | U43: 4 | V43: 2 | W43: 4 | X43: 2 | Y43: 3 | Z43: 4 | AA43: 4 | AB43: 3 | AC43: 2 | AD43: 4 | AE43: 3 | AF43: 4 | AG43: 4 | AH43: 3 | AI43: 4 | AJ43: 4 | AK43: 3 | AL43: 3 | AM43: 2 | AN43: 2 | AO43: 3 | AP43: 3 | AQ43: 3 | AR43: 4 | AS43: 3 | AT43: 3 | AU43: 3 | AV43: 3 | AW43: 2 | AX43: 1 | AY43: 3 | AZ43: 3 | BA43: 2 | BB43: 3 | BC43: =COUNT(E43:BB43)/50 -> 1 | BD43: =SUM(E43:BB43) -> 149 | BE43: =BD43/200 -> 0.745 | BF43: =SUM(E43:K43)/(7*4)*0.12+SUM(L43:R43)/(7*4)*0.15+SUM(S43:X43)/(6*4)*0.1+SUM(Y43:AE43)/(7*4)*0.13+SUM(AF43:AL43)/(7*4)*0.2+SUM(AM43:AS43)/(7*4)*0.18+SUM(AT43:AX43)/(5*4)*0.05+SUM(AY43:BB43)/(4*4)*0.07 -> 0.76098214 | BG43: =COUNTIFS(E43:BB43,">=0",E43:BB43,"<=1") -> 1 | BH43: =IF(BC43=0,"ยังไม่ประเมิน",IF(BF43>=0.8,"ดีมาก",IF(BF43>=0.65,"ดี",IF(BF43>=0.5,"ต้องพัฒนา","เร่งแก้ไข")))) -> ดี | BI43: =IF(BC43=0,"ยังไม่ประเมิน",INDEX($BJ$1:$BQ$1,1,MATCH(MIN(BJ43:BQ43),BJ43:BQ43,0))) -> มิติ 7 | BJ43: =SUM(E43:K43)/(7*4) -> 0.67857143 | BK43: =SUM(L43:R43)/(7*4) -> 0.75 | BL43: =SUM(S43:X43)/(6*4) -> 0.75 | BM43: =SUM(Y43:AE43)/(7*4) -> 0.82142857 | BN43: =SUM(AF43:AL43)/(7*4) -> 0.89285714 | BO43: =SUM(AM43:AS43)/(7*4) -> 0.71428571 | BP43: =SUM(AT43:AX43)/(5*4) -> 0.6 | BQ43: =SUM(AY43:BB43)/(4*4) -> 0.6875
A44: RAP69-043 | B44: =IFERROR(VLOOKUP(A44,'01_ข้อมูลร้าน'!$A$2:$B$51,2,FALSE),"") -> ร้านที่ 43 | C44: T0 | BC44: =COUNT(E44:BB44)/50 -> 0 | BD44: =SUM(E44:BB44) -> 0 | BE44: =BD44/200 -> 0 | BF44: =SUM(E44:K44)/(7*4)*0.12+SUM(L44:R44)/(7*4)*0.15+SUM(S44:X44)/(6*4)*0.1+SUM(Y44:AE44)/(7*4)*0.13+SUM(AF44:AL44)/(7*4)*0.2+SUM(AM44:AS44)/(7*4)*0.18+SUM(AT44:AX44)/(5*4)*0.05+SUM(AY44:BB44)/(4*4)*0.07 -> 0 | BG44: =COUNTIFS(E44:BB44,">=0",E44:BB44,"<=1") -> 0 | BH44: =IF(BC44=0,"ยังไม่ประเมิน",IF(BF44>=0.8,"ดีมาก",IF(BF44>=0.65,"ดี",IF(BF44>=0.5,"ต้องพัฒนา","เร่งแก้ไข")))) -> ยังไม่ประเมิน | BI44: =IF(BC44=0,"ยังไม่ประเมิน",INDEX($BJ$1:$BQ$1,1,MATCH(MIN(BJ44:BQ44),BJ44:BQ44,0))) -> ยังไม่ประเมิน | BJ44: =SUM(E44:K44)/(7*4) -> 0 | BK44: =SUM(L44:R44)/(7*4) -> 0 | BL44: =SUM(S44:X44)/(6*4) -> 0 | BM44: =SUM(Y44:AE44)/(7*4) -> 0 | BN44: =SUM(AF44:AL44)/(7*4) -> 0 | BO44: =SUM(AM44:AS44)/(7*4) -> 0 | BP44: =SUM(AT44:AX44)/(5*4) -> 0 | BQ44: =SUM(AY44:BB44)/(4*4) -> 0
A45: RAP69-044 | B45: =IFERROR(VLOOKUP(A45,'01_ข้อมูลร้าน'!$A$2:$B$51,2,FALSE),"") -> ร้านที่ 44 | C45: T0 | BC45: =COUNT(E45:BB45)/50 -> 0 | BD45: =SUM(E45:BB45) -> 0 | BE45: =BD45/200 -> 0 | BF45: =SUM(E45:K45)/(7*4)*0.12+SUM(L45:R45)/(7*4)*0.15+SUM(S45:X45)/(6*4)*0.1+SUM(Y45:AE45)/(7*4)*0.13+SUM(AF45:AL45)/(7*4)*0.2+SUM(AM45:AS45)/(7*4)*0.18+SUM(AT45:AX45)/(5*4)*0.05+SUM(AY45:BB45)/(4*4)*0.07 -> 0 | BG45: =COUNTIFS(E45:BB45,">=0",E45:BB45,"<=1") -> 0 | BH45: =IF(BC45=0,"ยังไม่ประเมิน",IF(BF45>=0.8,"ดีมาก",IF(BF45>=0.65,"ดี",IF(BF45>=0.5,"ต้องพัฒนา","เร่งแก้ไข")))) -> ยังไม่ประเมิน | BI45: =IF(BC45=0,"ยังไม่ประเมิน",INDEX($BJ$1:$BQ$1,1,MATCH(MIN(BJ45:BQ45),BJ45:BQ45,0))) -> ยังไม่ประเมิน | BJ45: =SUM(E45:K45)/(7*4) -> 0 | BK45: =SUM(L45:R45)/(7*4) -> 0 | BL45: =SUM(S45:X45)/(6*4) -> 0 | BM45: =SUM(Y45:AE45)/(7*4) -> 0 | BN45: =SUM(AF45:AL45)/(7*4) -> 0 | BO45: =SUM(AM45:AS45)/(7*4) -> 0 | BP45: =SUM(AT45:AX45)/(5*4) -> 0 | BQ45: =SUM(AY45:BB45)/(4*4) -> 0
A46: RAP69-045 | B46: =IFERROR(VLOOKUP(A46,'01_ข้อมูลร้าน'!$A$2:$B$51,2,FALSE),"") -> ร้านที่ 45 | C46: T0 | BC46: =COUNT(E46:BB46)/50 -> 0 | BD46: =SUM(E46:BB46) -> 0 | BE46: =BD46/200 -> 0 | BF46: =SUM(E46:K46)/(7*4)*0.12+SUM(L46:R46)/(7*4)*0.15+SUM(S46:X46)/(6*4)*0.1+SUM(Y46:AE46)/(7*4)*0.13+SUM(AF46:AL46)/(7*4)*0.2+SUM(AM46:AS46)/(7*4)*0.18+SUM(AT46:AX46)/(5*4)*0.05+SUM(AY46:BB46)/(4*4)*0.07 -> 0 | BG46: =COUNTIFS(E46:BB46,">=0",E46:BB46,"<=1") -> 0 | BH46: =IF(BC46=0,"ยังไม่ประเมิน",IF(BF46>=0.8,"ดีมาก",IF(BF46>=0.65,"ดี",IF(BF46>=0.5,"ต้องพัฒนา","เร่งแก้ไข")))) -> ยังไม่ประเมิน | BI46: =IF(BC46=0,"ยังไม่ประเมิน",INDEX($BJ$1:$BQ$1,1,MATCH(MIN(BJ46:BQ46),BJ46:BQ46,0))) -> ยังไม่ประเมิน | BJ46: =SUM(E46:K46)/(7*4) -> 0 | BK46: =SUM(L46:R46)/(7*4) -> 0 | BL46: =SUM(S46:X46)/(6*4) -> 0 | BM46: =SUM(Y46:AE46)/(7*4) -> 0 | BN46: =SUM(AF46:AL46)/(7*4) -> 0 | BO46: =SUM(AM46:AS46)/(7*4) -> 0 | BP46: =SUM(AT46:AX46)/(5*4) -> 0 | BQ46: =SUM(AY46:BB46)/(4*4) -> 0
A47: RAP69-046 | B47: =IFERROR(VLOOKUP(A47,'01_ข้อมูลร้าน'!$A$2:$B$51,2,FALSE),"") -> ร้านที่ 46 | C47: T0 | BC47: =COUNT(E47:BB47)/50 -> 0 | BD47: =SUM(E47:BB47) -> 0 | BE47: =BD47/200 -> 0 | BF47: =SUM(E47:K47)/(7*4)*0.12+SUM(L47:R47)/(7*4)*0.15+SUM(S47:X47)/(6*4)*0.1+SUM(Y47:AE47)/(7*4)*0.13+SUM(AF47:AL47)/(7*4)*0.2+SUM(AM47:AS47)/(7*4)*0.18+SUM(AT47:AX47)/(5*4)*0.05+SUM(AY47:BB47)/(4*4)*0.07 -> 0 | BG47: =COUNTIFS(E47:BB47,">=0",E47:BB47,"<=1") -> 0 | BH47: =IF(BC47=0,"ยังไม่ประเมิน",IF(BF47>=0.8,"ดีมาก",IF(BF47>=0.65,"ดี",IF(BF47>=0.5,"ต้องพัฒนา","เร่งแก้ไข")))) -> ยังไม่ประเมิน | BI47: =IF(BC47=0,"ยังไม่ประเมิน",INDEX($BJ$1:$BQ$1,1,MATCH(MIN(BJ47:BQ47),BJ47:BQ47,0))) -> ยังไม่ประเมิน | BJ47: =SUM(E47:K47)/(7*4) -> 0 | BK47: =SUM(L47:R47)/(7*4) -> 0 | BL47: =SUM(S47:X47)/(6*4) -> 0 | BM47: =SUM(Y47:AE47)/(7*4) -> 0 | BN47: =SUM(AF47:AL47)/(7*4) -> 0 | BO47: =SUM(AM47:AS47)/(7*4) -> 0 | BP47: =SUM(AT47:AX47)/(5*4) -> 0 | BQ47: =SUM(AY47:BB47)/(4*4) -> 0
A48: RAP69-047 | B48: =IFERROR(VLOOKUP(A48,'01_ข้อมูลร้าน'!$A$2:$B$51,2,FALSE),"") -> ร้านที่ 47 | C48: T0 | BC48: =COUNT(E48:BB48)/50 -> 0 | BD48: =SUM(E48:BB48) -> 0 | BE48: =BD48/200 -> 0 | BF48: =SUM(E48:K48)/(7*4)*0.12+SUM(L48:R48)/(7*4)*0.15+SUM(S48:X48)/(6*4)*0.1+SUM(Y48:AE48)/(7*4)*0.13+SUM(AF48:AL48)/(7*4)*0.2+SUM(AM48:AS48)/(7*4)*0.18+SUM(AT48:AX48)/(5*4)*0.05+SUM(AY48:BB48)/(4*4)*0.07 -> 0 | BG48: =COUNTIFS(E48:BB48,">=0",E48:BB48,"<=1") -> 0 | BH48: =IF(BC48=0,"ยังไม่ประเมิน",IF(BF48>=0.8,"ดีมาก",IF(BF48>=0.65,"ดี",IF(BF48>=0.5,"ต้องพัฒนา","เร่งแก้ไข")))) -> ยังไม่ประเมิน | BI48: =IF(BC48=0,"ยังไม่ประเมิน",INDEX($BJ$1:$BQ$1,1,MATCH(MIN(BJ48:BQ48),BJ48:BQ48,0))) -> ยังไม่ประเมิน | BJ48: =SUM(E48:K48)/(7*4) -> 0 | BK48: =SUM(L48:R48)/(7*4) -> 0 | BL48: =SUM(S48:X48)/(6*4) -> 0 | BM48: =SUM(Y48:AE48)/(7*4) -> 0 | BN48: =SUM(AF48:AL48)/(7*4) -> 0 | BO48: =SUM(AM48:AS48)/(7*4) -> 0 | BP48: =SUM(AT48:AX48)/(5*4) -> 0 | BQ48: =SUM(AY48:BB48)/(4*4) -> 0
A49: RAP69-048 | B49: =IFERROR(VLOOKUP(A49,'01_ข้อมูลร้าน'!$A$2:$B$51,2,FALSE),"") -> ร้านที่ 48 | C49: T0 | BC49: =COUNT(E49:BB49)/50 -> 0 | BD49: =SUM(E49:BB49) -> 0 | BE49: =BD49/200 -> 0 | BF49: =SUM(E49:K49)/(7*4)*0.12+SUM(L49:R49)/(7*4)*0.15+SUM(S49:X49)/(6*4)*0.1+SUM(Y49:AE49)/(7*4)*0.13+SUM(AF49:AL49)/(7*4)*0.2+SUM(AM49:AS49)/(7*4)*0.18+SUM(AT49:AX49)/(5*4)*0.05+SUM(AY49:BB49)/(4*4)*0.07 -> 0 | BG49: =COUNTIFS(E49:BB49,">=0",E49:BB49,"<=1") -> 0 | BH49: =IF(BC49=0,"ยังไม่ประเมิน",IF(BF49>=0.8,"ดีมาก",IF(BF49>=0.65,"ดี",IF(BF49>=0.5,"ต้องพัฒนา","เร่งแก้ไข")))) -> ยังไม่ประเมิน | BI49: =IF(BC49=0,"ยังไม่ประเมิน",INDEX($BJ$1:$BQ$1,1,MATCH(MIN(BJ49:BQ49),BJ49:BQ49,0))) -> ยังไม่ประเมิน | BJ49: =SUM(E49:K49)/(7*4) -> 0 | BK49: =SUM(L49:R49)/(7*4) -> 0 | BL49: =SUM(S49:X49)/(6*4) -> 0 | BM49: =SUM(Y49:AE49)/(7*4) -> 0 | BN49: =SUM(AF49:AL49)/(7*4) -> 0 | BO49: =SUM(AM49:AS49)/(7*4) -> 0 | BP49: =SUM(AT49:AX49)/(5*4) -> 0 | BQ49: =SUM(AY49:BB49)/(4*4) -> 0
A50: RAP69-049 | B50: =IFERROR(VLOOKUP(A50,'01_ข้อมูลร้าน'!$A$2:$B$51,2,FALSE),"") -> ร้านที่ 49 | C50: T0 | BC50: =COUNT(E50:BB50)/50 -> 0 | BD50: =SUM(E50:BB50) -> 0 | BE50: =BD50/200 -> 0 | BF50: =SUM(E50:K50)/(7*4)*0.12+SUM(L50:R50)/(7*4)*0.15+SUM(S50:X50)/(6*4)*0.1+SUM(Y50:AE50)/(7*4)*0.13+SUM(AF50:AL50)/(7*4)*0.2+SUM(AM50:AS50)/(7*4)*0.18+SUM(AT50:AX50)/(5*4)*0.05+SUM(AY50:BB50)/(4*4)*0.07 -> 0 | BG50: =COUNTIFS(E50:BB50,">=0",E50:BB50,"<=1") -> 0 | BH50: =IF(BC50=0,"ยังไม่ประเมิน",IF(BF50>=0.8,"ดีมาก",IF(BF50>=0.65,"ดี",IF(BF50>=0.5,"ต้องพัฒนา","เร่งแก้ไข")))) -> ยังไม่ประเมิน | BI50: =IF(BC50=0,"ยังไม่ประเมิน",INDEX($BJ$1:$BQ$1,1,MATCH(MIN(BJ50:BQ50),BJ50:BQ50,0))) -> ยังไม่ประเมิน | BJ50: =SUM(E50:K50)/(7*4) -> 0 | BK50: =SUM(L50:R50)/(7*4) -> 0 | BL50: =SUM(S50:X50)/(6*4) -> 0 | BM50: =SUM(Y50:AE50)/(7*4) -> 0 | BN50: =SUM(AF50:AL50)/(7*4) -> 0 | BO50: =SUM(AM50:AS50)/(7*4) -> 0 | BP50: =SUM(AT50:AX50)/(5*4) -> 0 | BQ50: =SUM(AY50:BB50)/(4*4) -> 0
A51: RAP69-050 | B51: =IFERROR(VLOOKUP(A51,'01_ข้อมูลร้าน'!$A$2:$B$51,2,FALSE),"") -> ร้านที่ 50 | C51: T0 | BC51: =COUNT(E51:BB51)/50 -> 0 | BD51: =SUM(E51:BB51) -> 0 | BE51: =BD51/200 -> 0 | BF51: =SUM(E51:K51)/(7*4)*0.12+SUM(L51:R51)/(7*4)*0.15+SUM(S51:X51)/(6*4)*0.1+SUM(Y51:AE51)/(7*4)*0.13+SUM(AF51:AL51)/(7*4)*0.2+SUM(AM51:AS51)/(7*4)*0.18+SUM(AT51:AX51)/(5*4)*0.05+SUM(AY51:BB51)/(4*4)*0.07 -> 0 | BG51: =COUNTIFS(E51:BB51,">=0",E51:BB51,"<=1") -> 0 | BH51: =IF(BC51=0,"ยังไม่ประเมิน",IF(BF51>=0.8,"ดีมาก",IF(BF51>=0.65,"ดี",IF(BF51>=0.5,"ต้องพัฒนา","เร่งแก้ไข")))) -> ยังไม่ประเมิน | BI51: =IF(BC51=0,"ยังไม่ประเมิน",INDEX($BJ$1:$BQ$1,1,MATCH(MIN(BJ51:BQ51),BJ51:BQ51,0))) -> ยังไม่ประเมิน | BJ51: =SUM(E51:K51)/(7*4) -> 0 | BK51: =SUM(L51:R51)/(7*4) -> 0 | BL51: =SUM(S51:X51)/(6*4) -> 0 | BM51: =SUM(Y51:AE51)/(7*4) -> 0 | BN51: =SUM(AF51:AL51)/(7*4) -> 0 | BO51: =SUM(AM51:AS51)/(7*4) -> 0 | BP51: =SUM(AT51:AX51)/(5*4) -> 0 | BQ51: =SUM(AY51:BB51)/(4*4) -> 0

Sheet 03_สรุปคะแนน
A1: รหัสร้าน | B1: ชื่อร้าน | C1: จังหวัด | D1: ความครบถ้วน | E1: คะแนนดิบ | F1: คะแนนรวม % | G1: คะแนนถ่วงน้ำหนัก | H1: Red Flag | I1: ระดับรวม | J1: มิติเร่งแก้ไข | K1: มิติ 1 | L1: มิติ 2 | M1: มิติ 3 | N1: มิติ 4 | O1: มิติ 5 | P1: มิติ 6 | Q1: มิติ 7 | R1: มิติ 8 | S1: ข้อเสนอแนะ
A2: RAP69-001 | B2: =IFERROR(VLOOKUP(A2,'01_ข้อมูลร้าน'!$A$2:$C$51,2,FALSE),"") -> Seed restaurant | C2: =IFERROR(VLOOKUP(A2,'01_ข้อมูลร้าน'!$A$2:$C$51,3,FALSE),"") | D2: =IFERROR(VLOOKUP(A2,'02_ประเมิน50ร้าน'!$A$2:$BR$51,55,FALSE),"") -> 1 | E2: =IFERROR(VLOOKUP(A2,'02_ประเมิน50ร้าน'!$A$2:$BR$51,56,FALSE),"") -> 150 | F2: =IFERROR(VLOOKUP(A2,'02_ประเมิน50ร้าน'!$A$2:$BR$51,57,FALSE),"") -> 0.75 | G2: =IFERROR(VLOOKUP(A2,'02_ประเมิน50ร้าน'!$A$2:$BR$51,58,FALSE),"") -> 0.74145833 | H2: =IFERROR(VLOOKUP(A2,'02_ประเมิน50ร้าน'!$A$2:$BR$51,59,FALSE),"") -> 0 | I2: =IFERROR(VLOOKUP(A2,'02_ประเมิน50ร้าน'!$A$2:$BR$51,60,FALSE),"") -> ดี | J2: =IFERROR(VLOOKUP(A2,'02_ประเมิน50ร้าน'!$A$2:$BR$51,61,FALSE),"") -> มิติ 6 | K2: =IFERROR(VLOOKUP(A2,'02_ประเมิน50ร้าน'!$A$2:$BR$51,62,FALSE),"") -> 0.67857143 | L2: =IFERROR(VLOOKUP(A2,'02_ประเมิน50ร้าน'!$A$2:$BR$51,63,FALSE),"") -> 0.85714286 | M2: =IFERROR(VLOOKUP(A2,'02_ประเมิน50ร้าน'!$A$2:$BR$51,64,FALSE),"") -> 0.83333333 | N2: =IFERROR(VLOOKUP(A2,'02_ประเมิน50ร้าน'!$A$2:$BR$51,65,FALSE),"") -> 0.71428571 | O2: =IFERROR(VLOOKUP(A2,'02_ประเมิน50ร้าน'!$A$2:$BR$51,66,FALSE),"") -> 0.71428571 | P2: =IFERROR(VLOOKUP(A2,'02_ประเมิน50ร้าน'!$A$2:$BR$51,67,FALSE),"") -> 0.60714286 | Q2: =IFERROR(VLOOKUP(A2,'02_ประเมิน50ร้าน'!$A$2:$BR$51,68,FALSE),"") -> 0.75 | R2: =IFERROR(VLOOKUP(A2,'02_ประเมิน50ร้าน'!$A$2:$BR$51,69,FALSE),"") -> 0.9375 | S2: =IF(D2=0,"กรอกคะแนนประเมินก่อน",IF(H2>0,"ตรวจข้อคะแนน 0-1 และจัดทำแผน 7/30/90 วัน","ติดตามพัฒนาตามมิติที่คะแนนต่ำสุด")) -> ติดตามพัฒนาตามมิติที่คะแนนต่ำสุด | T2: =IFERROR(VLOOKUP(A2,'02_ประเมิน50ร้าน'!$A$2:$BR$51,71,FALSE),"")
A3: RAP69-002 | B3: =IFERROR(VLOOKUP(A3,'01_ข้อมูลร้าน'!$A$2:$C$51,2,FALSE),"") -> ก๋วยเตี๋ยวเรือคุณปุ๊ก | C3: =IFERROR(VLOOKUP(A3,'01_ข้อมูลร้าน'!$A$2:$C$51,3,FALSE),"") | D3: =IFERROR(VLOOKUP(A3,'02_ประเมิน50ร้าน'!$A$2:$BR$51,55,FALSE),"") -> 1 | E3: =IFERROR(VLOOKUP(A3,'02_ประเมิน50ร้าน'!$A$2:$BR$51,56,FALSE),"") -> 112 | F3: =IFERROR(VLOOKUP(A3,'02_ประเมิน50ร้าน'!$A$2:$BR$51,57,FALSE),"") -> 0.56 | G3: =IFERROR(VLOOKUP(A3,'02_ประเมิน50ร้าน'!$A$2:$BR$51,58,FALSE),"") -> 0.55580357 | H3: =IFERROR(VLOOKUP(A3,'02_ประเมิน50ร้าน'!$A$2:$BR$51,59,FALSE),"") -> 16 | I3: =IFERROR(VLOOKUP(A3,'02_ประเมิน50ร้าน'!$A$2:$BR$51,60,FALSE),"") -> ต้องพัฒนา | J3: =IFERROR(VLOOKUP(A3,'02_ประเมิน50ร้าน'!$A$2:$BR$51,61,FALSE),"") -> มิติ 2 | K3: =IFERROR(VLOOKUP(A3,'02_ประเมิน50ร้าน'!$A$2:$BR$51,62,FALSE),"") -> 0.82142857 | L3: =IFERROR(VLOOKUP(A3,'02_ประเมิน50ร้าน'!$A$2:$BR$51,63,FALSE),"") -> 0.25 | M3: =IFERROR(VLOOKUP(A3,'02_ประเมิน50ร้าน'!$A$2:$BR$51,64,FALSE),"") -> 0.625 | N3: =IFERROR(VLOOKUP(A3,'02_ประเมิน50ร้าน'!$A$2:$BR$51,65,FALSE),"") -> 0.53571429 | O3: =IFERROR(VLOOKUP(A3,'02_ประเมิน50ร้าน'!$A$2:$BR$51,66,FALSE),"") -> 0.57142857 | P3: =IFERROR(VLOOKUP(A3,'02_ประเมิน50ร้าน'!$A$2:$BR$51,67,FALSE),"") -> 0.53571429 | Q3: =IFERROR(VLOOKUP(A3,'02_ประเมิน50ร้าน'!$A$2:$BR$51,68,FALSE),"") -> 0.4 | R3: =IFERROR(VLOOKUP(A3,'02_ประเมิน50ร้าน'!$A$2:$BR$51,69,FALSE),"") -> 0.8125 | S3: =IF(D3=0,"กรอกคะแนนประเมินก่อน",IF(H3>0,"ตรวจข้อคะแนน 0-1 และจัดทำแผน 7/30/90 วัน","ติดตามพัฒนาตามมิติที่คะแนนต่ำสุด")) -> ตรวจข้อคะแนน 0-1 และจัดทำแผน 7/30/90 วัน | T3: =IFERROR(VLOOKUP(A3,'02_ประเมิน50ร้าน'!$A$2:$BR$51,71,FALSE),"")
A4: RAP69-003 | B4: =IFERROR(VLOOKUP(A4,'01_ข้อมูลร้าน'!$A$2:$C$51,2,FALSE),"") -> บ้าน-บ้าน สุขพอดี | C4: =IFERROR(VLOOKUP(A4,'01_ข้อมูลร้าน'!$A$2:$C$51,3,FALSE),"") | D4: =IFERROR(VLOOKUP(A4,'02_ประเมิน50ร้าน'!$A$2:$BR$51,55,FALSE),"") -> 1 | E4: =IFERROR(VLOOKUP(A4,'02_ประเมิน50ร้าน'!$A$2:$BR$51,56,FALSE),"") -> 88 | F4: =IFERROR(VLOOKUP(A4,'02_ประเมิน50ร้าน'!$A$2:$BR$51,57,FALSE),"") -> 0.44 | G4: =IFERROR(VLOOKUP(A4,'02_ประเมิน50ร้าน'!$A$2:$BR$51,58,FALSE),"") -> 0.38776786 | H4: =IFERROR(VLOOKUP(A4,'02_ประเมิน50ร้าน'!$A$2:$BR$51,59,FALSE),"") -> 24 | I4: =IFERROR(VLOOKUP(A4,'02_ประเมิน50ร้าน'!$A$2:$BR$51,60,FALSE),"") -> เร่งแก้ไข | J4: =IFERROR(VLOOKUP(A4,'02_ประเมิน50ร้าน'!$A$2:$BR$51,61,FALSE),"") -> มิติ 2 | K4: =IFERROR(VLOOKUP(A4,'02_ประเมิน50ร้าน'!$A$2:$BR$51,62,FALSE),"") -> 0.25 | L4: =IFERROR(VLOOKUP(A4,'02_ประเมิน50ร้าน'!$A$2:$BR$51,63,FALSE),"") -> 0 | M4: =IFERROR(VLOOKUP(A4,'02_ประเมิน50ร้าน'!$A$2:$BR$51,64,FALSE),"") -> 0.5 | N4: =IFERROR(VLOOKUP(A4,'02_ประเมิน50ร้าน'!$A$2:$BR$51,65,FALSE),"") -> 0.89285714 | O4: =IFERROR(VLOOKUP(A4,'02_ประเมิน50ร้าน'!$A$2:$BR$51,66,FALSE),"") -> 0.32142857 | P4: =IFERROR(VLOOKUP(A4,'02_ประเมิน50ร้าน'!$A$2:$BR$51,67,FALSE),"") -> 0.10714286 | Q4: =IFERROR(VLOOKUP(A4,'02_ประเมิน50ร้าน'!$A$2:$BR$51,68,FALSE),"") -> 0.85 | R4: =IFERROR(VLOOKUP(A4,'02_ประเมิน50ร้าน'!$A$2:$BR$51,69,FALSE),"") -> 0.9375 | S4: =IF(D4=0,"กรอกคะแนนประเมินก่อน",IF(H4>0,"ตรวจข้อคะแนน 0-1 และจัดทำแผน 7/30/90 วัน","ติดตามพัฒนาตามมิติที่คะแนนต่ำสุด")) -> ตรวจข้อคะแนน 0-1 และจัดทำแผน 7/30/90 วัน | T4: =IFERROR(VLOOKUP(A4,'02_ประเมิน50ร้าน'!$A$2:$BR$51,71,FALSE),"")
A5: RAP69-004 | B5: =IFERROR(VLOOKUP(A5,'01_ข้อมูลร้าน'!$A$2:$C$51,2,FALSE),"") -> แฟรนไชส์ก๋วยเตี๋ยวปากหม้อแม่ว่าดี | C5: =IFERROR(VLOOKUP(A5,'01_ข้อมูลร้าน'!$A$2:$C$51,3,FALSE),"") | D5: =IFERROR(VLOOKUP(A5,'02_ประเมิน50ร้าน'!$A$2:$BR$51,55,FALSE),"") -> 1 | E5: =IFERROR(VLOOKUP(A5,'02_ประเมิน50ร้าน'!$A$2:$BR$51,56,FALSE),"") -> 162 | F5: =IFERROR(VLOOKUP(A5,'02_ประเมิน50ร้าน'!$A$2:$BR$51,57,FALSE),"") -> 0.81 | G5: =IFERROR(VLOOKUP(A5,'02_ประเมิน50ร้าน'!$A$2:$BR$51,58,FALSE),"") -> 0.79264881 | H5: =IFERROR(VLOOKUP(A5,'02_ประเมิน50ร้าน'!$A$2:$BR$51,59,FALSE),"") -> 3 | I5: =IFERROR(VLOOKUP(A5,'02_ประเมิน50ร้าน'!$A$2:$BR$51,60,FALSE),"") -> ดี | J5: =IFERROR(VLOOKUP(A5,'02_ประเมิน50ร้าน'!$A$2:$BR$51,61,FALSE),"") -> มิติ 2 | K5: =IFERROR(VLOOKUP(A5,'02_ประเมิน50ร้าน'!$A$2:$BR$51,62,FALSE),"") -> 0.92857143 | L5: =IFERROR(VLOOKUP(A5,'02_ประเมิน50ร้าน'!$A$2:$BR$51,63,FALSE),"") -> 0.57142857 | M5: =IFERROR(VLOOKUP(A5,'02_ประเมิน50ร้าน'!$A$2:$BR$51,64,FALSE),"") -> 0.79166667 | N5: =IFERROR(VLOOKUP(A5,'02_ประเมิน50ร้าน'!$A$2:$BR$51,65,FALSE),"") -> 0.89285714 | O5: =IFERROR(VLOOKUP(A5,'02_ประเมิน50ร้าน'!$A$2:$BR$51,66,FALSE),"") -> 0.85714286 | P5: =IFERROR(VLOOKUP(A5,'02_ประเมิน50ร้าน'!$A$2:$BR$51,67,FALSE),"") -> 0.64285714 | Q5: =IFERROR(VLOOKUP(A5,'02_ประเมิน50ร้าน'!$A$2:$BR$51,68,FALSE),"") -> 0.95 | R5: =IFERROR(VLOOKUP(A5,'02_ประเมิน50ร้าน'!$A$2:$BR$51,69,FALSE),"") -> 0.9375 | S5: =IF(D5=0,"กรอกคะแนนประเมินก่อน",IF(H5>0,"ตรวจข้อคะแนน 0-1 และจัดทำแผน 7/30/90 วัน","ติดตามพัฒนาตามมิติที่คะแนนต่ำสุด")) -> ตรวจข้อคะแนน 0-1 และจัดทำแผน 7/30/90 วัน | T5: =IFERROR(VLOOKUP(A5,'02_ประเมิน50ร้าน'!$A$2:$BR$51,71,FALSE),"")
A6: RAP69-005 | B6: =IFERROR(VLOOKUP(A6,'01_ข้อมูลร้าน'!$A$2:$C$51,2,FALSE),"") -> 16Brix Melon Farm&Café | C6: =IFERROR(VLOOKUP(A6,'01_ข้อมูลร้าน'!$A$2:$C$51,3,FALSE),"") | D6: =IFERROR(VLOOKUP(A6,'02_ประเมิน50ร้าน'!$A$2:$BR$51,55,FALSE),"") -> 1 | E6: =IFERROR(VLOOKUP(A6,'02_ประเมิน50ร้าน'!$A$2:$BR$51,56,FALSE),"") -> 154 | F6: =IFERROR(VLOOKUP(A6,'02_ประเมิน50ร้าน'!$A$2:$BR$51,57,FALSE),"") -> 0.77 | G6: =IFERROR(VLOOKUP(A6,'02_ประเมิน50ร้าน'!$A$2:$BR$51,58,FALSE),"") -> 0.74741071 | H6: =IFERROR(VLOOKUP(A6,'02_ประเมิน50ร้าน'!$A$2:$BR$51,59,FALSE),"") -> 6 | I6: =IFERROR(VLOOKUP(A6,'02_ประเมิน50ร้าน'!$A$2:$BR$51,60,FALSE),"") -> ดี | J6: =IFERROR(VLOOKUP(A6,'02_ประเมิน50ร้าน'!$A$2:$BR$51,61,FALSE),"") -> มิติ 2 | K6: =IFERROR(VLOOKUP(A6,'02_ประเมิน50ร้าน'!$A$2:$BR$51,62,FALSE),"") -> 0.89285714 | L6: =IFERROR(VLOOKUP(A6,'02_ประเมิน50ร้าน'!$A$2:$BR$51,63,FALSE),"") -> 0.42857143 | M6: =IFERROR(VLOOKUP(A6,'02_ประเมิน50ร้าน'!$A$2:$BR$51,64,FALSE),"") -> 0.875 | N6: =IFERROR(VLOOKUP(A6,'02_ประเมิน50ร้าน'!$A$2:$BR$51,65,FALSE),"") -> 0.82142857 | O6: =IFERROR(VLOOKUP(A6,'02_ประเมิน50ร้าน'!$A$2:$BR$51,66,FALSE),"") -> 0.89285714 | P6: =IFERROR(VLOOKUP(A6,'02_ประเมิน50ร้าน'!$A$2:$BR$51,67,FALSE),"") -> 0.5 | Q6: =IFERROR(VLOOKUP(A6,'02_ประเมิน50ร้าน'!$A$2:$BR$51,68,FALSE),"") -> 0.95 | R6: =IFERROR(VLOOKUP(A6,'02_ประเมิน50ร้าน'!$A$2:$BR$51,69,FALSE),"") -> 0.9375 | S6: =IF(D6=0,"กรอกคะแนนประเมินก่อน",IF(H6>0,"ตรวจข้อคะแนน 0-1 และจัดทำแผน 7/30/90 วัน","ติดตามพัฒนาตามมิติที่คะแนนต่ำสุด")) -> ตรวจข้อคะแนน 0-1 และจัดทำแผน 7/30/90 วัน | T6: =IFERROR(VLOOKUP(A6,'02_ประเมิน50ร้าน'!$A$2:$BR$51,71,FALSE),"")
A7: RAP69-006 | B7: =IFERROR(VLOOKUP(A7,'01_ข้อมูลร้าน'!$A$2:$C$51,2,FALSE),"") -> ร้านอีสานเฮาส์ (304 ปราจีนบุรี) | C7: =IFERROR(VLOOKUP(A7,'01_ข้อมูลร้าน'!$A$2:$C$51,3,FALSE),"") | D7: =IFERROR(VLOOKUP(A7,'02_ประเมิน50ร้าน'!$A$2:$BR$51,55,FALSE),"") -> 1 | E7: =IFERROR(VLOOKUP(A7,'02_ประเมิน50ร้าน'!$A$2:$BR$51,56,FALSE),"") -> 177 | F7: =IFERROR(VLOOKUP(A7,'02_ประเมิน50ร้าน'!$A$2:$BR$51,57,FALSE),"") -> 0.885 | G7: =IFERROR(VLOOKUP(A7,'02_ประเมิน50ร้าน'!$A$2:$BR$51,58,FALSE),"") -> 0.87107143 | H7: =IFERROR(VLOOKUP(A7,'02_ประเมิน50ร้าน'!$A$2:$BR$51,59,FALSE),"") -> 2 | I7: =IFERROR(VLOOKUP(A7,'02_ประเมิน50ร้าน'!$A$2:$BR$51,60,FALSE),"") -> ดีมาก | J7: =IFERROR(VLOOKUP(A7,'02_ประเมิน50ร้าน'!$A$2:$BR$51,61,FALSE),"") -> มิติ 1 | K7: =IFERROR(VLOOKUP(A7,'02_ประเมิน50ร้าน'!$A$2:$BR$51,62,FALSE),"") -> 0.71428571 | L7: =IFERROR(VLOOKUP(A7,'02_ประเมิน50ร้าน'!$A$2:$BR$51,63,FALSE),"") -> 0.92857143 | M7: =IFERROR(VLOOKUP(A7,'02_ประเมิน50ร้าน'!$A$2:$BR$51,64,FALSE),"") -> 1 | N7: =IFERROR(VLOOKUP(A7,'02_ประเมิน50ร้าน'!$A$2:$BR$51,65,FALSE),"") -> 1 | O7: =IFERROR(VLOOKUP(A7,'02_ประเมิน50ร้าน'!$A$2:$BR$51,66,FALSE),"") -> 0.78571429 | P7: =IFERROR(VLOOKUP(A7,'02_ประเมิน50ร้าน'!$A$2:$BR$51,67,FALSE),"") -> 0.78571429 | Q7: =IFERROR(VLOOKUP(A7,'02_ประเมิน50ร้าน'!$A$2:$BR$51,68,FALSE),"") -> 0.95 | R7: =IFERROR(VLOOKUP(A7,'02_ประเมิน50ร้าน'!$A$2:$BR$51,69,FALSE),"") -> 1 | S7: =IF(D7=0,"กรอกคะแนนประเมินก่อน",IF(H7>0,"ตรวจข้อคะแนน 0-1 และจัดทำแผน 7/30/90 วัน","ติดตามพัฒนาตามมิติที่คะแนนต่ำสุด")) -> ตรวจข้อคะแนน 0-1 และจัดทำแผน 7/30/90 วัน | T7: =IFERROR(VLOOKUP(A7,'02_ประเมิน50ร้าน'!$A$2:$BR$51,71,FALSE),"")
A8: RAP69-007 | B8: =IFERROR(VLOOKUP(A8,'01_ข้อมูลร้าน'!$A$2:$C$51,2,FALSE),"") -> ร้านคำนิยม | C8: =IFERROR(VLOOKUP(A8,'01_ข้อมูลร้าน'!$A$2:$C$51,3,FALSE),"") | D8: =IFERROR(VLOOKUP(A8,'02_ประเมิน50ร้าน'!$A$2:$BR$51,55,FALSE),"") -> 1 | E8: =IFERROR(VLOOKUP(A8,'02_ประเมิน50ร้าน'!$A$2:$BR$51,56,FALSE),"") -> 161 | F8: =IFERROR(VLOOKUP(A8,'02_ประเมิน50ร้าน'!$A$2:$BR$51,57,FALSE),"") -> 0.805 | G8: =IFERROR(VLOOKUP(A8,'02_ประเมิน50ร้าน'!$A$2:$BR$51,58,FALSE),"") -> 0.7827381 | H8: =IFERROR(VLOOKUP(A8,'02_ประเมิน50ร้าน'!$A$2:$BR$51,59,FALSE),"") -> 3 | I8: =IFERROR(VLOOKUP(A8,'02_ประเมิน50ร้าน'!$A$2:$BR$51,60,FALSE),"") -> ดี | J8: =IFERROR(VLOOKUP(A8,'02_ประเมิน50ร้าน'!$A$2:$BR$51,61,FALSE),"") -> มิติ 5 | K8: =IFERROR(VLOOKUP(A8,'02_ประเมิน50ร้าน'!$A$2:$BR$51,62,FALSE),"") -> 0.75 | L8: =IFERROR(VLOOKUP(A8,'02_ประเมิน50ร้าน'!$A$2:$BR$51,63,FALSE),"") -> 0.78571429 | M8: =IFERROR(VLOOKUP(A8,'02_ประเมิน50ร้าน'!$A$2:$BR$51,64,FALSE),"") -> 0.91666667 | N8: =IFERROR(VLOOKUP(A8,'02_ประเมิน50ร้าน'!$A$2:$BR$51,65,FALSE),"") -> 0.92857143 | O8: =IFERROR(VLOOKUP(A8,'02_ประเมิน50ร้าน'!$A$2:$BR$51,66,FALSE),"") -> 0.60714286 | P8: =IFERROR(VLOOKUP(A8,'02_ประเมิน50ร้าน'!$A$2:$BR$51,67,FALSE),"") -> 0.71428571 | Q8: =IFERROR(VLOOKUP(A8,'02_ประเมิน50ร้าน'!$A$2:$BR$51,68,FALSE),"") -> 0.85 | R8: =IFERROR(VLOOKUP(A8,'02_ประเมิน50ร้าน'!$A$2:$BR$51,69,FALSE),"") -> 1 | S8: =IF(D8=0,"กรอกคะแนนประเมินก่อน",IF(H8>0,"ตรวจข้อคะแนน 0-1 และจัดทำแผน 7/30/90 วัน","ติดตามพัฒนาตามมิติที่คะแนนต่ำสุด")) -> ตรวจข้อคะแนน 0-1 และจัดทำแผน 7/30/90 วัน | T8: =IFERROR(VLOOKUP(A8,'02_ประเมิน50ร้าน'!$A$2:$BR$51,71,FALSE),"")
A9: RAP69-008 | B9: =IFERROR(VLOOKUP(A9,'01_ข้อมูลร้าน'!$A$2:$C$51,2,FALSE),"") -> ร้านอรวรรณบ้านเพ | C9: =IFERROR(VLOOKUP(A9,'01_ข้อมูลร้าน'!$A$2:$C$51,3,FALSE),"") | D9: =IFERROR(VLOOKUP(A9,'02_ประเมิน50ร้าน'!$A$2:$BR$51,55,FALSE),"") -> 1 | E9: =IFERROR(VLOOKUP(A9,'02_ประเมิน50ร้าน'!$A$2:$BR$51,56,FALSE),"") -> 87 | F9: =IFERROR(VLOOKUP(A9,'02_ประเมิน50ร้าน'!$A$2:$BR$51,57,FALSE),"") -> 0.435 | G9: =IFERROR(VLOOKUP(A9,'02_ประเมิน50ร้าน'!$A$2:$BR$51,58,FALSE),"") -> 0.4039881 | H9: =IFERROR(VLOOKUP(A9,'02_ประเมิน50ร้าน'!$A$2:$BR$51,59,FALSE),"") -> 26 | I9: =IFERROR(VLOOKUP(A9,'02_ประเมิน50ร้าน'!$A$2:$BR$51,60,FALSE),"") -> เร่งแก้ไข | J9: =IFERROR(VLOOKUP(A9,'02_ประเมิน50ร้าน'!$A$2:$BR$51,61,FALSE),"") -> มิติ 2 | K9: =IFERROR(VLOOKUP(A9,'02_ประเมิน50ร้าน'!$A$2:$BR$51,62,FALSE),"") -> 0.42857143 | L9: =IFERROR(VLOOKUP(A9,'02_ประเมิน50ร้าน'!$A$2:$BR$51,63,FALSE),"") -> 0.14285714 | M9: =IFERROR(VLOOKUP(A9,'02_ประเมิน50ร้าน'!$A$2:$BR$51,64,FALSE),"") -> 0.41666667 | N9: =IFERROR(VLOOKUP(A9,'02_ประเมิน50ร้าน'!$A$2:$BR$51,65,FALSE),"") -> 0.42857143 | O9: =IFERROR(VLOOKUP(A9,'02_ประเมิน50ร้าน'!$A$2:$BR$51,66,FALSE),"") -> 0.32142857 | P9: =IFERROR(VLOOKUP(A9,'02_ประเมิน50ร้าน'!$A$2:$BR$51,67,FALSE),"") -> 0.39285714 | Q9: =IFERROR(VLOOKUP(A9,'02_ประเมิน50ร้าน'!$A$2:$BR$51,68,FALSE),"") -> 0.75 | R9: =IFERROR(VLOOKUP(A9,'02_ประเมิน50ร้าน'!$A$2:$BR$51,69,FALSE),"") -> 0.875 | S9: =IF(D9=0,"กรอกคะแนนประเมินก่อน",IF(H9>0,"ตรวจข้อคะแนน 0-1 และจัดทำแผน 7/30/90 วัน","ติดตามพัฒนาตามมิติที่คะแนนต่ำสุด")) -> ตรวจข้อคะแนน 0-1 และจัดทำแผน 7/30/90 วัน | T9: =IFERROR(VLOOKUP(A9,'02_ประเมิน50ร้าน'!$A$2:$BR$51,71,FALSE),"")
A10: RAP69-009 | B10: =IFERROR(VLOOKUP(A10,'01_ข้อมูลร้าน'!$A$2:$C$51,2,FALSE),"") -> ครัวเดอมอง | C10: =IFERROR(VLOOKUP(A10,'01_ข้อมูลร้าน'!$A$2:$C$51,3,FALSE),"") | D10: =IFERROR(VLOOKUP(A10,'02_ประเมิน50ร้าน'!$A$2:$BR$51,55,FALSE),"") -> 1 | E10: =IFERROR(VLOOKUP(A10,'02_ประเมิน50ร้าน'!$A$2:$BR$51,56,FALSE),"") -> 89 | F10: =IFERROR(VLOOKUP(A10,'02_ประเมิน50ร้าน'!$A$2:$BR$51,57,FALSE),"") -> 0.445 | G10: =IFERROR(VLOOKUP(A10,'02_ประเมิน50ร้าน'!$A$2:$BR$51,58,FALSE),"") -> 0.42449405 | H10: =IFERROR(VLOOKUP(A10,'02_ประเมิน50ร้าน'!$A$2:$BR$51,59,FALSE),"") -> 22 | I10: =IFERROR(VLOOKUP(A10,'02_ประเมิน50ร้าน'!$A$2:$BR$51,60,FALSE),"") -> เร่งแก้ไข | J10: =IFERROR(VLOOKUP(A10,'02_ประเมิน50ร้าน'!$A$2:$BR$51,61,FALSE),"") -> มิติ 4 | K10: =IFERROR(VLOOKUP(A10,'02_ประเมิน50ร้าน'!$A$2:$BR$51,62,FALSE),"") -> 0.75 | L10: =IFERROR(VLOOKUP(A10,'02_ประเมิน50ร้าน'!$A$2:$BR$51,63,FALSE),"") -> 0.39285714 | M10: =IFERROR(VLOOKUP(A10,'02_ประเมิน50ร้าน'!$A$2:$BR$51,64,FALSE),"") -> 0.33333333 | N10: =IFERROR(VLOOKUP(A10,'02_ประเมิน50ร้าน'!$A$2:$BR$51,65,FALSE),"") -> 0.25 | O10: =IFERROR(VLOOKUP(A10,'02_ประเมิน50ร้าน'!$A$2:$BR$51,66,FALSE),"") -> 0.28571429 | P10: =IFERROR(VLOOKUP(A10,'02_ประเมิน50ร้าน'!$A$2:$BR$51,67,FALSE),"") -> 0.39285714 | Q10: =IFERROR(VLOOKUP(A10,'02_ประเมิน50ร้าน'!$A$2:$BR$51,68,FALSE),"") -> 0.5 | R10: =IFERROR(VLOOKUP(A10,'02_ประเมิน50ร้าน'!$A$2:$BR$51,69,FALSE),"") -> 0.8125 | S10: =IF(D10=0,"กรอกคะแนนประเมินก่อน",IF(H10>0,"ตรวจข้อคะแนน 0-1 และจัดทำแผน 7/30/90 วัน","ติดตามพัฒนาตามมิติที่คะแนนต่ำสุด")) -> ตรวจข้อคะแนน 0-1 และจัดทำแผน 7/30/90 วัน | T10: =IFERROR(VLOOKUP(A10,'02_ประเมิน50ร้าน'!$A$2:$BR$51,71,FALSE),"")
A11: RAP69-010 | B11: =IFERROR(VLOOKUP(A11,'01_ข้อมูลร้าน'!$A$2:$C$51,2,FALSE),"") -> เรือนไทย พัทยา | C11: =IFERROR(VLOOKUP(A11,'01_ข้อมูลร้าน'!$A$2:$C$51,3,FALSE),"") | D11: =IFERROR(VLOOKUP(A11,'02_ประเมิน50ร้าน'!$A$2:$BR$51,55,FALSE),"") -> 0.6 | E11: =IFERROR(VLOOKUP(A11,'02_ประเมิน50ร้าน'!$A$2:$BR$51,56,FALSE),"") -> 78 | F11: =IFERROR(VLOOKUP(A11,'02_ประเมิน50ร้าน'!$A$2:$BR$51,57,FALSE),"") -> 0.39 | G11: =IFERROR(VLOOKUP(A11,'02_ประเมิน50ร้าน'!$A$2:$BR$51,58,FALSE),"") -> 0.36080357 | H11: =IFERROR(VLOOKUP(A11,'02_ประเมิน50ร้าน'!$A$2:$BR$51,59,FALSE),"") -> 10 | I11: =IFERROR(VLOOKUP(A11,'02_ประเมิน50ร้าน'!$A$2:$BR$51,60,FALSE),"") -> เร่งแก้ไข | J11: =IFERROR(VLOOKUP(A11,'02_ประเมิน50ร้าน'!$A$2:$BR$51,61,FALSE),"") -> มิติ 3 | K11: =IFERROR(VLOOKUP(A11,'02_ประเมิน50ร้าน'!$A$2:$BR$51,62,FALSE),"") -> 0.5 | L11: =IFERROR(VLOOKUP(A11,'02_ประเมิน50ร้าน'!$A$2:$BR$51,63,FALSE),"") -> 0.57142857 | M11: =IFERROR(VLOOKUP(A11,'02_ประเมิน50ร้าน'!$A$2:$BR$51,64,FALSE),"") -> 0 | N11: =IFERROR(VLOOKUP(A11,'02_ประเมิน50ร้าน'!$A$2:$BR$51,65,FALSE),"") -> 0 | O11: =IFERROR(VLOOKUP(A11,'02_ประเมิน50ร้าน'!$A$2:$BR$51,66,FALSE),"") -> 0 | P11: =IFERROR(VLOOKUP(A11,'02_ประเมิน50ร้าน'!$A$2:$BR$51,67,FALSE),"") -> 0.64285714 | Q11: =IFERROR(VLOOKUP(A11,'02_ประเมิน50ร้าน'!$A$2:$BR$51,68,FALSE),"") -> 0.85 | R11: =IFERROR(VLOOKUP(A11,'02_ประเมิน50ร้าน'!$A$2:$BR$51,69,FALSE),"") -> 0.8125 | S11: =IF(D11=0,"กรอกคะแนนประเมินก่อน",IF(H11>0,"ตรวจข้อคะแนน 0-1 และจัดทำแผน 7/30/90 วัน","ติดตามพัฒนาตามมิติที่คะแนนต่ำสุด")) -> ตรวจข้อคะแนน 0-1 และจัดทำแผน 7/30/90 วัน | T11: =IFERROR(VLOOKUP(A11,'02_ประเมิน50ร้าน'!$A$2:$BR$51,71,FALSE),"")
A12: RAP69-011 | B12: =IFERROR(VLOOKUP(A12,'01_ข้อมูลร้าน'!$A$2:$C$51,2,FALSE),"") -> ร้านอาหาร ทะเลลานโพธิ์ ซีฟู้ด | C12: =IFERROR(VLOOKUP(A12,'01_ข้อมูลร้าน'!$A$2:$C$51,3,FALSE),"") | D12: =IFERROR(VLOOKUP(A12,'02_ประเมิน50ร้าน'!$A$2:$BR$51,55,FALSE),"") -> 1 | E12: =IFERROR(VLOOKUP(A12,'02_ประเมิน50ร้าน'!$A$2:$BR$51,56,FALSE),"") -> 134 | F12: =IFERROR(VLOOKUP(A12,'02_ประเมิน50ร้าน'!$A$2:$BR$51,57,FALSE),"") -> 0.67 | G12: =IFERROR(VLOOKUP(A12,'02_ประเมิน50ร้าน'!$A$2:$BR$51,58,FALSE),"") -> 0.6722619 | H12: =IFERROR(VLOOKUP(A12,'02_ประเมิน50ร้าน'!$A$2:$BR$51,59,FALSE),"") -> 5 | I12: =IFERROR(VLOOKUP(A12,'02_ประเมิน50ร้าน'!$A$2:$BR$51,60,FALSE),"") -> ดี | J12: =IFERROR(VLOOKUP(A12,'02_ประเมิน50ร้าน'!$A$2:$BR$51,61,FALSE),"") -> มิติ 1 | K12: =IFERROR(VLOOKUP(A12,'02_ประเมิน50ร้าน'!$A$2:$BR$51,62,FALSE),"") -> 0.57142857 | L12: =IFERROR(VLOOKUP(A12,'02_ประเมิน50ร้าน'!$A$2:$BR$51,63,FALSE),"") -> 0.78571429 | M12: =IFERROR(VLOOKUP(A12,'02_ประเมิน50ร้าน'!$A$2:$BR$51,64,FALSE),"") -> 0.70833333 | N12: =IFERROR(VLOOKUP(A12,'02_ประเมิน50ร้าน'!$A$2:$BR$51,65,FALSE),"") -> 0.57142857 | O12: =IFERROR(VLOOKUP(A12,'02_ประเมิน50ร้าน'!$A$2:$BR$51,66,FALSE),"") -> 0.57142857 | P12: =IFERROR(VLOOKUP(A12,'02_ประเมิน50ร้าน'!$A$2:$BR$51,67,FALSE),"") -> 0.78571429 | Q12: =IFERROR(VLOOKUP(A12,'02_ประเมิน50ร้าน'!$A$2:$BR$51,68,FALSE),"") -> 0.65 | R12: =IFERROR(VLOOKUP(A12,'02_ประเมิน50ร้าน'!$A$2:$BR$51,69,FALSE),"") -> 0.75 | S12: =IF(D12=0,"กรอกคะแนนประเมินก่อน",IF(H12>0,"ตรวจข้อคะแนน 0-1 และจัดทำแผน 7/30/90 วัน","ติดตามพัฒนาตามมิติที่คะแนนต่ำสุด")) -> ตรวจข้อคะแนน 0-1 และจัดทำแผน 7/30/90 วัน | T12: =IFERROR(VLOOKUP(A12,'02_ประเมิน50ร้าน'!$A$2:$BR$51,71,FALSE),"")
A13: RAP69-012 | B13: =IFERROR(VLOOKUP(A13,'01_ข้อมูลร้าน'!$A$2:$C$51,2,FALSE),"") -> นายกุ่ยไก่หุบบอน @เขาชีจรรย์ | C13: =IFERROR(VLOOKUP(A13,'01_ข้อมูลร้าน'!$A$2:$C$51,3,FALSE),"") | D13: =IFERROR(VLOOKUP(A13,'02_ประเมิน50ร้าน'!$A$2:$BR$51,55,FALSE),"") -> 1 | E13: =IFERROR(VLOOKUP(A13,'02_ประเมิน50ร้าน'!$A$2:$BR$51,56,FALSE),"") -> 134 | F13: =IFERROR(VLOOKUP(A13,'02_ประเมิน50ร้าน'!$A$2:$BR$51,57,FALSE),"") -> 0.67 | G13: =IFERROR(VLOOKUP(A13,'02_ประเมิน50ร้าน'!$A$2:$BR$51,58,FALSE),"") -> 0.6603869 | H13: =IFERROR(VLOOKUP(A13,'02_ประเมิน50ร้าน'!$A$2:$BR$51,59,FALSE),"") -> 6 | I13: =IFERROR(VLOOKUP(A13,'02_ประเมิน50ร้าน'!$A$2:$BR$51,60,FALSE),"") -> ดี | J13: =IFERROR(VLOOKUP(A13,'02_ประเมิน50ร้าน'!$A$2:$BR$51,61,FALSE),"") -> มิติ 4 | K13: =IFERROR(VLOOKUP(A13,'02_ประเมิน50ร้าน'!$A$2:$BR$51,62,FALSE),"") -> 0.64285714 | L13: =IFERROR(VLOOKUP(A13,'02_ประเมิน50ร้าน'!$A$2:$BR$51,63,FALSE),"") -> 0.71428571 | M13: =IFERROR(VLOOKUP(A13,'02_ประเมิน50ร้าน'!$A$2:$BR$51,64,FALSE),"") -> 0.70833333 | N13: =IFERROR(VLOOKUP(A13,'02_ประเมิน50ร้าน'!$A$2:$BR$51,65,FALSE),"") -> 0.42857143 | O13: =IFERROR(VLOOKUP(A13,'02_ประเมิน50ร้าน'!$A$2:$BR$51,66,FALSE),"") -> 0.60714286 | P13: =IFERROR(VLOOKUP(A13,'02_ประเมิน50ร้าน'!$A$2:$BR$51,67,FALSE),"") -> 0.75 | Q13: =IFERROR(VLOOKUP(A13,'02_ประเมิน50ร้าน'!$A$2:$BR$51,68,FALSE),"") -> 0.9 | R13: =IFERROR(VLOOKUP(A13,'02_ประเมิน50ร้าน'!$A$2:$BR$51,69,FALSE),"") -> 0.6875 | S13: =IF(D13=0,"กรอกคะแนนประเมินก่อน",IF(H13>0,"ตรวจข้อคะแนน 0-1 และจัดทำแผน 7/30/90 วัน","ติดตามพัฒนาตามมิติที่คะแนนต่ำสุด")) -> ตรวจข้อคะแนน 0-1 และจัดทำแผน 7/30/90 วัน | T13: =IFERROR(VLOOKUP(A13,'02_ประเมิน50ร้าน'!$A$2:$BR$51,71,FALSE),"")
... A51: RAP69-050 | B51: =IFERROR(VLOOKUP(A51,'01_ข้อมูลร้าน'!$A$2:$C$51,2,FALSE),"") -> ร้านที่ 50 | C51: =IFERROR(VLOOKUP(A51,'01_ข้อมูลร้าน'!$A$2:$C$51,3,FALSE),"") | D51: =IFERROR(VLOOKUP(A51,'02_ประเมิน50ร้าน'!$A$2:$BR$51,55,FALSE),"") -> 0 | E51: =IFERROR(VLOOKUP(A51,'02_ประเมิน50ร้าน'!$A$2:$BR$51,56,FALSE),"") -> 0 | F51: =IFERROR(VLOOKUP(A51,'02_ประเมิน50ร้าน'!$A$2:$BR$51,57,FALSE),"") -> 0 | G51: =IFERROR(VLOOKUP(A51,'02_ประเมิน50ร้าน'!$A$2:$BR$51,58,FALSE),"") -> 0 | H51: =IFERROR(VLOOKUP(A51,'02_ประเมิน50ร้าน'!$A$2:$BR$51,59,FALSE),"") -> 0 | I51: =IFERROR(VLOOKUP(A51,'02_ประเมิน50ร้าน'!$A$2:$BR$51,60,FALSE),"") -> ยังไม่ประเมิน | J51: =IFERROR(VLOOKUP(A51,'02_ประเมิน50ร้าน'!$A$2:$BR$51,61,FALSE),"") -> ยังไม่ประเมิน | K51: =IFERROR(VLOOKUP(A51,'02_ประเมิน50ร้าน'!$A$2:$BR$51,62,FALSE),"") -> 0 | L51: =IFERROR(VLOOKUP(A51,'02_ประเมิน50ร้าน'!$A$2:$BR$51,63,FALSE),"") -> 0 | M51: =IFERROR(VLOOKUP(A51,'02_ประเมิน50ร้าน'!$A$2:$BR$51,64,FALSE),"") -> 0 | N51: =IFERROR(VLOOKUP(A51,'02_ประเมิน50ร้าน'!$A$2:$BR$51,65,FALSE),"") -> 0 | O51: =IFERROR(VLOOKUP(A51,'02_ประเมิน50ร้าน'!$A$2:$BR$51,66,FALSE),"") -> 0 | P51: =IFERROR(VLOOKUP(A51,'02_ประเมิน50ร้าน'!$A$2:$BR$51,67,FALSE),"") -> 0 | Q51: =IFERROR(VLOOKUP(A51,'02_ประเมิน50ร้าน'!$A$2:$BR$51,68,FALSE),"") -> 0 | R51: =IFERROR(VLOOKUP(A51,'02_ประเมิน50ร้าน'!$A$2:$BR$51,69,FALSE),"") -> 0 | S51: =IF(D51=0,"กรอกคะแนนประเมินก่อน",IF(H51>0,"ตรวจข้อคะแนน 0-1 และจัดทำแผน 7/30/90 วัน","ติดตามพัฒนาตามมิติที่คะแนนต่ำสุด")) -> กรอกคะแนนประเมินก่อน | T51: =IFERROR(VLOOKUP(A51,'02_ประเมิน50ร้าน'!$A$2:$BR$51,71,FALSE),"")

Sheet 04_Dashboard
A1: THAI-RAP Dashboard สรุปประเมินร้าน 50 ร้าน
A2: KPI | B2: ค่า | C2: คำอธิบาย
A3: จำนวนร้านทั้งหมด | B3: =COUNTA('03_สรุปคะแนน'!$A$2:$A$51) -> 50 | C3: จำนวนรหัสร้าน
A4: กรอกครบ 50 ข้อ | B4: =COUNTIF('03_สรุปคะแนน'!$D$2:$D$51,1) -> 39 | C4: ร้านที่กรอกครบ
A5: คะแนนถ่วงน้ำหนักเฉลี่ย | B5: =AVERAGEIF('03_สรุปคะแนน'!$D$2:$D$51,">0",'03_สรุปคะแนน'!$G$2:$G$51) -> 0.63890774 | C5: เฉพาะร้านที่มีคะแนน
A6: จำนวน Red Flag ทั้งหมด | B6: =SUM('03_สรุปคะแนน'!$H$2:$H$51) -> 358 | C6: คะแนน 0-1
A7: ร้านเร่งแก้ไข | B7: =COUNTIF('03_สรุปคะแนน'!$I$2:$I$51,"เร่งแก้ไข") -> 9 | C7: คะแนนถ่วงน้ำหนักต่ำกว่า 50%
A9: มิติ | B9: ชื่อมิติ | C9: คะแนนเฉลี่ย | D9: น้ำหนัก | E9: จำนวนข้อ
A10: 1 | B10: คุณภาพอาหารและนวัตกรรมเมนู | C10: =AVERAGE('03_สรุปคะแนน'!K$2:K$51) -> 0.50785714 | D10: 0.12 | E10: 7
A11: 2 | B11: ความปลอดภัยอาหารและมาตรฐาน | C11: =AVERAGE('03_สรุปคะแนน'!L$2:L$51) -> 0.48857143 | D11: 0.15 | E11: 7
A12: 3 | B12: แบรนด์และโมเดลธุรกิจ | C12: =AVERAGE('03_สรุปคะแนน'!M$2:M$51) -> 0.51833333 | D12: 0.1 | E12: 6
A13: 4 | B13: การตลาดและฐานลูกค้า | C13: =AVERAGE('03_สรุปคะแนน'!N$2:N$51) -> 0.49 | D13: 0.13 | E13: 7
A14: 5 | B14: การเงิน ต้นทุน และกำไร | C14: =AVERAGE('03_สรุปคะแนน'!O$2:O$51) -> 0.50285714 | D14: 0.2 | E14: 7
A15: 6 | B15: ระบบปฏิบัติการร้านและการบริการ | C15: =AVERAGE('03_สรุปคะแนน'!P$2:P$51) -> 0.50357143 | D15: 0.18 | E15: 7
A16: 7 | B16: เครือข่าย วัตถุดิบ และห่วงโซ่อุปทาน | C16: =AVERAGE('03_สรุปคะแนน'!Q$2:Q$51) -> 0.535 | D16: 0.05 | E16: 5
A17: 8 | B17: ความพร้อมเติบโตและเข้าร่วมโครงการ | C17: =AVERAGE('03_สรุปคะแนน'!R$2:R$51) -> 0.62 | D17: 0.07 | E17: 4
A19: ลำดับ | B19: รหัสร้าน | C19: ชื่อร้าน | D19: คะแนนถ่วงน้ำหนัก | E19: ระดับรวม | F19: Red Flag
A20: 1 | B20: {=IFERROR(INDEX('03_สรุปคะแนน'!$A$2:$A$51,MATCH(LARGE('03_สรุปคะแนน'!$G$2:$G$51,A20),'03_สรุปคะแนน'!$G$2:$G$51,0)),"")} -> RAP69-022 | C20: =IFERROR(VLOOKUP(B20,'03_สรุปคะแนน'!$A$2:$I$51,2,FALSE),"") -> หมึกสดริมเล | D20: =IFERROR(VLOOKUP(B20,'03_สรุปคะแนน'!$A$2:$I$51,7,FALSE),"") -> 0.925625 | E20: =IFERROR(VLOOKUP(B20,'03_สรุปคะแนน'!$A$2:$I$51,9,FALSE),"") -> ดีมาก | F20: =IFERROR(VLOOKUP(B20,'03_สรุปคะแนน'!$A$2:$I$51,8,FALSE),"") -> 2
A21: 2 | B21: {=IFERROR(INDEX('03_สรุปคะแนน'!$A$2:$A$51,MATCH(LARGE('03_สรุปคะแนน'!$G$2:$G$51,A21),'03_สรุปคะแนน'!$G$2:$G$51,0)),"")} -> RAP69-037 | C21: =IFERROR(VLOOKUP(B21,'03_สรุปคะแนน'!$A$2:$I$51,2,FALSE),"") -> จันทรโภชนา | D21: =IFERROR(VLOOKUP(B21,'03_สรุปคะแนน'!$A$2:$I$51,7,FALSE),"") -> 0.88741071 | E21: =IFERROR(VLOOKUP(B21,'03_สรุปคะแนน'!$A$2:$I$51,9,FALSE),"") -> ดีมาก | F21: =IFERROR(VLOOKUP(B21,'03_สรุปคะแนน'!$A$2:$I$51,8,FALSE),"") -> 0
A22: 3 | B22: {=IFERROR(INDEX('03_สรุปคะแนน'!$A$2:$A$51,MATCH(LARGE('03_สรุปคะแนน'!$G$2:$G$51,A22),'03_สรุปคะแนน'!$G$2:$G$51,0)),"")} -> RAP69-006 | C22: =IFERROR(VLOOKUP(B22,'03_สรุปคะแนน'!$A$2:$I$51,2,FALSE),"") -> ร้านอีสานเฮาส์ (304 ปราจีนบุรี) | D22: =IFERROR(VLOOKUP(B22,'03_สรุปคะแนน'!$A$2:$I$51,7,FALSE),"") -> 0.87107143 | E22: =IFERROR(VLOOKUP(B22,'03_สรุปคะแนน'!$A$2:$I$51,9,FALSE),"") -> ดีมาก | F22: =IFERROR(VLOOKUP(B22,'03_สรุปคะแนน'!$A$2:$I$51,8,FALSE),"") -> 2
A23: 4 | B23: {=IFERROR(INDEX('03_สรุปคะแนน'!$A$2:$A$51,MATCH(LARGE('03_สรุปคะแนน'!$G$2:$G$51,A23),'03_สรุปคะแนน'!$G$2:$G$51,0)),"")} -> RAP69-036 | C23: =IFERROR(VLOOKUP(B23,'03_สรุปคะแนน'!$A$2:$I$51,2,FALSE),"") -> Garagecafechan | D23: =IFERROR(VLOOKUP(B23,'03_สรุปคะแนน'!$A$2:$I$51,7,FALSE),"") -> 0.82095238 | E23: =IFERROR(VLOOKUP(B23,'03_สรุปคะแนน'!$A$2:$I$51,9,FALSE),"") -> ดีมาก | F23: =IFERROR(VLOOKUP(B23,'03_สรุปคะแนน'!$A$2:$I$51,8,FALSE),"") -> 2
A24: 5 | B24: {=IFERROR(INDEX('03_สรุปคะแนน'!$A$2:$A$51,MATCH(LARGE('03_สรุปคะแนน'!$G$2:$G$51,A24),'03_สรุปคะแนน'!$G$2:$G$51,0)),"")} -> RAP69-040 | C24: =IFERROR(VLOOKUP(B24,'03_สรุปคะแนน'!$A$2:$I$51,2,FALSE),"") -> จิน ข้าวมันไก่สไตล์สิงคโปร์ | D24: =IFERROR(VLOOKUP(B24,'03_สรุปคะแนน'!$A$2:$I$51,7,FALSE),"") -> 0.8058631 | E24: =IFERROR(VLOOKUP(B24,'03_สรุปคะแนน'!$A$2:$I$51,9,FALSE),"") -> ดีมาก | F24: =IFERROR(VLOOKUP(B24,'03_สรุปคะแนน'!$A$2:$I$51,8,FALSE),"") -> 4
A25: 6 | B25: {=IFERROR(INDEX('03_สรุปคะแนน'!$A$2:$A$51,MATCH(LARGE('03_สรุปคะแนน'!$G$2:$G$51,A25),'03_สรุปคะแนน'!$G$2:$G$51,0)),"")} -> RAP69-032 | C25: =IFERROR(VLOOKUP(B25,'03_สรุปคะแนน'!$A$2:$I$51,2,FALSE),"") -> ร้านคดข้าว | D25: =IFERROR(VLOOKUP(B25,'03_สรุปคะแนน'!$A$2:$I$51,7,FALSE),"") -> 0.80505952 | E25: =IFERROR(VLOOKUP(B25,'03_สรุปคะแนน'!$A$2:$I$51,9,FALSE),"") -> ดีมาก | F25: =IFERROR(VLOOKUP(B25,'03_สรุปคะแนน'!$A$2:$I$51,8,FALSE),"") -> 1
A26: 7 | B26: {=IFERROR(INDEX('03_สรุปคะแนน'!$A$2:$A$51,MATCH(LARGE('03_สรุปคะแนน'!$G$2:$G$51,A26),'03_สรุปคะแนน'!$G$2:$G$51,0)),"")} -> RAP69-023 | C26: =IFERROR(VLOOKUP(B26,'03_สรุปคะแนน'!$A$2:$I$51,2,FALSE),"") -> บ้านแมะคาเฟ่ | D26: =IFERROR(VLOOKUP(B26,'03_สรุปคะแนน'!$A$2:$I$51,7,FALSE),"") -> 0.79577381 | E26: =IFERROR(VLOOKUP(B26,'03_สรุปคะแนน'!$A$2:$I$51,9,FALSE),"") -> ดี | F26: =IFERROR(VLOOKUP(B26,'03_สรุปคะแนน'!$A$2:$I$51,8,FALSE),"") -> 3
A27: 8 | B27: {=IFERROR(INDEX('03_สรุปคะแนน'!$A$2:$A$51,MATCH(LARGE('03_สรุปคะแนน'!$G$2:$G$51,A27),'03_สรุปคะแนน'!$G$2:$G$51,0)),"")} -> RAP69-027 | C27: =IFERROR(VLOOKUP(B27,'03_สรุปคะแนน'!$A$2:$I$51,2,FALSE),"") -> Chatrium Golf Resort Soidao | D27: =IFERROR(VLOOKUP(B27,'03_สรุปคะแนน'!$A$2:$I$51,7,FALSE),"") -> 0.79473214 | E27: =IFERROR(VLOOKUP(B27,'03_สรุปคะแนน'!$A$2:$I$51,9,FALSE),"") -> ดี | F27: =IFERROR(VLOOKUP(B27,'03_สรุปคะแนน'!$A$2:$I$51,8,FALSE),"") -> 1
A28: 9 | B28: {=IFERROR(INDEX('03_สรุปคะแนน'!$A$2:$A$51,MATCH(LARGE('03_สรุปคะแนน'!$G$2:$G$51,A28),'03_สรุปคะแนน'!$G$2:$G$51,0)),"")} -> RAP69-004 | C28: =IFERROR(VLOOKUP(B28,'03_สรุปคะแนน'!$A$2:$I$51,2,FALSE),"") -> แฟรนไชส์ก๋วยเตี๋ยวปากหม้อแม่ว่าดี | D28: =IFERROR(VLOOKUP(B28,'03_สรุปคะแนน'!$A$2:$I$51,7,FALSE),"") -> 0.79264881 | E28: =IFERROR(VLOOKUP(B28,'03_สรุปคะแนน'!$A$2:$I$51,9,FALSE),"") -> ดี | F28: =IFERROR(VLOOKUP(B28,'03_สรุปคะแนน'!$A$2:$I$51,8,FALSE),"") -> 3
A29: 10 | B29: {=IFERROR(INDEX('03_สรุปคะแนน'!$A$2:$A$51,MATCH(LARGE('03_สรุปคะแนน'!$G$2:$G$51,A29),'03_สรุปคะแนน'!$G$2:$G$51,0)),"")} -> RAP69-007 | C29: =IFERROR(VLOOKUP(B29,'03_สรุปคะแนน'!$A$2:$I$51,2,FALSE),"") -> ร้านคำนิยม | D29: =IFERROR(VLOOKUP(B29,'03_สรุปคะแนน'!$A$2:$I$51,7,FALSE),"") -> 0.7827381 | E29: =IFERROR(VLOOKUP(B29,'03_สรุปคะแนน'!$A$2:$I$51,9,FALSE),"") -> ดี | F29: =IFERROR(VLOOKUP(B29,'03_สรุปคะแนน'!$A$2:$I$51,8,FALSE),"") -> 3

Sheet 05_QuestionMaster
A1: ข้อ | B1: มิติ | C1: ชื่อมิติ | D1: น้ำหนัก | E1: จำนวนข้อ | F1: คะแนนเต็ม | G1: รายการประเมิน | H1: หลักฐาน/วิธีเก็บ
A2: 1 | B2: 1 | C2: คุณภาพอาหารและนวัตกรรมเมนู | D2: 0.12 | E2: 7 | F2: 28 | G2: ร้านมีเมนูหลักที่ขายดีและลูกค้าจดจำได้ชัดเจน | H2: เมนู/ยอดขาย/รีวิว
A3: 2 | B3: 1 | C3: คุณภาพอาหารและนวัตกรรมเมนู | D3: 0.12 | E3: 7 | F3: 28 | G3: รสชาติอาหารมีความสม่ำเสมอ | H3: ชิม/สังเกต/รีวิว
A4: 3 | B4: 1 | C4: คุณภาพอาหารและนวัตกรรมเมนู | D4: 0.12 | E4: 7 | F4: 28 | G4: มีสูตรมาตรฐานหรือวิธีทำที่บันทึกไว้ | H4: Recipe Card/สูตร
A5: 4 | B5: 1 | C5: คุณภาพอาหารและนวัตกรรมเมนู | D5: 0.12 | E5: 7 | F5: 28 | G5: วัตถุดิบหลักมีคุณภาพและควบคุมความสดได้ | H5: วัตถุดิบ/คลัง/ซัพพลายเออร์
A6: 5 | B6: 1 | C6: คุณภาพอาหารและนวัตกรรมเมนู | D6: 0.12 | E6: 7 | F6: 28 | G6: เมนูมีจุดเด่นหรืออัตลักษณ์เฉพาะของร้าน | H6: เมนู Signature/เรื่องเล่า
A7: 6 | B7: 1 | C7: คุณภาพอาหารและนวัตกรรมเมนู | D7: 0.12 | E7: 7 | F7: 28 | G7: มีการรับฟังความคิดเห็นลูกค้าเพื่อนำมาปรับเมนู | H7: รีวิว/แบบสอบถาม/แชต
A8: 7 | B8: 1 | C8: คุณภาพอาหารและนวัตกรรมเมนู | D8: 0.12 | E8: 7 | F8: 28 | G8: มีโอกาสพัฒนาเมนู Signature หรือเมนูใหม่เพื่อเพิ่มยอดขาย | H8: ทดลองขาย/ต้นทุน/สูตรต้นแบบ
A9: 8 | B9: 2 | C9: ความปลอดภัยอาหารและมาตรฐาน | D9: 0.15 | E9: 7 | F9: 28 | G9: พื้นที่ครัวสะอาด เป็นระเบียบ และแยกโซนเหมาะสม | H9: ภาพครัว/โซนงาน
A10: 9 | B10: 2 | C10: ความปลอดภัยอาหารและมาตรฐาน | D10: 0.15 | E10: 7 | F10: 28 | G10: มีการจัดเก็บวัตถุดิบสด แห้ง และปรุงสุกอย่างถูกสุขลักษณะ | H10: ตู้เย็น/ฉลาก/FIFO
A11: 10 | B11: 2 | C11: ความปลอดภัยอาหารและมาตรฐาน | D11: 0.15 | E11: 7 | F11: 28 | G11: เจ้าของร้านหรือพนักงานมีความรู้พื้นฐานด้านสุขอนามัยอาหาร | H11: ใบอบรม/สัมภาษณ์
A12: 11 | B12: 2 | C12: ความปลอดภัยอาหารและมาตรฐาน | D12: 0.15 | E12: 7 | F12: 28 | G12: มีการควบคุมวันหมดอายุของวัตถุดิบ | H12: สติกเกอร์วัน/Stock Card
A13: 12 | B13: 2 | C13: ความปลอดภัยอาหารและมาตรฐาน | D13: 0.15 | E13: 7 | F13: 28 | G13: อุปกรณ์ครัว ภาชนะ และพื้นที่บริการสะอาดพร้อมใช้งาน | H13: อุปกรณ์/ตารางทำความสะอาด
... A51: 50 | B51: 8 | C51: ความพร้อมเติบโตและเข้าร่วมโครงการ | D51: 0.07 | E51: 4 | F51: 16 | G51: ร้านมีเป้าหมายการพัฒนาภายใน 3-6 เดือน เช่น เพิ่มยอดขาย ลดต้นทุน ปรับเมนู ทำแบรนด์ หรือขยายช่องทางขาย | H51: Goal Sheet/OKR/IDP

Sheet 06_Lists
A1: คะแนน | B1: รอบ | C1: ประเภทร้าน
A2: 0 | B2: T0 | C2: อาหารไทย
A3: 1 | B3: T1 | C3: อาหารทะเล
A4: 2 | B4: T2 | C4: คาเฟ่
A5: 3 | B5: T3 | C5: เดลิเวอรี
A6: 4 | B6: T4 | C6: Catering
C7: อื่น ๆ

Sheet 07_Prompt
A1: Prompt สำหรับใช้กับ AI เพื่อช่วยกรอก ตรวจ และสรุปข้อมูลร้านจากไฟล์ Excel
A3: Prompt
A4: คุณคือผู้ช่วยวิเคราะห์ข้อมูลโครงการ THAI-RAP Restaurant Survival Diagnostic System งานของคุณ: 1) อ่านไฟล์ Excel ที่แนบ ซึ่งมีข้อมูลร้าน 50 ร้าน และแบบประเมินร้านอาหาร 50 ข้อ ตาม 8 มิติ 2) ตรวจความครบถ้วนของข้อมูลในชีต 01_ข้อมูลร้าน และ 02_ประเมิน50ร้าน 3) สรุปผลรายร้านจากชีต 03_สรุปคะแนน เป็นภาษาไทยสำหรับ PMO/Assessor/Mentor 4) ระบุร้านที่มี Red Flag สูงสุด พร้อมข้อที่ควรแก้ไขเร่งด่วน 5) เสนอแผนพัฒนา 7/30/90 วันต่อร้าน โดยอิงจากมิติที่คะแนนต่ำสุด 6) สรุปภาพรวม 50 ร้าน เช่น คะแนนเฉลี่ย มิติที่อ่อนที่สุด มิติที่แข็งแรงที่สุด จำนวนร้านที่กรอกครบ และประเด็นร่วมที่พบมากที่สุด กติกา: - คะแนนแต่ละข้ออยู่ในช่วง 0-4 เท่านั้น - คะแนน 0-1 ให้ถือเป็นประเด็นเสี่ยง/ต้องแก้ไข - ไม่เดาข้อมูล หากข้อมูลไม่ครบให้บอกว่า “ข้อมูลไม่เพียงพอ” - ใช้ข้อมูลจากชีตในไฟล์เท่านั้น ไม่แต่งข้อมูลร้านเพิ่มเอง รูปแบบผลลัพธ์: A) Executive Summary ภาพรวม 50 ร้าน ไม่เกิน 10 บรรทัด B) ตาราง Top 10 ร้านที่ต้องเร่งช่วยเหลือ: รหัสร้าน, ชื่อร้าน, คะแนนถ่วงน้ำหนัก, Red Flag, มิติอ่อนสุด, คำแนะนำเร่งด่วน C) สรุปรายร้าน: จุดแข็ง 3 ข้อ, จุดอ่อน 3 ข้อ, Red Flag, แผน 7/30/90 วัน D) ข้อเสนอสำหรับทีมโครงการ: กิจกรรมอบรม/โค้ช/ลงพื้นที่ที่ควรจัดลำดับก่อน
